Workbook

Sheet FactuScore (2)
A1: Facturación por Score (S/MM) | AM1: PRIMA | AN1: 12.704389 | AO1: 12.641761 | AP1: 12.529264 | AQ1: 12.452429 | AR1: 12.386583 | AS1: 12.291931 | AT1: 12.225291 | AU1: 12.187898 | AV1: 12.095706 | AW1: 12.104614 | AX1: 12.11684 | AY1: 12.113452 | AZ1: 12.119329 | BA1: 12.128399
AN2: 0.43347127 | AO2: 0.42569774 | AP2: 0.42743296 | AQ2: 0.4277685 | AR2: 0.43118991 | AS2: 0.43786192 | AT2: 0.44086771 | AU2: 0.44326811 | AV2: 0.44415135 | AW2: 0.44279495 | AX2: 0.44055663 | AY2: 0.44072213 | AZ2: 0.43817748 | BA2: 0.43386385
A3: ANTERIOR | AM3: CONSUMO | AO3: 0.041959101 | AP3: 0.038380481 | AQ3: 0.037440381 | AR3: 0.037099111 | AS3: 0.039131966 | AT3: 0.039801473 | AU3: 0.039978124 | AV3: 0.038100903 | AW3: 0.038573972 | AX3: 0.038596267 | AY3: 0.038911516 | AZ3: 0.038713609 | BA3: 0.038606916
AM4: Mto Desembolsado (S/MM) | AO4: 0.009813428 | AP4: 0.0094731906 | AQ4: 0.0085771272 | AR4: 0.0080991818 | AS4: 0.0072980043 | AT4: 0.0065455917 | AU4: 0.0063050191 | AV4: 0.005541759 | AW4: 0.0054600621 | AX4: 0.0053969281 | AY4: 0.0053617356 | AZ4: 0.0052988301 | BA4: 0.0051806663
AS5: Plan Yellow
A6: Facturación | B6: 202101 | C6: 202102 | D6: 202103 | E6: 202104 | F6: 202105 | G6: 202106 | H6: 202107-Proy | I6: Jun - May | AS6: 202101 | AT6: 202102 | AU6: 202103
A7: MUY ALTO | B7: 256.59138 | C7: 217.4677 | D7: 317.36218 | E7: 294.6018 | F7: 346.1021 | G7: 314.83821 | H7: =+H$13*(#REF!/#REF!) -> #REF! | I7: =G7-F7 -> -31.263891 | AS7: 256.59138 | AT7: 217.4677 | AU7: 295.04113
A8: ALTO | B8: 128.30226 | C8: 119.71832 | D8: 177.25392 | E8: 165.10622 | F8: 174.62132 | G8: 158.85011 | H8: =+H$13*(#REF!/#REF!) -> #REF! | I8: =G8-F8 -> -15.771208 | AS8: 128.30226 | AT8: 119.71832 | AU8: 146.97315
A9: MEDIO | B9: 64.892364 | C9: 59.756773 | D9: 86.713302 | E9: 81.92946 | F9: 85.355396 | G9: 83.628558 | H9: =+H$13*(#REF!/#REF!) -> #REF! | I9: =G9-F9 -> -1.726838 | AS9: 64.892364 | AT9: 59.756773 | AU9: 75.779706
A10: BAJO | B10: 97.969837 | C10: 92.706152 | D10: 128.28817 | E10: 121.28794 | F10: 135.66866 | G10: 138.66339 | H10: =+H$13*(#REF!/#REF!) -> #REF! | I10: =G10-F10 -> 2.9947286 | AS10: 97.969837 | AT10: 92.706152 | AU10: 115.03886
A11: MUY BAJO | B11: 36.105297 | C11: 36.376225 | D11: 48.339105 | E11: 43.697523 | F11: 50.39221 | G11: 56.175929 | H11: =+H$13*(#REF!/#REF!) -> #REF! | I11: =G11-F11 -> 5.7837193 | AS11: 36.105297 | AT11: 36.376225 | AU11: 43.332879
A12: RECHAZO | B12: 9.8998813 | C12: 10.061747 | D12: 12.516528 | E12: 9.7740536 | F12: 11.120408 | G12: 11.091556 | H12: =+H$13*(#REF!/#REF!) -> #REF! | I12: =G12-F12 -> -0.028852226 | AS12: 9.8998813 | AT12: 10.067113 | AU12: 13.834277
A13: Total | B13: =+SUM(B7:B12) -> 593.76102 | C13: =+SUM(C7:C12) -> 536.08691 | D13: =+SUM(D7:D12) -> 770.4732 | E13: 716.397 | F13: 815.0871 | G13: 776.05889 | H13: 845.97688 | I13: =G13-F13 -> -39.028209 | AS13: =+SUM(AS7:AS12) -> 593.76102 | AT13: =+SUM(AT7:AT12) -> 536.09228 | AU13: =+SUM(AU7:AU12) -> 690
A16: Pesos | B16: 202101 | C16: 202102 | D16: 202103 | E16: 202104 | F16: 202105 | G16: 202106 | H16: 202107-Proy | AS16: 202101 | AT16: 202102 | AU16: 202103
A17: MUY ALTO | B17: =+B7/B$13 -> 0.43214588 | C17: =+C7/C$13 -> 0.40565755 | D17: =+D7/D$13 -> 0.41190553 | E17: 0.41122702 | F17: =+F7/F$13 -> 0.42461977 | G17: =+G7/G$13 -> 0.40568855 | H17: =+H7/H$13 -> #REF! | AS17: =+AS7/AS$13 -> 0.43214588 | AT17: =+AT7/AT$13 -> 0.40565349 | AU17: =+AU7/AU$13 -> 0.42759584
A18: ALTO | B18: =+B8/B$13 -> 0.21608401 | C18: =+C8/C$13 -> 0.22331885 | D18: =+D8/D$13 -> 0.23005852 | E18: 0.23046749 | F18: =+F8/F$13 -> 0.21423639 | G18: =+G8/G$13 -> 0.20468822 | H18: =+H8/H$13 -> #REF! | AS18: =+AS8/AS$13 -> 0.21608401 | AT18: =+AT8/AT$13 -> 0.22331662 | AU18: =+AU8/AU$13 -> 0.21300456
A19: MEDIO | B19: =+B9/B$13 -> 0.10929037 | C19: =+C9/C$13 -> 0.11146844 | D19: =+D9/D$13 -> 0.11254551 | E19: 0.11436321 | F19: =+F9/F$13 -> 0.10471936 | G19: =+G9/G$13 -> 0.10776058 | H19: =+H9/H$13 -> #REF! | AS19: =+AS9/AS$13 -> 0.10929037 | AT19: =+AT9/AT$13 -> 0.11146733 | AU19: =+AU9/AU$13 -> 0.10982566
A20: BAJO | B20: =+B10/B$13 -> 0.16499877 | C20: =+C10/C$13 -> 0.1729312 | D20: =+D10/D$13 -> 0.16650568 | E20: 0.16930269 | F20: =+F10/F$13 -> 0.16644683 | G20: =+G10/G$13 -> 0.17867638 | H20: =+H10/H$13 -> #REF! | AS20: =+AS10/AS$13 -> 0.16499877 | AT20: =+AT10/AT$13 -> 0.17292947 | AU20: =+AU10/AU$13 -> 0.16672298
A21: MUY BAJO | B21: =+B11/B$13 -> 0.060807792 | C21: =+C11/C$13 -> 0.067855088 | D21: =+D11/D$13 -> 0.062739502 | E21: 0.06099624 | F21: =+F11/F$13 -> 0.061824325 | G21: =+G11/G$13 -> 0.072386167 | H21: =+H11/H$13 -> #REF! | AS21: =+AS11/AS$13 -> 0.060807792 | AT21: =+AT11/AT$13 -> 0.067854409 | AU21: =+AU11/AU$13 -> 0.062801274
A22: RECHAZO | B22: =+B12/B$13 -> 0.016673175 | C22: =+C12/C$13 -> 0.018768873 | D22: =+D12/D$13 -> 0.016245247 | E22: 0.013643348 | F22: =+F12/F$13 -> 0.013643215 | G22: =+G12/G$13 -> 0.014292158 | H22: =+H12/H$13 -> #REF! | AS22: =+AS12/AS$13 -> 0.016673175 | AT22: =+AT12/AT$13 -> 0.018778694 | AU22: =+AU12/AU$13 -> 0.020049677
A24: MUY ALTO+ALTO | B24: =+B17+B18 -> 0.64822989 | C24: =+C17+C18 -> 0.6289764 | D24: =+D17+D18 -> 0.64196405 | E24: =+E17+E18 -> 0.64169451 | F24: =+F17+F18 -> 0.63885616 | G24: =+G17+G18 -> 0.61037677 | H24: =+H17+H18 -> #REF! | AS24: =+AS17+AS18 -> 0.64822989 | AT24: =+AT17+AT18 -> 0.6289701 | AU24: =+AU17+AU18 -> 0.6406004
AM25: CONSUMO | AN25: 0.045843633 | AO25: 0.041959101 | AP25: 0.038380481 | AQ25: 0.037440381 | AR25: 0.037099111 | AS25: 0.039131966 | AT25: 0.039801473 | AU25: 0.039978124 | AV25: 0.038100903 | AW25: 0.038573972 | AX25: 0.038596267 | AY25: 0.038911516 | AZ25: 0.038713609 | BA25: 0.038606916
A26: Factu Procesada | AM26: Mto Desembolsado (S/MM) | AN26: 0.0095787131 | AO26: 0.009813428 | AP26: 0.0094731906 | AQ26: 0.0085771272 | AR26: 0.0080991818 | AS26: 0.0072980043 | AT26: 0.0065455917 | AU26: 0.0063050191 | AV26: 0.005541759 | AW26: 0.0054600621 | AX26: 0.0053969281 | AY26: 0.0053617356 | AZ26: 0.0052988301 | BA26: 0.0051806663
B28: 202101 | C28: 202102 | D28: 202103 | E28: 202104 | F28: 202105 | G28: 202106 | H28: 202107 | I28: 202108 | J28: 202109 | K28: 202110 | L28: 202111 | M28: 202112 | N28: 202201 | O28: 202202 | P28: 202203 | Q28: 202004 | R28: 202005 | S28: 202206 | T28: 202207 | U28: 202208 | V28: 202209 | W28: 202210 | X28: 202211 | Y28: 202212 | Z28: 202301 | AA28: 202302 | AB28: 202303 Av | AC28: 202303 Proy | AM28: TRX | AN28: 202211 | AO28: 202212 | AP28: 202301 | AQ28: 202302 | AR28: 202303 | AS28: 202304 | AT28: 202305 | AU28: 202306 | AV28: 202307 | AW28: 202308 | AX28: 202309 | AY28: 202310 | AZ28: 202311 | BA28: 202312
A29: MUY ALTO | B29: 257.11812 | C29: 218.31236 | D29: 306.5895 | E29: 304.75928 | F29: 355.64639 | G29: 352.99305 | H29: 420.09653 | I29: 414.51929 | J29: 437.55442 | K29: 450.58582 | L29: 542.37331 | M29: 551.76712 | N29: 495.2257 | O29: 504.59368 | P29: 585.45418 | Q29: 541.69101 | R29: 607.55044 | S29: 561.50284 | T29: 541.56301 | U29: 676.88539 | V29: 570.70913 | W29: 621.03499 | X29: 617.33303 | Y29: 644.06054 | Z29: =+Z60 -> 397.26262 | AC29: =+$AC$35*(Z29/$Y$35) -> 376.30967 | AM29: MUY ALTO | AN29: 6.2755359e+08 | AO29: 6.5081066e+08 | AP29: 5.9598517e+08 | AQ29: 6.0798585e+08 | AR29: 6.6969555e+08 | AS29: 6.3314237e+08 | AT29: 6.8172059e+08 | AU29: 6.4413377e+08 | AV29: 6.8881266e+08 | AW29: 6.92271e+08 | AX29: 6.5647175e+08 | AY29: 6.9709406e+08 | AZ29: 7.2307837e+08 | BA29: 7.6045668e+08
A30: ALTO | B30: 128.76692 | C30: 119.77027 | D30: 179.51381 | E30: 161.99113 | F30: 179.53743 | G30: 170.43719 | H30: 209.70944 | I30: 215.13464 | J30: 214.4942 | K30: 221.13981 | L30: 272.90378 | M30: 281.17183 | N30: 255.1388 | O30: 252.5513 | P30: 296.53019 | Q30: 263.53671 | R30: 296.27304 | S30: 281.93083 | T30: 271.05906 | U30: 351.70207 | V30: 303.44104 | W30: 331.2232 | X30: 336.4268 | Y30: 350.99244 | Z30: =+Z57 -> 262.23898 | AC30: =+$AC$35*(Z30/$Y$35) -> 248.40763 | AM30: ALTO | AN30: 3.5864836e+08 | AO30: 3.895421e+08 | AP30: 3.5776337e+08 | AQ30: 3.62824e+08 | AR30: 3.9519204e+08 | AS30: 3.6807705e+08 | AT30: 3.9458192e+08 | AU30: 3.6938394e+08 | AV30: 3.9255238e+08 | AW30: 3.958199e+08 | AX30: 3.7665789e+08 | AY30: 3.9990339e+08 | AZ30: 4.1977541e+08 | BA30: 4.5002862e+08
A31: MEDIO | B31: 65.110978 | C31: 59.483426 | D31: 89.717292 | E31: 76.486415 | F31: 87.381582 | G31: 82.270583 | H31: 96.660888 | I31: 103.52093 | J31: 99.196516 | K31: 104.46973 | L31: 126.71351 | M31: 130.59912 | N31: 126.35603 | O31: 129.42605 | P31: 149.35837 | Q31: 129.0711 | R31: 150.65258 | S31: 141.22135 | T31: 135.66445 | U31: 171.79711 | V31: 150.48327 | W31: 164.6418 | X31: 166.96185 | Y31: 174.19049 | Z31: =+Z59 -> 140.77577 | AC31: =+$AC$35*(Z31/$Y$35) -> 133.35079 | AM31: MEDIO | AN31: 1.6468708e+08 | AO31: 1.8614339e+08 | AP31: 1.6955178e+08 | AQ31: 1.7677536e+08 | AR31: 1.9499582e+08 | AS31: 1.782129e+08 | AT31: 1.8986801e+08 | AU31: 1.8170857e+08 | AV31: 1.9713108e+08 | AW31: 2.0181652e+08 | AX31: 1.9722807e+08 | AY31: 2.10513e+08 | AZ31: 2.2109495e+08 | BA31: 2.3974194e+08
A32: BAJO | B32: 98.598311 | C32: 91.399719 | D32: 131.65943 | E32: 116.97523 | F32: 127.61457 | G32: 117.20631 | H32: 132.91553 | I32: 147.08075 | J32: 133.26239 | K32: 142.09797 | L32: 174.69552 | M32: 179.17834 | N32: 168.78928 | O32: 171.62193 | P32: 201.95276 | Q32: 173.2128 | R32: 201.31582 | S32: 194.18984 | T32: 186.17407 | U32: 238.65555 | V32: 208.62821 | W32: 222.09163 | X32: 229.75868 | Y32: 239.70611 | Z32: =+Z58 -> 103.69091 | AC32: =+$AC$35*(Z32/$Y$35) -> 98.221903 | AM32: BAJO | AN32: 2.1661358e+08 | AO32: 2.2316281e+08 | AP32: 2.0431157e+08 | AQ32: 2.0830673e+08 | AR32: 2.2305124e+08 | AS32: 1.9941694e+08 | AT32: 2.0847784e+08 | AU32: 1.906646e+08 | AV32: 2.0467184e+08 | AW32: 2.0466137e+08 | AX32: 1.9418437e+08 | AY32: 2.0417095e+08 | AZ32: 2.1361735e+08 | BA32: 2.2577807e+08
A33: MUY BAJO | B33: 36.262 | C33: 36.13715 | D33: 50.419139 | E33: 44.437661 | F33: 49.529513 | G33: 41.368257 | H33: 45.159665 | I33: 52.95658 | J33: 42.645179 | K33: 44.639406 | L33: 56.299005 | M33: 52.065923 | N33: 50.036829 | O33: 53.269351 | P33: 63.242932 | Q33: 53.61645 | R33: 64.397725 | S33: 61.298051 | T33: 58.749585 | U33: 75.195287 | V33: 65.006428 | W33: 68.425065 | X33: 70.917681 | Y33: 73.988071 | Z33: =+Z61 -> 61.335084 | AC33: =+$AC$35*(Z33/$Y$35) -> 58.100068 | AM33: MUY BAJO | AN33: 66369649 | AO33: 64147462 | AP33: 53515286 | AQ33: 53213882 | AR33: 57619876 | AS33: 56584290 | AT33: 61545636 | AU33: 58094095 | AV33: 59088833 | AW33: 60307016 | AX33: 57512149 | AY33: 61546687 | AZ33: 63885011 | BA33: 67668433
A34: RECHAZO | B34: 9.9305897 | C34: 10.017097 | D34: 12.897199 | E34: 10.917682 | F34: 11.772249 | G34: 9.0450333 | H34: 10.358663 | I34: 12.469981 | J34: 8.7733015 | K34: 9.4036092 | L34: 11.899275 | M34: 10.387041 | N34: 9.799368 | O34: 11.493934 | P34: 13.770645 | Q34: 11.851935 | R34: 14.017439 | S34: 13.701073 | T34: 12.659305 | U34: 16.352861 | V34: 10.126501 | W34: 9.1623331 | X34: 10.296273 | Y34: 10.742051 | Z34: =+Z62 -> 34.638224 | AC34: =+$AC$35*(Z34/$Y$35) -> 32.81129 | AM34: RECHAZO | AN34: 13867484 | AO34: 15002860 | AP34: 13208811 | AQ34: 12190641 | AR34: 12579112 | AS34: 10552815 | AT34: 10121550 | AU34: 9162120.2 | AV34: 8594443.9 | AW34: 8536327.3 | AX34: 8041941.9 | AY34: 8480704.2 | AZ34: 8744103.9 | BA34: 9080434.6
A35: Total | B35: 595.78692 | C35: 535.12003 | D35: 770.79637 | E35: 715.5674 | F35: 811.48173 | G35: 774.53675 | H35: 914.91202 | I35: 945.68217 | J35: 935.926 | K35: =+SUM(K29:K34) -> 972.33634 | L35: =+SUM(L29:L34) -> 1184.8844 | M35: =SUM(M29:M34) -> 1205.1694 | N35: =SUM(N29:N34) -> 1105.346 | O35: =SUM(O29:O34) -> 1122.9562 | P35: =SUM(P29:P34) -> 1310.3091 | Q35: =SUM(Q29:Q34) -> 1172.98 | R35: =SUM(R29:R34) -> 1334.207 | S35: =SUM(S29:S34) -> 1253.844 | T35: =SUM(T29:T34) -> 1205.8695 | ... X35: =SUM(X29:X34) -> 1431.6943 | Y35: 1493.6797 | Z35: =SUM(Z29:Z34) -> 999.94158 | AC35: 1414.8981 | AM35: Total | AN35: 1.4477397e+09 | AO35: 1.5288093e+09 | AP35: 1.394336e+09 | AQ35: 1.4212965e+09 | AR35: 1.5531336e+09 | AS35: 1.4459864e+09 | AT35: 1.5463156e+09 | AU35: 1.4531471e+09 | AV35: 1.5508512e+09 | AW35: 1.5634121e+09 | AX35: 1.4900962e+09 | AY35: 1.5817088e+09 | AZ35: 1.6501952e+09 | BA35: 1.7527542e+09
AE36: (Para Power Bi)
B37: 202101 | C37: 202102 | D37: 202103 | E37: 202104 | F37: 202105 | G37: 202106 | H37: 202107 | I37: 202108 | J37: 202109 | K37: 202110 | L37: 202111 | M37: 202112 | N37: 202201 | O37: 202202 | P37: 202203 | Q37: 202004 | R37: 202005 | S37: 202206 | T37: 202207 | U37: 202208 | V37: 202209 | W37: 202210 | X37: =+X28 -> 202211 | Y37: =+Y28 -> 202212 | Z37: =+Z28 -> 202301 | AC37: =+AC28 -> 202303 Proy | AE37: PROYEC ENERO | AM37: PPTO | AN37: 202211 | AO37: 202212 | AP37: 202301 | AQ37: 202302 | AR37: 202302
A38: MUY ALTO | B38: =B29/B$35 -> 0.43156054 | C38: =C29/C$35 -> 0.40796896 | D38: =D29/D$35 -> 0.3977568 | E38: =E29/E$35 -> 0.42589877 | F38: =F29/F$35 -> 0.4382679 | G38: =G29/G$35 -> 0.45574732 | H38: =+H29/H$35 -> 0.45916604 | I38: =+I29/I$35 -> 0.43832834 | J38: =+J29/J$35 -> 0.46750963 | K38: =+K29/K$35 -> 0.4634053 | L38: =L29/$L$35 -> 0.45774365 | M38: =M29/$M$35 -> 0.45783367 | N38: =N29/$N$35 -> 0.44802776 | O38: =O29/$O$35 -> 0.44934403 | P38: =P29/P$35 -> 0.44680617 | Q38: =Q29/Q$35 -> 0.46180754 | R38: =R29/R$35 -> 0.45536444 | S38: =S29/S$35 -> 0.44782513 | T38: =T29/T$35 -> 0.44910582 | U38: =U29/U$35 -> 0.44223871 | V38: =V29/V$35 -> 0.43619038 | W38: =W29/W$35 -> 0.43840476 | X38: =X29/$X$35 -> 0.43119053 | Y38: =Y29/$Y$35 -> 0.43119053 | Z38: =Z29/$Z$35 -> 0.39728583 | AC38: =+Z38 -> 0.39728583 | AE38: 0.429 | AM38: MUY ALTO | AN38: 0.43347127 | AO38: 0.42569774 | AP38: 0.42743296 | AQ38: 0.4277685 | AR38: 0.43118991 | AS38: 0.43786192 | AT38: 0.44086771 | AU38: 0.44326811 | AV38: 0.44415135 | AW38: 0.44279495 | AX38: 0.44055663 | AY38: 0.44072213 | AZ38: 0.43817748 | BA38: 0.43386385
A39: ALTO | B39: =B30/B$35 -> 0.21612915 | C39: =C30/C$35 -> 0.22381946 | D39: =D30/D$35 -> 0.23289395 | E39: =E30/E$35 -> 0.22638137 | F39: =F30/F$35 -> 0.22124642 | G39: =G30/G$35 -> 0.22005049 | H39: =+H30/H$35 -> 0.22921268 | I39: =+I30/I$35 -> 0.22749148 | J39: =+J30/J$35 -> 0.22917859 | K39: =+K30/K$35 -> 0.22743139 | L39: =L30/$L$35 -> 0.23032101 | M39: =M30/$M$35 -> 0.23330482 | N39: =N30/$N$35 -> 0.23082257 | O39: =O30/$O$35 -> 0.22489861 | P39: =P30/$P$35 -> 0.22630553 | Q39: =Q30/Q$35 -> 0.22467281 | R39: =R30/R$35 -> 0.22205927 | S39: =S30/S$35 -> 0.2248532 | T39: =T30/T$35 -> 0.22478308 | U39: =U30/U$35 -> 0.22978228 | V39: =V30/V$35 -> 0.2319186 | W39: =W30/W$35 -> 0.23381908 | X39: =X30/$X$35 -> 0.23498507 | Y39: =Y30/$Y$35 -> 0.23498507 | Z39: =Z30/$Z$35 -> 0.2622543 | AC39: =+Z39 -> 0.2622543 | AE39: 0.236 | AM39: ALTO | AN39: 0.24772986 | AO39: 0.25480098 | AP39: 0.25658333 | AQ39: 0.25527679 | AR39: 0.25444819 | AS39: 0.25455085 | AT39: 0.25517555 | AU39: 0.25419584 | AV39: 0.25312059 | AW39: 0.25317694 | AX39: 0.25277422 | AY39: 0.25282997 | AZ39: 0.25437925 | BA39: 0.25675513
A40: MEDIO | B40: =B31/B$35 -> 0.10928568 | C40: =C31/C$35 -> 0.11115903 | D40: =D31/D$35 -> 0.11639558 | E40: =E31/E$35 -> 0.10688918 | F40: =F31/F$35 -> 0.10768152 | G40: =G31/G$35 -> 0.10621908 | H40: =+H31/H$35 -> 0.10565047 | I40: =+I31/I$35 -> 0.10946694 | J40: =+J31/J$35 -> 0.10598756 | K40: =+K31/K$35 -> 0.10744197 | L40: =L31/$L$35 -> 0.10694167 | M40: =M31/$M$35 -> 0.10836578 | N40: =N31/$N$35 -> 0.11431355 | O40: =O31/$O$35 -> 0.11525476 | P40: =P31/$P$35 -> 0.11398713 | Q40: =Q31/Q$35 -> 0.11003691 | R40: =R31/R$35 -> 0.11291544 | S40: =S31/S$35 -> 0.11263072 | T40: =T31/T$35 -> 0.11250343 | U40: =U31/U$35 -> 0.11224254 | V40: =V31/V$35 -> 0.11501368 | W40: =W31/W$35 -> 0.11622493 | X40: =X31/$X$35 -> 0.11661837 | Y40: =Y31/$Y$35 -> 0.11661837 | Z40: =Z31/$Z$35 -> 0.140784 | AC40: =+Z40 -> 0.140784 | AE40: 0.122 | AM40: MEDIO | AN40: 0.11375462 | AO40: 0.1217571 | AP40: 0.12160038 | AQ40: 0.12437614 | AR40: 0.12554993 | AS40: 0.1232466 | AT40: 0.12278736 | AU40: 0.12504486 | AV40: 0.12711153 | AW40: 0.12908721 | AX40: 0.13235929 | AY40: 0.13309213 | AZ40: 0.13398109 | BA40: 0.13678013
A41: BAJO | B41: =B32/B$35 -> 0.16549257 | C41: =C32/C$35 -> 0.17080228 | D41: =D32/D$35 -> 0.17080962 | E41: =E32/E$35 -> 0.163472 | F41: =F32/F$35 -> 0.15726117 | G41: =G32/G$35 -> 0.1513244 | H41: =+H32/H$35 -> 0.14527685 | I41: =+I32/I$35 -> 0.15552873 | J41: =+J32/J$35 -> 0.1423856 | K41: =+K32/K$35 -> 0.14614076 | L41: =L32/$L$35 -> 0.14743677 | M41: =M32/$M$35 -> 0.14867482 | N41: =N32/$N$35 -> 0.15270266 | O41: =O32/$O$35 -> 0.15283047 | P41: =P32/$P$35 -> 0.15412605 | Q41: =Q32/Q$35 -> 0.14766902 | R41: =R32/R$35 -> 0.15088799 | S41: =S32/S$35 -> 0.1548756 | T41: =T32/T$35 -> 0.1543899 | U41: =U32/U$35 -> 0.15592407 | V41: =V32/V$35 -> 0.15945359 | W41: =W32/W$35 -> 0.15678026 | X41: =X32/$X$35 -> 0.16048026 | Y41: =Y32/$Y$35 -> 0.16048026 | Z41: =Z32/$Z$35 -> 0.10369696 | AC41: =+Z41 -> 0.10369696 | AE41: 0.157 | AM41: BAJO | AN41: 0.1496219 | AO41: 0.14597164 | AP41: 0.14652966 | AQ41: 0.14656107 | AR41: 0.14361368 | AS41: 0.13791066 | AT41: 0.13482231 | AU41: 0.13120805 | AV41: 0.13197387 | AW41: 0.13090686 | AX41: 0.13031667 | AY41: 0.12908251 | AZ41: 0.12944975 | BA41: 0.12881331
A42: MUY BAJO | B42: =B33/B$35 -> 0.060864041 | C42: =C33/C$35 -> 0.067530925 | D42: =D33/D$35 -> 0.06541175 | E42: =E33/E$35 -> 0.062101294 | F42: =F33/F$35 -> 0.061035894 | G42: =G33/G$35 -> 0.053410321 | H42: =+H33/H$35 -> 0.049359571 | I42: =+I33/I$35 -> 0.055998285 | J42: =+J33/J$35 -> 0.045564691 | K42: =+K33/K$35 -> 0.045909429 | L42: =L33/$L$35 -> 0.047514344 | M42: =M33/$M$35 -> 0.043202163 | N42: =N33/$N$35 -> 0.045268024 | O42: =O33/$O$35 -> 0.047436711 | P42: =P33/$P$35 -> 0.048265659 | Q42: =Q33/Q$35 -> 0.045709603 | R42: =R33/R$35 -> 0.048266666 | S42: =S33/S$35 -> 0.048888101 | T42: =T33/T$35 -> 0.048719688 | U42: =U33/U$35 -> 0.049128357 | V42: =V33/V$35 -> 0.049684116 | W42: =W33/W$35 -> 0.048303035 | X42: =X33/$X$35 -> 0.049534094 | Y42: =Y33/$Y$35 -> 0.049534094 | Z42: =Z33/$Z$35 -> 0.061338667 | AC42: =+Z42 -> 0.061338667 | AE42: 0.047 | AM42: MUY BAJO | AN42: 0.045843633 | AO42: 0.041959101 | AP42: 0.038380481 | AQ42: 0.037440381 | AR42: 0.037099111 | AS42: 0.039131966 | AT42: 0.039801473 | AU42: 0.039978124 | AV42: 0.038100903 | AW42: 0.038573972 | AX42: 0.038596267 | AY42: 0.038911516 | AZ42: 0.038713609 | BA42: 0.038606916
A43: RECHAZO | B43: =B34/B$35 -> 0.016668022 | C43: =C34/C$35 -> 0.018719346 | D43: =D34/D$35 -> 0.016732303 | E43: =E34/E$35 -> 0.015257378 | F43: =F34/F$35 -> 0.014507103 | G43: =G34/G$35 -> 0.011677991 | H43: =+H34/H$35 -> 0.011322032 | I43: =+I34/I$35 -> 0.013186228 | J43: =+J34/J$35 -> 0.0093739264 | K43: =+K34/K$35 -> 0.0096711486 | L43: =L34/$L$35 -> 0.010042562 | M43: =M34/$M$35 -> 0.0086187396 | N43: =N34/$N$35 -> 0.0088654304 | O43: =O34/$O$35 -> 0.010235424 | P43: =P34/$P$35 -> 0.010509463 | Q43: =Q34/Q$35 -> 0.010104123 | R43: =R34/R$35 -> 0.010506195 | S43: =S34/S$35 -> 0.010927255 | T43: =T34/T$35 -> 0.010498072 | U43: =U34/U$35 -> 0.010684036 | V43: =V34/V$35 -> 0.0077396385 | W43: =W34/W$35 -> 0.0064679294 | X43: =X34/$X$35 -> 0.0071916696 | Y43: =Y34/$Y$35 -> 0.0071916696 | Z43: =Z34/$Z$35 -> 0.034640248 | AC43: =+Z43 -> 0.034640248 | AE43: =100%-SUM(AE38:AE42) -> 0.009 | AM43: RECHAZO | AN43: 0.0095787131 | AO43: 0.009813428 | AP43: 0.0094731906 | AQ43: 0.0085771272 | AR43: 0.0080991818 | AS43: 0.0072980043 | AT43: 0.0065455917 | AU43: 0.0063050191 | AV43: 0.005541759 | AW43: 0.0054600621 | AX43: 0.0053969281 | AY43: 0.0053617356 | AZ43: 0.0052988301 | BA43: 0.0051806663
AE44: =SUM(AE38:AE43) -> 1
A45: MUY ALTO+ALTO | B45: =B38+B39 -> 0.64768969 | C45: =C38+C39 -> 0.63178842 | D45: =D38+D39 -> 0.63065075 | E45: =E38+E39 -> 0.65228015 | F45: =F38+F39 -> 0.65951432 | G45: =G38+G39 -> 0.67579781 | H45: =+H38+H39 -> 0.68837872 | I45: =+I38+I39 -> 0.66581982 | J45: =+J38+J39 -> 0.69668822 | K45: =+K38+K39 -> 0.6908367 | L45: =+L38+L39 -> 0.68806466 | M45: =M38+M39 -> 0.69113849 | N45: =N38+N39 -> 0.67885033 | O45: =O38+O39 -> 0.67424264 | P45: =P38+P39 -> 0.6731117 | Q45: =Q38+Q39 -> 0.68648034 | R45: =R38+R39 -> 0.67742371 | S45: =S38+S39 -> 0.67267832 | T45: =T38+T39 -> 0.67388891 | ... Z45: =Z38+Z39 -> 0.65954013 | AC45: =AC38+AC39 -> 0.65954013 | AN45: PPTO - REAL | AO45: PPTO - REAL | AP45: PPTO - REAL | AQ45: PPTO - REAL
A46: MEDIO + BAJO | B46: =B40+B41 -> 0.27477825 | C46: =C40+C41 -> 0.28196131 | D46: =D40+D41 -> 0.2872052 | E46: =E40+E41 -> 0.27036118 | F46: =F40+F41 -> 0.26494269 | G46: =G40+G41 -> 0.25754349 | H46: =H40+H41 -> 0.25092732 | I46: =I40+I41 -> 0.26499567 | ... Z46: =Z40+Z41 -> 0.24448096 | AC46: =AC40+AC41 -> 0.24448096 | AM46: MUY ALTO | AN46: =AN38-X38 -> 0.0022807455 | AO46: =AO38-Y38 -> -0.005492787 | AP46: =AP38-AP54 -> -0.001567036 | AQ46: =AQ38-AQ54 -> -0.0012315046
A47: MUY BAJO + RECHAZO | B47: =B42+B43 -> 0.077532064 | C47: =C42+C43 -> 0.08625027 | D47: =D42+D43 -> 0.082144054 | E47: =E42+E43 -> 0.077358672 | F47: =F42+F43 -> 0.075542997 | G47: =G42+G43 -> 0.065088312 | H47: =H42+H43 -> 0.060681602 | I47: =I42+I43 -> 0.069184514 | ... Z47: =Z42+Z43 -> 0.095978915 | AC47: =AC42+AC43 -> 0.095978915 | AM47: ALTO | AN47: =AN39-X39 -> 0.012744782 | AO47: =AO39-Y39 -> 0.019815906 | AP47: =AP39-AP55 -> 0.020583331 | AQ47: =AQ39-AQ55 -> 0.017276787
AM48: MEDIO | AN48: =AN40-X40 -> -0.0028637494 | AO48: =AO40-Y40 -> 0.0051387352 | AP48: =AP40-AP56 -> -0.00039962241 | AQ48: =AQ40-AQ56 -> 0.0023761375
AM49: BAJO | AN49: =AN41-X41 -> -0.01085836 | AO49: =AO41-Y41 -> -0.014508619 | AP49: =AP41-AP57 -> -0.010470345 | AQ49: =AQ41-AQ57 -> -0.010438929
A50: VAR VERDE | L50: =L45-#REF! -> #REF! | M50: =M45-L45 -> 0.0030738337 | N50: =N45-M45 -> -0.01228816 | O50: =O45-N45 -> -0.0046076934 | P50: =P45-O45 -> -0.0011309415 | Q50: =Q45-P45 -> 0.013368646 | R50: =R45-Q45 -> -0.0090566361 | S50: =S45-R45 -> -0.0047453849 | T50: =T45-S45 -> 0.0012105838 | ... Y50: =Y45-X45 -> 0 | Z50: =Z45-X45 -> -0.0066354784 | AC50: =AC45-V45 -> -0.0085688553 | AM50: MUY BAJO | AN50: =AN42-X42 -> -0.0036904615 | AO50: =AO42-Y42 -> -0.0075749935 | AP50: =AP42-AP58 -> -0.0086195188 | AQ50: =AQ42-AQ58 -> -0.0075596188
A51: VAR YELLOW | L51: =L46-#REF! -> #REF! | M51: =M46-L46 -> 0.0026621703 | N51: =N46-M46 -> 0.0099756087 | O51: =O46-N46 -> 0.001069012 | P51: =P46-O46 -> 2.7954354e-05 | Q51: =Q46-P46 -> -0.010407251 | R51: =R46-Q46 -> 0.0060975019 | S51: =S46-R46 -> 0.0037028902 | T51: =T46-S46 -> -0.00061298824 | ... Y51: =Y46-X46 -> 0 | Z51: =Z46-X46 -> -0.032617673 | AC51: =AC46-V46 -> -0.029986306 | AM51: RECHAZO | AN51: =AN43-X43 -> 0.0023870434 | AO51: =AO43-Y43 -> 0.0026217583 | AP51: =AP43-AP59 -> 0.00047319059 | AQ51: =AQ43-AQ59 -> -0.00042287281
L52: =L47-#REF! -> #REF! | M52: =M47-L47 -> -0.005736004 | N52: =N47-M47 -> 0.0023125517 | O52: =O47-N47 -> 0.0035386814 | P52: =P47-O47 -> 0.0011029872 | Q52: =Q47-P47 -> -0.0029613959 | R52: =R47-Q47 -> 0.0029591342 | S52: =S47-R47 -> 0.0010424947 | T52: =T47-S47 -> -0.00059759551 | ... Y52: =Y47-X47 -> 0 | Z52: =Z47-X47 -> 0.039253152 | AC52: =AC47-V47 -> 0.038555161
AP53: PROYEC ENERO | AQ53: PROYEC FEBRERO | AR53: PROYEC FEBRERO
AM54: MUY ALTO | AP54: 0.429 | AQ54: 0.429 | AR54: =AQ54+AS54 -> 0.43242141 | AS54: =AR38-AQ38 -> 0.0034214148
AM55: ALTO | AP55: 0.236 | AQ55: 0.238 | AR55: =AQ55+AS55 -> 0.2371714 | AS55: =AR39-AQ39 -> -0.0008285996
V56: NIVEL | W56: FACTU | Z56: FACTU PRORRATEADA | AM56: MEDIO | AP56: 0.122 | AQ56: 0.122 | AR56: =AQ56+AS56 -> 0.12317379 | AS56: =AR40-AQ40 -> 0.0011737913
U57: 1 | V57: ALTO | W57: 259.81463 | X57: =W57/$W$67 -> 0.2622543 | Y57: =$W$63*X57 -> 2.424348 | Z57: =W57+Y57 -> 262.23898 | AM57: BAJO | AP57: 0.157 | AQ57: 0.157 | AR57: =AQ57+AS57 -> 0.15405261 | AS57: =AR41-AQ41 -> -0.0029473906
U58: 2 | V58: BAJO | W58: 102.7323 | X58: =W58/$W$67 -> 0.10369696 | Y58: =$W$63*X58 -> 0.95860212 | Z58: =W58+Y58 -> 103.69091 | AC58: CODMES | AD58: CA_NIVEL | AE58: CTAS | AM58: MUY BAJO | AP58: 0.047 | AQ58: 0.045 | AR58: =AQ58+AS58 -> 0.04465873 | AS58: =AR42-AQ42 -> -0.00034127047
U59: 3 | V59: MEDIO | W59: 139.47433 | X59: =W59/$W$67 -> 0.140784 | Y59: =$W$63*X59 -> 1.3014444 | Z59: =W59+Y59 -> 140.77577 | AC59: 202203 | AD59: MUY BAJO | AE59: 71599 | AM59: RECHAZO | AP59: =100%-SUM(AP54:AP58) -> 0.009 | AQ59: 0.009 | AR59: =AQ59+AS59 -> 0.0085220546 | AS59: =AR43-AQ43 -> -0.00047794542
U60: 4 | V60: MUY ALTO | W60: 393.59 | X60: =W60/$W$67 -> 0.39728583 | Y60: =$W$63*X60 -> 3.6726151 | Z60: =W60+Y60 -> 397.26262 | AC60: 202203 | AD60: MUY ALTO | AE60: 335911 | AP60: =SUM(AP54:AP59) -> 1 | AQ60: =SUM(AQ54:AQ59) -> 1 | AR60: =SUM(AR54:AR59) -> 1
U61: 5 | V61: MUY BAJO | W61: 60.768053 | X61: =W61/$W$67 -> 0.061338667 | Y61: =$W$63*X61 -> 0.56703084 | Z61: =W61+Y61 -> 61.335084 | AC61: 202203 | AD61: BAJO | AE61: 173582
U62: 6 | V62: RECHAZO | W62: 34.318001 | X62: =W62/$W$67 -> 0.034640248 | Y62: =$W$63*X62 -> 0.3202236 | Z62: =W62+Y62 -> 34.638224 | AC62: 202203 | AD62: MEDIO | AE62: 108873
U63: 7 | W63: 9.2442641 | AC63: 202203 | AD63: RECHAZO | AE63: 35686
W64: =SUM(W57:W63) -> 999.94158 | Z64: =SUM(Z57:Z62) -> 999.94158 | AC64: 202203 | AE64: 32444
AC65: 202203 | AD65: ALTO | AE65: 208184
Q67: VAR VERDE | R67: -0.014981521 | W67: =SUM(W57:W62) -> 990.69732
Q68: VAR YELLOW | R68: 0.0074835229
R69: 0.0074979978
A71: Parque
B72: 202101 | C72: 202102 | D72: 202103 | E72: 202104 | F72: 202105 | G72: 202106 | H72: 202107 | I72: 202108 | J72: 202109 | K72: 202110 | L72: 202111 | M72: 202112 | N72: 202201 | O72: 202202 | P72: 202203 | Q72: 202004 | R72: 202005 | S72: 202206 | T72: 202207 | U72: 202208 | V72: 202209 | W72: 202210 | X72: 202211 | Y72: 202212 | Z72: 202301 | AA72: 202302 | AB72: 202303 Av | AC72: 202303 Proy | AG72: CODMES | AH72: CA_NIVEL | AI72: CTAS | AL72: PARQUE PRORR
A73: MUY ALTO | B73: 255334 | C73: 272491 | D73: 258162 | E73: 247309 | F73: 259643 | G73: 260437 | H73: 293847 | I73: 295725 | J73: 291079 | K73: 319476 | L73: 321366 | M73: 325230 | N73: 329341 | O73: 329341 | P73: 329341 | Q73: 329341 | R73: 329341 | S73: 329341 | T73: 329341 | U73: 329341 | V73: 329341 | W73: 329341 | Z73: =+AK76 -> 119.84613 | AA73: =+$AL76 -> 252535.85 | AB73: 347581.47 | AG73: 202301 | AH73: ALTO | AI73: 244055 | AJ73: =AI73/$AI$80 -> 0.23362169 | AK73: =$AI$79*AJ73 -> 115.87636 | AL73: =+AI73+AK73 -> 244170.88 | AN73: 338651 | AO73: =+AN73/$AO$79 -> 0.33094527
A74: ALTO | B74: 192011 | C74: 194119 | D74: 201766 | E74: 189342 | F74: 183286 | G74: 180017 | H74: 191338 | I74: 197100 | J74: 197611 | K74: 202847 | L74: 204587 | M74: 207237 | N74: 207014 | O74: 207014 | P74: 207014 | Q74: 207014 | R74: 207014 | S74: 207014 | T74: 207014 | U74: 207014 | V74: 207014 | W74: 207014 | Z74: =+AK73 -> 115.87636 | AA74: =+AL73 -> 244170.88 | AB74: 215416.89 | AG74: 202301 | AH74: BAJO | AI74: 152947 | AJ74: =AI74/$AI$80 -> 0.14640854 | AK74: =$AI$79*AJ74 -> 72.618636 | AL74: =+AI74+AK74 -> 153019.62 | AN74: 214089 | AO74: =+AN74/$AO$79 -> 0.20921758
A75: MEDIO | B75: 90893 | C75: 92032 | D75: 94245 | E75: 95443 | F75: 92087 | G75: 92018 | H75: 92761 | I75: 94971 | J75: 97226 | K75: 99460 | L75: 101485 | M75: 103030 | N75: 106932 | O75: 106932 | P75: 106932 | Q75: 106932 | R75: 106932 | S75: 106932 | T75: 106932 | U75: 106932 | V75: 106932 | W75: 106932 | Z75: =+AK75 -> 80.6783 | AA75: =+AL75 -> 170002.68 | AB75: 112655.55 | AG75: 202301 | AH75: MEDIO | AI75: 169922 | AJ75: =AI75/$AI$80 -> 0.16265786 | AK75: =$AI$79*AJ75 -> 80.6783 | AL75: =+AI75+AK75 -> 170002.68 | AN75: 114368 | AO75: =+AN75/$AO$79 -> 0.11176565
A76: BAJO | B76: 156382 | C76: 152603 | D76: 155496 | E76: 159166 | F76: 159728 | G76: 164155 | H76: 147914 | I76: 150716 | J76: 160835 | K76: 156091 | L76: 160090 | M76: 163875 | N76: 170853 | O76: 170853 | P76: 170853 | Q76: 170853 | R76: 170853 | S76: 170853 | T76: 170853 | U76: 170853 | V76: 170853 | W76: 170853 | Z76: =+AK74 -> 72.618636 | AA76: =+AL74 -> 153019.62 | AB76: 179612.72 | AG76: 202301 | AH76: MUY ALTO | AI76: 252416 | AJ76: =AI76/$AI$80 -> 0.24162526 | AK76: =$AI$79*AJ76 -> 119.84613 | AL76: =+AI76+AK76 -> 252535.85 | AN76: 190272 | AO76: =+AN76/$AO$79 -> 0.18594251
A77: MUY BAJO | B77: 83181 | C77: 76036 | D77: 81142 | E77: 77677 | F77: 78946 | G77: 81910 | H77: 66986 | I77: 65034 | J77: 71388 | K77: 62531 | L77: 63947 | M77: 64724 | N77: 69622 | O77: 69622 | P77: 69622 | Q77: 69622 | R77: 69622 | S77: 69622 | T77: 69622 | U77: 69622 | V77: 69622 | W77: 69622 | Z77: =+AK77 -> 51.704344 | AA77: =+AL77 -> 108949.7 | AB77: 74086.546 | AG77: 202301 | AH77: MUY BAJO | AI77: 108898 | AJ77: =AI77/$AI$80 -> 0.10424263 | AK77: =$AI$79*AJ77 -> 51.704344 | AL77: =+AI77+AK77 -> 108949.7 | AN77: 92360 | AO77: =+AN77/$AO$79 -> 0.090258423
A78: RECHAZO | B78: 75013 | C78: 63774 | D78: 57286 | E78: 49653 | F78: 48088 | G78: 44392 | H78: 33454 | I78: 32616 | J78: 31917 | K78: 30382 | L78: 32381 | M78: 33156 | N78: 36829 | O78: 36829 | P78: 36829 | Q78: 36829 | R78: 36829 | S78: 36829 | T78: 36829 | U78: 36829 | V78: 36829 | W78: 36829 | Z78: =+AK78 -> 55.276235 | AA78: =+AL78 -> 116476.28 | AB78: 36925.83 | AG78: 202301 | AH78: RECHAZO | AI78: 116421 | AJ78: =AI78/$AI$80 -> 0.11144402 | AK78: =$AI$79*AJ78 -> 55.276235 | AL78: =+AI78+AK78 -> 116476.28 | AN78: 73544 | AO78: =+AN78/$AO$79 -> 0.071870566
A79: Total | B79: 865356 | C79: 862859 | D79: 865547 | E79: 834530 | F79: 841966 | G79: 841796 | H79: 843933 | I79: 860260 | J79: 878064 | K79: 896706 | L79: 910455 | M79: 930949 | N79: 947275 | O79: 947275 | P79: 947275 | Q79: 947275 | R79: 947275 | S79: 947275 | T79: 947275 | U79: 947275 | V79: 947275 | W79: 947275 | AG79: 202301 | AI79: 496 | AO79: =+SUM(AN73:AN78) -> 1023284
AH80: parcial | AI80: =SUM(AI73:AI78) -> 1044659
AH81: SUM TOT | AI81: =SUM(AI73:AI79) -> 1045155 | AL81: =SUM(AL73:AL78) -> 1045155 | AM81: =SUM(AM73:AM79) -> 0
A82: Factu Trx
B83: 202101 | C83: 202102 | D83: 202103 | E83: 202104 | F83: 202105 | G83: 202106 | H83: 202107 | I83: 202108 | J83: 202109 | K83: 202110 | L83: 202111 | M83: 202112 | N83: 202201 | O83: 202202 | P83: 202203 | Q83: 202004 | R83: 202005 | S83: 202206 | T83: 202207 | U83: 202208 | V83: 202209 | W83: 202210 | AC83: 202210 Pr
A84: MUY ALTO | B84: 2.6120127e+08 | C84: 2.319962e+08 | D84: 3.0313692e+08 | E84: 2.8880408e+08 | F84: 3.4434625e+08 | G84: 3.2751367e+08 | H84: 4.2725467e+08 | I84: 4.2107309e+08 | J84: 4.0831077e+08 | K84: 4.8374386e+08 | L84: 5.0743006e+08 | M84: 5.4908722e+08 | N84: 4.7944017e+08
A85: ALTO | B85: 1.3432666e+08 | C85: 1.1461961e+08 | D85: 1.7053027e+08 | E85: 1.6108148e+08 | F85: 1.7415565e+08 | G85: 1.6467095e+08 | H85: 2.039395e+08 | I85: 2.1358081e+08 | J85: 2.1474293e+08 | K85: 2.3360963e+08 | L85: 2.4629753e+08 | M85: 2.7464709e+08 | N85: 2.4164395e+08
A86: MEDIO | B86: 69527524 | C86: 58537079 | D86: 82994220 | E86: 79825713 | F86: 85367712 | G86: 86331932 | H86: 95722259 | I86: 98557926 | J86: 1.0146543e+08 | K86: 1.1008467e+08 | L86: 1.1432083e+08 | M86: 1.2639333e+08 | N86: 1.1799085e+08
A87: BAJO | B87: 1.0730923e+08 | C87: 86637458 | D87: 1.2362211e+08 | E87: 1.1838139e+08 | F87: 1.3537837e+08 | G87: 1.4360488e+08 | H87: 1.2993272e+08 | I87: 1.3266501e+08 | J87: 1.4221306e+08 | K87: 1.4347297e+08 | L87: 1.4938825e+08 | M87: 1.7200518e+08 | N87: 1.5543142e+08
A88: MUY BAJO | B88: 40231759 | C88: 31503401 | D88: 46610985 | E88: 42507263 | F88: 50243534 | G88: 57731325 | H88: 43097588 | I88: 43133056 | J88: 46100888 | K88: 42603073 | L88: 42978373 | M88: 48840510 | N88: 44658226
A89: RECHAZO | B89: 11147138 | C89: 8305740.6 | D89: 12094178 | E89: 9460446.6 | F89: 11064344 | G89: 11453658 | H89: 8738336 | I89: 9009016.8 | J89: 9309278.1 | K89: 7957734.3 | L89: 8190034.6 | M89: 9780549.5 | N89: 8755935.5
A90: Total | B90: 6.3103209e+08 | C90: 5.3688909e+08 | D90: 7.4886191e+08 | E90: 7.0815111e+08 | F90: 8.130847e+08 | G90: 8.0392091e+08 | H90: 9.2075275e+08 | I90: 9.3467873e+08 | J90: 9.3867429e+08 | K90: 1.037879e+09 | L90: 1.0860317e+09 | M90: 1.2056193e+09 | N90: 1.0642614e+09
A92: Ctas con Cons
B93: 202101 | C93: 202102 | D93: 202103 | E93: 202104 | F93: 202105 | G93: 202106 | H93: 202107 | I93: 202108 | J93: 202109 | K93: 202110 | L93: 202111 | M93: 202112 | N93: 202201 | O93: 202202 | P93: 202203 | Q93: 202004 | R93: 202005 | S93: 202206 | T93: 202207 | U93: 202208 | V93: 202209 | W93: 202210 | AC93: 202210 Pr
A94: MUY ALTO | B94: 170746 | C94: 181130 | D94: 175519 | E94: 173536 | F94: 183862 | G94: 185874 | H94: 215637 | I94: 216413 | J94: 211356 | K94: 237534 | L94: 241464 | M94: 247271 | N94: 249099
A95: ALTO | B95: 107961 | C95: 106629 | D95: 116948 | E95: 118273 | F95: 115338 | G95: 113905 | H95: 123578 | I95: 127641 | J95: 129248 | K95: 134546 | L95: 136841 | M95: 141535 | N95: 139512
A96: MEDIO | B96: 58906 | C96: 58370 | D96: 62867 | E96: 64395 | F96: 63248 | G96: 64430 | H96: 65399 | I96: 67042 | J96: 69299 | K96: 71716 | L96: 73643 | M96: 76367 | N96: 77990
A97: BAJO | B97: 109053 | C97: 103163 | D97: 110757 | E97: 113528 | F97: 117257 | G97: 123618 | H97: 110732 | I97: 112845 | J97: 121920 | K97: 119458 | L97: 122331 | M97: 128229 | N97: 131221
A98: MUY BAJO | B98: 57895 | C98: 51408 | D98: 57858 | E98: 56146 | F98: 59235 | G98: 63249 | H98: 51508 | I98: 49794 | J98: 55317 | K98: 48816 | L98: 49850 | M98: 51458 | N98: 53863
A99: RECHAZO | B99: 26308 | C99: 21359 | D99: 22831 | E99: 19273 | F99: 20603 | G99: 19873 | H99: 16238 | I99: 15189 | J99: 15677 | K99: 13435 | L99: 13794 | M99: 14013 | N99: 14693
A100: Total | B100: 541008 | C100: 531125 | D100: 560475 | E100: 557218 | F100: 575580 | G100: 586215 | H100: 597333 | I100: 608059 | J100: 624836 | K100: 647133 | L100: 659530 | M100: 687435 | N100: 687992
A102: Actividad
B103: 202101 | C103: 202102 | D103: 202103 | E103: 202104 | F103: 202105 | G103: 202106 | H103: 202107 | I103: 202108 | J103: 202109 | K103: 202110 | L103: 202111 | M103: 202112 | N103: 202201 | O103: 202202 | P103: 202203 | Q103: 202004 | R103: 202005 | S103: 202206 | T103: 202207 | U103: 202208 | V103: 202209 | W103: 202210 | AC103: 202210 Pr
A104: MUY ALTO | B104: =+B94/B73 -> 0.66871627 | C104: =+C94/C73 -> 0.6647192 | D104: =+D94/D73 -> 0.6798793 | E104: =+E94/E73 -> 0.70169707 | F104: =+F94/F73 -> 0.70813386 | G104: =+G94/G73 -> 0.71370043 | H104: =+H94/H73 -> 0.73384108 | I104: =+I94/I73 -> 0.73180489 | ... V104: =+V94/V73 -> 0
A105: ALTO | B105: =+B95/B74 -> 0.56226466 | C105: =+C95/C74 -> 0.54929708 | D105: =+D95/D74 -> 0.57962194 | E105: =+E95/E74 -> 0.62465274 | F105: =+F95/F74 -> 0.62927883 | G105: =+G95/G74 -> 0.6327458 | H105: =+H95/H74 -> 0.6458623 | I105: =+I95/I74 -> 0.64759513 | ... V105: =+V95/V74 -> 0
A106: MEDIO | B106: =+B96/B75 -> 0.64808071 | C106: =+C96/C75 -> 0.63423592 | D106: =+D96/D75 -> 0.66705926 | E106: =+E96/E75 -> 0.67469589 | F106: =+F96/F75 -> 0.68682876 | G106: =+G96/G75 -> 0.70018909 | H106: =+H96/H75 -> 0.7050269 | I106: =+I96/I75 -> 0.70592075 | ... V106: =+V96/V75 -> 0
A107: BAJO | B107: =+B97/B76 -> 0.69735008 | C107: =+C97/C76 -> 0.6760221 | D107: =+D97/D76 -> 0.71228199 | E107: =+E97/E76 -> 0.71326791 | F107: =+F97/F76 -> 0.73410423 | G107: =+G97/G76 -> 0.75305656 | H107: =+H97/H76 -> 0.7486242 | I107: =+I97/I76 -> 0.74872608 | ... V107: =+V97/V76 -> 0
A108: MUY BAJO | B108: =+B98/B77 -> 0.69601231 | C108: =+C98/C77 -> 0.67610079 | D108: =+D98/D77 -> 0.71304626 | E108: =+E98/E77 -> 0.7228137 | F108: =+F98/F77 -> 0.75032301 | G108: =+G98/G77 -> 0.77217678 | H108: =+H98/H77 -> 0.76893679 | I108: =+I98/I77 -> 0.76566104 | ... V108: =+V98/V77 -> 0
...

Sheet PyCCuotas
A1: PASE A CUOTAS | H1: CONSUMO EN CUOTAS | N1: VS2 --> | O1: PASE A CUOTAS | V1: CONSUMO EN CUOTAS
A3: CODMES | B3: CA_NIVEL | C3: PONDERADO | D3: FACTU | E3: CLIENTES | H3: CODMES | I3: CA_NIVEL | J3: CLIENTES | K3: PONDCUOTAS | L3: FACTUTOTAL | O3: CODMES | P3: CA_NIVEL | Q3: PONDERADO | R3: FACTU | S3: CLIENTES | V3: CODMES | W3: CA_NIVEL | X3: CLIENTES | Y3: PONDCUOTAS | Z3: FACTUTOTAL
A4: 201901 | B4: MUY ALTO | C4: 16.452513 | D4: 2.0645966 | E4: 1.995 | H4: 201901 | I4: MUY BAJO | J4: 30.134 | K4: 137.10913 | L4: 18.976679 | O4: 201901 | Q4: 5.5413525 | R4: 0.65687864 | S4: 0.997 | V4: 201901 | W4: MUY BAJO | X4: 30.134 | Y4: 137.10913 | Z4: 18.976679
A5: 201901 | B5: MEDIO | C5: 39.682358 | D5: 4.7065481 | E5: 5.93 | H5: 201901 | I5: MUY ALTO | J5: 12.385 | K5: 81.506034 | L5: 9.2961916 | O5: 201901 | P5: RECHAZO | Q5: 16.959445 | R5: 2.2104552 | S5: 4.287 | V5: 201901 | W5: MUY ALTO | X5: 12.385 | Y5: 81.506034 | Z5: 9.2961916
A6: 201901 | C6: 6.1602097 | D6: 0.73054464 | E6: 0.997 | H6: 201901 | I6: ALTO | J6: 23.507 | K6: 160.91692 | L6: 17.553646 | O6: 201901 | P6: ALTO | Q6: 39.166753 | R6: 4.5194896 | S6: 5.178 | V6: 201901 | W6: ALTO | X6: 23.507 | Y6: 160.91692 | Z6: 17.553646
A7: 201901 | B7: MUY BAJO | C7: 45.784871 | D7: 6.0251464 | E7: 9.849 | H7: 201901 | J7: 4.385 | K7: 41.78528 | L7: 4.0141 | O7: 201901 | P7: BAJO | Q7: 52.690141 | R7: 6.7478142 | S7: 10.181 | V7: 201901 | X7: 4.385 | Y7: 41.78528 | Z7: 4.0141
A8: 201901 | B8: RECHAZO | C8: 17.949101 | D8: 2.357181 | E8: 4.287 | H8: 201901 | I8: BAJO | J8: 35.209 | K8: 167.32696 | L8: 22.685224 | O8: 201901 | P8: MEDIO | Q8: 37.667183 | R8: 4.4661819 | S8: 5.93 | V8: 201901 | W8: BAJO | X8: 35.209 | Y8: 167.32696 | Z8: 22.685224
A9: 201901 | B9: BAJO | C9: 56.621809 | D9: 7.1461336 | E9: 10.181 | H9: 201901 | I9: MEDIO | J9: 22.623 | K9: 131.86141 | L9: 15.642626 | O9: 201901 | P9: MUY ALTO | Q9: 15.428183 | R9: 1.9459622 | S9: 1.995 | V9: 201901 | W9: MEDIO | X9: 22.623 | Y9: 131.86141 | Z9: 15.642626
A10: 201901 | B10: ALTO | C10: 41.818508 | D10: 4.7969231 | E10: 5.178 | H10: 201901 | I10: RECHAZO | J10: 12.97 | K10: 44.304894 | L10: 7.2845794 | O10: 201901 | P10: MUY BAJO | Q10: 43.392493 | R10: 5.6970881 | S10: 9.849 | V10: 201901 | W10: RECHAZO | X10: 12.97 | Y10: 44.304894 | Z10: 7.2845794
A11: 201902 | B11: MUY ALTO | C11: 13.668879 | D11: 1.7124848 | E11: 1.886 | H11: 201902 | J11: 5.143 | K11: 54.030457 | L11: 5.0313002 | O11: 201902 | P11: BAJO | Q11: 50.115286 | R11: 5.9485315 | S11: 9.092 | V11: 201902 | X11: 5.143 | Y11: 54.030457 | Z11: 5.0313002
A12: 201902 | B12: RECHAZO | C12: 12.791993 | D12: 1.8553959 | E12: 4.063 | H12: 201902 | I12: MEDIO | J12: 22.975 | K12: 133.82364 | L12: 16.062186 | O12: 201902 | P12: MUY BAJO | Q12: 42.473384 | R12: 5.0282636 | S12: 8.618 | V12: 201902 | W12: MEDIO | X12: 22.975 | Y12: 133.82364 | Z12: 16.062186
A13: 201902 | B13: ALTO | C13: 35.018237 | D13: 4.1651611 | E13: 4.671 | H13: 201902 | I13: ALTO | J13: 23.555 | K13: 154.90828 | L13: 17.390728 | O13: 201902 | P13: RECHAZO | Q13: 12.635149 | R13: 1.8379236 | S13: 4.063 | V13: 201902 | W13: ALTO | X13: 23.555 | Y13: 154.90828 | Z13: 17.390728
A14: 201902 | B14: MEDIO | C14: 40.483279 | D14: 4.3003003 | E14: 5.427 | H14: 201902 | I14: MUY ALTO | J14: 12.744 | K14: 97.907503 | L14: 9.9222693 | O14: 201902 | P14: MEDIO | Q14: 40.125651 | R14: 4.2543399 | S14: 5.427 | V14: 201902 | W14: MUY ALTO | X14: 12.744 | Y14: 97.907503 | Z14: 9.9222693
A15: 201902 | C15: 5.084565 | D15: 0.60611709 | E15: 0.887 | H15: 201902 | I15: MUY BAJO | J15: 30.692 | K15: 134.6666 | L15: 19.502217 | O15: 201902 | Q15: 5.0186661 | R15: 0.59713515 | S15: 0.887 | V15: 201902 | W15: MUY BAJO | X15: 30.692 | Y15: 134.6666 | Z15: 19.502217
A16: 201902 | B16: MUY BAJO | C16: 43.37437 | D16: 5.0926377 | E16: 8.618 | H16: 201902 | I16: BAJO | J16: 35.009 | K16: 168.29381 | L16: 22.858628 | O16: 201902 | P16: ALTO | Q16: 34.510823 | R16: 4.109802 | S16: 4.671 | V16: 201902 | W16: BAJO | X16: 35.009 | Y16: 168.29381 | Z16: 22.858628
A17: 201902 | B17: BAJO | C17: 50.567256 | D17: 6.0079626 | E17: 9.092 | H17: 201902 | I17: RECHAZO | J17: 13.978 | K17: 40.803203 | L17: 7.4170187 | O17: 201902 | P17: MUY ALTO | Q17: 13.515841 | R17: 1.6812577 | S17: 1.886 | V17: 201902 | W17: RECHAZO | X17: 13.978 | Y17: 40.803203 | Z17: 7.4170187
A18: 201903 | B18: MUY BAJO | C18: 44.361215 | D18: 5.4181515 | E18: 8.91 | H18: 201903 | I18: MUY ALTO | J18: 13.49 | K18: 108.06584 | L18: 10.769031 | O18: 201903 | P18: MUY ALTO | Q18: 11.233506 | R18: 1.5317401 | S18: 1.741 | V18: 201903 | W18: MUY ALTO | X18: 13.49 | Y18: 108.06584 | Z18: 10.769031
A19: 201903 | B19: MEDIO | C19: 34.15128 | D19: 3.9592379 | E19: 5.088 | H19: 201903 | I19: MUY BAJO | J19: 35.628 | K19: 165.55103 | L19: 24.349444 | O19: 201903 | P19: RECHAZO | Q19: 13.099976 | R19: 1.8437988 | S19: 4.022 | V19: 201903 | W19: MUY BAJO | X19: 35.628 | Y19: 165.55103 | Z19: 24.349444
A20: 201903 | B20: MUY ALTO | C20: 11.303203 | D20: 1.5427652 | E20: 1.741 | H20: 201903 | J20: 7.53 | K20: 75.805435 | L20: 7.1142283 | O20: 201903 | P20: MEDIO | Q20: 33.760614 | R20: 3.9203165 | S20: 5.088 | V20: 201903 | X20: 7.53 | Y20: 75.805435 | Z20: 7.1142283
A21: 201903 | B21: RECHAZO | C21: 13.188354 | D21: 1.8626167 | E21: 4.022 | H21: 201903 | I21: MEDIO | J21: 25.358 | K21: 160.80613 | L21: 19.485894 | O21: 201903 | Q21: 8.5990666 | R21: 0.87595294 | S21: 1.377 | V21: 201903 | W21: MEDIO | X21: 25.358 | Y21: 160.80613 | Z21: 19.485894
A22: 201903 | C22: 8.660913 | D22: 0.88428285 | E22: 1.377 | H22: 201903 | I22: BAJO | J22: 39.897 | K22: 226.46096 | L22: 30.350779 | O22: 201903 | P22: ALTO | Q22: 34.128198 | R22: 4.0430521 | S22: 4.46 | V22: 201903 | W22: BAJO | X22: 39.897 | Y22: 226.46096 | Z22: 30.350779
A23: 201903 | B23: BAJO | C23: 54.719458 | D23: 6.6102085 | E23: 9.357 | H23: 201903 | I23: ALTO | J23: 25.616 | K23: 197.77605 | L23: 20.661572 | O23: 201903 | P23: BAJO | Q23: 53.680144 | R23: 6.5271495 | S23: 9.357 | V23: 201903 | W23: ALTO | X23: 25.616 | Y23: 197.77605 | Z23: 20.661572
A24: 201903 | B24: ALTO | C24: 34.674453 | D24: 4.0987171 | E24: 4.46 | H24: 201903 | I24: RECHAZO | J24: 15.779 | K24: 50.63542 | L24: 8.8925176 | O24: 201903 | P24: MUY BAJO | Q24: 43.759835 | R24: 5.364319 | S24: 8.91 | V24: 201903 | W24: RECHAZO | X24: 15.779 | Y24: 50.63542 | Z24: 8.8925176
A25: 201904 | B25: RECHAZO | C25: 16.164511 | D25: 2.2609276 | E25: 5.1 | H25: 201904 | J25: 6.725 | K25: 65.141737 | L25: 6.3891292 | O25: 201904 | P25: ALTO | Q25: 40.118264 | R25: 4.6788385 | S25: 5.587 | V25: 201904 | X25: 6.725 | Y25: 65.141737 | Z25: 6.3891292
A26: 201904 | B26: MUY BAJO | C26: 44.788854 | D26: 6.0380137 | E26: 10.532 | H26: 201904 | I26: MUY ALTO | J26: 12.837 | K26: 87.656201 | L26: 9.6211442 | O26: 201904 | P26: MUY BAJO | Q26: 43.584674 | R26: 5.9614512 | S26: 10.532 | V26: 201904 | W26: MUY ALTO | X26: 12.837 | Y26: 87.656201 | Z26: 9.6211442
A27: 201904 | B27: BAJO | C27: 58.185405 | D27: 7.1436001 | E27: 10.073 | H27: 201904 | I27: BAJO | J27: 35.524 | K27: 189.33006 | L27: 25.023598 | O27: 201904 | P27: RECHAZO | Q27: 15.895282 | R27: 2.2357748 | S27: 5.1 | V27: 201904 | W27: BAJO | X27: 35.524 | Y27: 189.33006 | Z27: 25.023598
A28: 201904 | B28: MUY ALTO | C28: 14.899086 | D28: 1.8981191 | E28: 2.067 | H28: 201904 | I28: RECHAZO | J28: 15.949 | K28: 45.098273 | L28: 8.3641918 | O28: 201904 | P28: MUY ALTO | Q28: 14.672339 | R28: 1.8584338 | S28: 2.067 | V28: 201904 | W28: RECHAZO | X28: 15.949 | Y28: 45.098273 | Z28: 8.3641918
A29: 201904 | B29: MEDIO | C29: 42.530903 | D29: 5.1190287 | E29: 6.283 | H29: 201904 | I29: ALTO | J29: 25.103 | K29: 182.54087 | L29: 19.254015 | O29: 201904 | P29: BAJO | Q29: 57.762378 | R29: 7.0814173 | S29: 10.073 | V29: 201904 | W29: ALTO | X29: 25.103 | Y29: 182.54087 | Z29: 19.254015
A30: 201904 | C30: 6.2767083 | D30: 0.82799533 | E30: 1.487 | H30: 201904 | I30: MUY BAJO | J30: 32.697 | K30: 131.91384 | L30: 20.025191 | O30: 201904 | Q30: 6.2312951 | R30: 0.82025554 | S30: 1.487 | V30: 201904 | W30: MUY BAJO | X30: 32.697 | Y30: 131.91384 | Z30: 20.025191
A31: 201904 | B31: ALTO | C31: 41.048809 | D31: 4.7550768 | E31: 5.587 | H31: 201904 | I31: MEDIO | J31: 23.879 | K31: 145.26955 | L31: 17.987598 | O31: 201904 | P31: MEDIO | Q31: 41.533512 | R31: 5.0253742 | S31: 6.283 | V31: 201904 | W31: MEDIO | X31: 23.879 | Y31: 145.26955 | Z31: 17.987598
A32: 201905 | B32: ALTO | C32: 43.183208 | D32: 5.5915011 | E32: 6.788 | H32: 201905 | I32: BAJO | J32: 38.277 | K32: 215.11019 | L32: 28.3706 | O32: 201905 | P32: ALTO | Q32: 42.627248 | R32: 5.5396129 | S32: 6.788 | V32: 201905 | W32: BAJO | X32: 38.277 | Y32: 215.11019 | Z32: 28.3706
A33: 201905 | B33: MUY BAJO | C33: 57.324477 | D33: 7.4355148 | E33: 12.25 | H33: 201905 | I33: RECHAZO | J33: 18.256 | K33: 55.67746 | L33: 9.719385 | O33: 201905 | P33: MUY ALTO | Q33: 13.478114 | R33: 2.1130174 | S33: 2.549 | V33: 201905 | W33: RECHAZO | X33: 18.256 | Y33: 55.67746 | Z33: 9.719385
A34: 201905 | B34: MUY ALTO | C34: 13.55025 | D34: 2.1306112 | E34: 2.549 | H34: 201905 | J34: 5.796 | K34: 50.011206 | L34: 5.4063602 | O34: 201905 | P34: MUY BAJO | Q34: 56.734038 | R34: 7.3704177 | S34: 12.25 | V34: 201905 | X34: 5.796 | Y34: 50.011206 | Z34: 5.4063602
A35: 201905 | B35: RECHAZO | C35: 19.392326 | D35: 2.9035342 | E35: 6.291 | H35: 201905 | I35: MUY BAJO | J35: 35.951 | K35: 159.27446 | L35: 23.681004 | O35: 201905 | P35: MEDIO | Q35: 47.132403 | R35: 5.9404994 | S35: 7.583 | V35: 201905 | W35: MUY BAJO | X35: 35.951 | Y35: 159.27446 | Z35: 23.681004
A36: 201905 | B36: MEDIO | C36: 48.281273 | D36: 6.0335333 | E36: 7.583 | H36: 201905 | I36: ALTO | J36: 27.495 | K36: 173.00963 | L36: 20.898348 | O36: 201905 | P36: BAJO | Q36: 68.98211 | R36: 8.7605619 | S36: 12.189 | V36: 201905 | W36: ALTO | X36: 27.495 | Y36: 173.00963 | Z36: 20.898348
A37: 201905 | B37: BAJO | C37: 69.879207 | D37: 8.8458228 | E37: 12.189 | H37: 201905 | I37: MUY ALTO | J37: 14.532 | K37: 89.844017 | L37: 10.701179 | O37: 201905 | Q37: 6.7161156 | R37: 0.817403 | S37: 1.36 | V37: 201905 | W37: MUY ALTO | X37: 14.532 | Y37: 89.844017 | Z37: 10.701179
A38: 201905 | C38: 6.7996527 | D38: 0.82432462 | E38: 1.36 | H38: 201905 | I38: MEDIO | J38: 26.147 | K38: 166.08539 | L38: 19.804477 | O38: 201905 | P38: RECHAZO | Q38: 19.228486 | R38: 2.8809301 | S38: 6.291 | V38: 201905 | W38: MEDIO | X38: 26.147 | Y38: 166.08539 | Z38: 19.804477
A39: 201906 | B39: MUY ALTO | C39: 17.502309 | D39: 2.2461536 | E39: 2.445 | H39: 201906 | I39: MUY BAJO | J39: 34.761 | K39: 149.2411 | L39: 21.740745 | O39: 201906 | P39: BAJO | Q39: 67.347101 | R39: 8.5110245 | S39: 11.794 | V39: 201906 | W39: MUY BAJO | X39: 34.761 | Y39: 149.2411 | Z39: 21.740745
A40: 201906 | B40: RECHAZO | C40: 19.63499 | D40: 3.1635077 | E40: 6.639 | H40: 201906 | I40: ALTO | J40: 25.625 | K40: 159.90253 | L40: 19.106063 | O40: 201906 | P40: ALTO | Q40: 45.368861 | R40: 5.5687754 | S40: 6.671 | V40: 201906 | W40: ALTO | X40: 25.625 | Y40: 159.90253 | Z40: 19.106063
A41: 201906 | C41: 5.5381387 | D41: 0.7033129 | E41: 1.173 | H41: 201906 | I41: BAJO | J41: 36.637 | K41: 181.69185 | L41: 25.804319 | O41: 201906 | P41: MEDIO | Q41: 52.550502 | R41: 5.988895 | S41: 7.32 | V41: 201906 | W41: BAJO | X41: 36.637 | Y41: 181.69185 | Z41: 25.804319
A42: 201906 | B42: ALTO | C42: 49.456793 | D42: 6.0755531 | E42: 6.671 | H42: 201906 | J42: 5.227 | K42: 43.074162 | L42: 4.4432988 | O42: 201906 | Q42: 5.375987 | R42: 0.68455707 | S42: 1.173 | V42: 201906 | X42: 5.227 | Y42: 43.074162 | Z42: 4.4432988
A43: 201906 | B43: MEDIO | C43: 56.553984 | D43: 6.4972659 | E43: 7.32 | H43: 201906 | I43: MUY ALTO | J43: 13.466 | K43: 67.236371 | L43: 8.9498094 | O43: 201906 | P43: RECHAZO | Q43: 17.79223 | R43: 2.8452515 | S43: 6.639 | V43: 201906 | W43: MUY ALTO | X43: 13.466 | Y43: 67.236371 | Z43: 8.9498094
A44: 201906 | B44: BAJO | C44: 74.282594 | D44: 9.4434598 | E44: 11.794 | H44: 201906 | I44: MEDIO | J44: 24.583 | K44: 139.02479 | L44: 18.040904 | O44: 201906 | P44: MUY BAJO | Q44: 54.461684 | R44: 7.1155313 | S44: 12.101 | V44: 201906 | W44: MEDIO | X44: 24.583 | Y44: 139.02479 | Z44: 18.040904
A45: 201906 | B45: MUY BAJO | C45: 60.53162 | D45: 7.8990739 | E45: 12.101 | H45: 201906 | I45: RECHAZO | J45: 18.393 | K45: 47.936156 | L45: 9.1914605 | O45: 201906 | P45: MUY ALTO | Q45: 15.640881 | R45: 2.0330011 | S45: 2.445 | V45: 201906 | W45: RECHAZO | X45: 18.393 | Y45: 47.936156 | Z45: 9.1914605
A46: 201907 | B46: MUY BAJO | C46: 60.783633 | D46: 8.3193829 | E46: 12.187 | H46: 201907 | I46: ALTO | J46: 24.67 | K46: 141.26286 | L46: 17.102708 | O46: 201907 | P46: MUY ALTO | Q46: 17.06951 | R46: 2.3314465 | S46: 2.464 | V46: 201907 | W46: ALTO | X46: 24.67 | Y46: 141.26286 | Z46: 17.102708
A47: 201907 | C47: 6.7268347 | D47: 0.78183788 | E47: 1.244 | H47: 201907 | I47: BAJO | J47: 34.752 | K47: 164.15037 | L47: 22.783131 | O47: 201907 | P47: MUY BAJO | Q47: 55.954617 | R47: 7.6676412 | S47: 12.187 | V47: 201907 | W47: BAJO | X47: 34.752 | Y47: 164.15037 | Z47: 22.783131
A48: 201907 | B48: RECHAZO | C48: 23.405436 | D48: 3.5171235 | E48: 7.213 | H48: 201907 | I48: MEDIO | J48: 23.567 | K48: 129.93197 | L48: 16.362846 | O48: 201907 | P48: RECHAZO | Q48: 21.66174 | R48: 3.2431126 | S48: 7.213 | V48: 201907 | W48: MEDIO | X48: 23.567 | Y48: 129.93197 | Z48: 16.362846
A49: 201907 | B49: MUY ALTO | C49: 18.321725 | D49: 2.5115073 | E49: 2.464 | H49: 201907 | I49: RECHAZO | J49: 18.843 | K49: 46.297651 | L49: 8.1818426 | O49: 201907 | P49: BAJO | Q49: 80.396117 | R49: 9.7865886 | S49: 11.807 | V49: 201907 | W49: RECHAZO | X49: 18.843 | Y49: 46.297651 | Z49: 8.1818426
A50: 201907 | B50: MEDIO | C50: 63.981175 | D50: 7.2246606 | E50: 7.212 | H50: 201907 | J50: 5.779 | K50: 43.53313 | L50: 4.3610312 | O50: 201907 | Q50: 6.4753174 | R50: 0.76815014 | S50: 1.244 | V50: 201907 | X50: 5.779 | Y50: 43.53313 | Z50: 4.3610312
A51: 201907 | B51: ALTO | C51: 53.067592 | D51: 6.6418123 | E51: 6.407 | H51: 201907 | I51: MUY BAJO | J51: 33.122 | K51: 128.32655 | L51: 18.826102 | O51: 201907 | P51: MEDIO | Q51: 58.069916 | R51: 6.6574584 | S51: 7.212 | V51: 201907 | W51: MUY BAJO | X51: 33.122 | Y51: 128.32655 | Z51: 18.826102
A52: 201907 | B52: BAJO | C52: 86.809375 | D52: 10.591549 | E52: 11.807 | H52: 201907 | I52: MUY ALTO | J52: 13.166 | K52: 75.884794 | L52: 9.2895015 | O52: 201907 | P52: ALTO | Q52: 48.893739 | R52: 6.1383244 | S52: 6.407 | V52: 201907 | W52: MUY ALTO | X52: 13.166 | Y52: 75.884794 | Z52: 9.2895015
A53: 201908 | B53: ALTO | C53: 83.23983 | D53: 8.8866643 | E53: 7.806 | H53: 201908 | I53: MEDIO | J53: 23.76 | K53: 125.29319 | L53: 16.02876 | O53: 201908 | P53: BAJO | Q53: 93.621683 | R53: 11.392598 | S53: 13.179 | V53: 201908 | W53: MEDIO | X53: 23.76 | Y53: 125.29319 | Z53: 16.02876
A54: 201908 | B54: MEDIO | C54: 73.002512 | D54: 8.2844619 | E54: 8.359 | H54: 201908 | I54: MUY BAJO | J54: 33.432 | K54: 125.84125 | L54: 18.358026 | O54: 201908 | Q54: 5.6705167 | R54: 0.78167477 | S54: 1.314 | V54: 201908 | W54: MUY BAJO | X54: 33.432 | Y54: 125.84125 | Z54: 18.358026
A55: 201908 | B55: BAJO | C55: 98.002562 | D55: 11.973273 | E55: 13.179 | H55: 201908 | I55: BAJO | J55: 34.906 | K55: 167.942 | L55: 22.41045 | O55: 201908 | P55: MEDIO | Q55: 68.9207 | R55: 7.8805537 | S55: 8.359 | V55: 201908 | W55: BAJO | X55: 34.906 | Y55: 167.942 | Z55: 22.41045
A56: 201908 | B56: MUY ALTO | C56: 26.723919 | D56: 3.4465622 | E56: 3.143 | H56: 201908 | I56: MUY ALTO | J56: 13.713 | K56: 72.200239 | L56: 9.3008302 | O56: 201908 | P56: RECHAZO | Q56: 24.107298 | R56: 3.6321873 | S56: 7.751 | V56: 201908 | W56: MUY ALTO | X56: 13.713 | Y56: 72.200239 | Z56: 9.3008302
A57: 201908 | B57: RECHAZO | C57: 25.74871 | D57: 3.8390552 | E57: 7.751 | H57: 201908 | J57: 5.615 | K57: 49.752129 | L57: 4.6453625 | O57: 201908 | P57: ALTO | Q57: 79.655447 | R57: 8.4982463 | S57: 7.806 | V57: 201908 | X57: 5.615 | Y57: 49.752129 | Z57: 4.6453625
A58: 201908 | C58: 6.2971031 | D58: 0.83191761 | E58: 1.314 | H58: 201908 | I58: ALTO | J58: 25.362 | K58: 148.43606 | L58: 17.711248 | O58: 201908 | P58: MUY BAJO | Q58: 65.395618 | R58: 8.5435007 | S58: 13.425 | V58: 201908 | W58: ALTO | X58: 25.362 | Y58: 148.43606 | Z58: 17.711248
A59: 201908 | B59: MUY BAJO | C59: 68.915483 | D59: 8.9863827 | E59: 13.425 | H59: 201908 | I59: RECHAZO | J59: 18.972 | K59: 46.40762 | L59: 8.1778422 | O59: 201908 | P59: MUY ALTO | Q59: 25.510959 | R59: 3.3009622 | S59: 3.143 | V59: 201908 | W59: RECHAZO | X59: 18.972 | Y59: 46.40762 | Z59: 8.1778422
A60: 201909 | B60: MUY ALTO | C60: 29.042639 | D60: 3.4610998 | E60: 3.203 | H60: 201909 | J60: 4.776 | K60: 43.774153 | L60: 4.0636374 | O60: 201909 | P60: ALTO | Q60: 64.435576 | R60: 7.3714104 | S60: 7.598 | V60: 201909 | X60: 4.776 | Y60: 43.774153 | Z60: 4.0636374
A61: 201909 | C61: 6.7728971 | D61: 0.72658941 | E61: 1.161 | H61: 201909 | I61: MEDIO | J61: 22.81 | K61: 125.38907 | L61: 14.835953 | O61: 201909 | P61: BAJO | Q61: 80.704377 | R61: 9.9722926 | S61: 13.067 | V61: 201909 | W61: MEDIO | X61: 22.81 | Y61: 125.38907 | Z61: 14.835953
A62: 201909 | B62: MUY BAJO | C62: 63.343982 | D62: 8.1721321 | E62: 13.424 | H62: 201909 | I62: MUY ALTO | J62: 13.717 | K62: 70.069219 | L62: 8.7267624 | O62: 201909 | P62: RECHAZO | Q62: 20.829664 | R62: 3.2250517 | S62: 7.937 | V62: 201909 | W62: MUY ALTO | X62: 13.717 | Y62: 70.069219 | Z62: 8.7267624
A63: 201909 | B63: MEDIO | C63: 59.428462 | D63: 6.9831076 | E63: 8.065 | H63: 201909 | I63: MUY BAJO | J63: 31.938 | K63: 111.16192 | L63: 16.919153 | O63: 201909 | Q63: 6.6517564 | R63: 0.71853679 | S63: 1.161 | V63: 201909 | W63: MUY BAJO | X63: 31.938 | Y63: 111.16192 | Z63: 16.919153
A64: 201909 | B64: BAJO | C64: 82.174499 | D64: 10.083301 | E64: 13.067 | H64: 201909 | I64: RECHAZO | J64: 18.46 | K64: 40.470863 | L64: 7.5763573 | O64: 201909 | P64: MUY BAJO | Q64: 62.630505 | R64: 8.0890578 | S64: 13.424 | V64: 201909 | W64: RECHAZO | X64: 18.46 | Y64: 40.470863 | Z64: 7.5763573
A65: 201909 | B65: RECHAZO | C65: 21.09866 | D65: 3.2566789 | E65: 7.937 | H65: 201909 | I65: BAJO | J65: 33.881 | K65: 159.54411 | L65: 20.738401 | O65: 201909 | P65: MEDIO | Q65: 58.511819 | R65: 6.8744066 | S65: 8.065 | V65: 201909 | W65: BAJO | X65: 33.881 | Y65: 159.54411 | Z65: 20.738401
A66: 201909 | B66: ALTO | C66: 65.80916 | D66: 7.4851405 | E66: 7.598 | H66: 201909 | I66: ALTO | J66: 24.982 | K66: 151.16766 | L66: 16.4305 | O66: 201909 | P66: MUY ALTO | Q66: 28.219404 | R66: 3.4070616 | S66: 3.203 | V66: 201909 | W66: ALTO | X66: 24.982 | Y66: 151.16766 | Z66: 16.4305
A67: 201910 | B67: MEDIO | C67: 60.479138 | D67: 7.2787556 | E67: 8.213 | H67: 201910 | I67: RECHAZO | J67: 18.093 | K67: 41.15871 | L67: 7.4672293 | O67: 201910 | P67: MUY ALTO | Q67: 28.085816 | R67: 3.5655344 | S67: 3.403 | V67: 201910 | W67: RECHAZO | X67: 18.093 | Y67: 41.15871 | Z67: 7.4672293
A68: 201910 | B68: MUY BAJO | C68: 63.193364 | D68: 8.2208084 | E68: 13.21 | H68: 201910 | I68: MUY BAJO | J68: 31.828 | K68: 112.10356 | L68: 17.065035 | O68: 201910 | P68: MUY BAJO | Q68: 62.005388 | R68: 8.1341086 | S68: 13.21 | V68: 201910 | W68: MUY BAJO | X68: 31.828 | Y68: 112.10356 | Z68: 17.065035
A69: 201910 | B69: MUY ALTO | C69: 29.346297 | D69: 3.6361122 | E69: 3.403 | H69: 201910 | J69: 4.389 | K69: 34.311078 | L69: 3.5206152 | O69: 201910 | Q69: 5.7807259 | R69: 0.63095058 | S69: 0.997 | V69: 201910 | X69: 4.389 | Y69: 34.311078 | Z69: 3.5206152
A70: 201910 | C70: 5.8552894 | D70: 0.64157345 | E70: 0.997 | H70: 201910 | I70: MEDIO | J70: 23.049 | K70: 125.79615 | L70: 14.808008 | O70: 201910 | P70: BAJO | Q70: 84.190153 | R70: 10.071768 | S70: 13.578 | V70: 201910 | W70: MEDIO | X70: 23.049 | Y70: 125.79615 | Z70: 14.808008
A71: 201910 | B71: BAJO | C71: 86.641218 | D71: 10.227779 | E71: 13.578 | H71: 201910 | I71: MUY ALTO | J71: 14.095 | K71: 76.587974 | L71: 9.0613538 | O71: 201910 | P71: ALTO | Q71: 68.036497 | R71: 7.752247 | S71: 8.027 | V71: 201910 | W71: MUY ALTO | X71: 14.095 | Y71: 76.587974 | Z71: 9.0613538
A72: 201910 | B72: RECHAZO | C72: 21.784861 | D72: 3.350898 | E72: 7.884 | H72: 201910 | I72: BAJO | J72: 34.393 | K72: 152.87207 | L72: 20.825914 | O72: 201910 | P72: MEDIO | Q72: 59.253147 | R72: 7.1819073 | S72: 8.213 | V72: 201910 | W72: BAJO | X72: 34.393 | Y72: 152.87207 | Z72: 20.825914
A73: 201910 | B73: ALTO | C73: 69.174931 | D73: 7.847373 | E73: 8.027 | H73: 201910 | I73: ALTO | J73: 25.187 | K73: 149.35565 | L73: 16.688819 | O73: 201910 | P73: RECHAZO | Q73: 21.008071 | R73: 3.3048635 | S73: 7.884 | V73: 201910 | W73: ALTO | X73: 25.187 | Y73: 149.35565 | Z73: 16.688819
A74: 201911 | C74: 5.868245 | D74: 0.654723 | E74: 0.828 | H74: 201911 | I74: BAJO | J74: 33.653 | K74: 167.78309 | L74: 21.173159 | O74: 201911 | P74: BAJO | Q74: 83.338636 | R74: 10.524939 | S74: 13.892 | V74: 201911 | W74: BAJO | X74: 33.653 | Y74: 167.78309 | Z74: 21.173159
A75: 201911 | B75: MUY BAJO | C75: 64.269297 | D75: 8.6870127 | E75: 12.858 | H75: 201911 | I75: RECHAZO | J75: 16.988 | K75: 37.295732 | L75: 6.8251779 | O75: 201911 | P75: MUY BAJO | Q75: 57.7805 | R75: 7.8044178 | S75: 12.858 | V75: 201911 | W75: RECHAZO | X75: 16.988 | Y75: 37.295732 | Z75: 6.8251779
A76: 201911 | B76: ALTO | C76: 79.768881 | D76: 9.087598 | E76: 8.084 | H76: 201911 | I76: MUY BAJO | J76: 30.479 | K76: 111.57049 | L76: 16.410162 | O76: 201911 | P76: ALTO | Q76: 68.767359 | R76: 8.0892884 | S76: 8.084 | V76: 201911 | W76: MUY BAJO | X76: 30.479 | Y76: 111.57049 | Z76: 16.410162
A77: 201911 | B77: MEDIO | C77: 66.267632 | D77: 8.2253824 | E77: 8.239 | H77: 201911 | I77: MUY ALTO | J77: 13.888 | K77: 113.80684 | L77: 10.879745 | O77: 201911 | Q77: 4.6147441 | R77: 0.52431847 | S77: 0.828 | V77: 201911 | W77: MUY ALTO | X77: 13.888 | Y77: 113.80684 | Z77: 10.879745
A78: 201911 | B78: RECHAZO | C78: 19.470919 | D78: 3.2292155 | E78: 7.292 | H78: 201911 | I78: MEDIO | J78: 22.348 | K78: 141.28061 | L78: 15.79611 | O78: 201911 | P78: MEDIO | Q78: 59.680293 | R78: 7.3913407 | S78: 8.239 | V78: 201911 | W78: MEDIO | X78: 22.348 | Y78: 141.28061 | Z78: 15.79611
A79: 201911 | B79: BAJO | C79: 97.030958 | D79: 11.895616 | E79: 13.892 | H79: 201911 | J79: 3.792 | K79: 45.13301 | L79: 3.6233954 | O79: 201911 | P79: RECHAZO | Q79: 17.520709 | R79: 2.8940528 | S79: 7.292 | V79: 201911 | X79: 3.792 | Y79: 45.13301 | Z79: 3.6233954
A80: 201911 | B80: MUY ALTO | C80: 30.565972 | D80: 4.080158 | E80: 3.326 | H80: 201911 | I80: ALTO | J80: 24.615 | K80: 179.39594 | L80: 18.394413 | O80: 201911 | P80: MUY ALTO | Q80: 26.722374 | R80: 3.5726073 | S80: 3.326 | V80: 201911 | W80: ALTO | X80: 24.615 | Y80: 179.39594 | Z80: 18.394413
A81: 201912 | B81: MUY BAJO | C81: 77.734223 | D81: 10.415121 | E81: 13.527 | H81: 201912 | I81: MEDIO | J81: 25.882 | K81: 156.10293 | L81: 19.166169 | O81: 201912 | Q81: 4.7326385 | R81: 0.58008603 | S81: 0.848 | V81: 201912 | W81: MEDIO | X81: 25.882 | Y81: 156.10293 | Z81: 19.166169
A82: 201912 | B82: MEDIO | C82: 86.858644 | D82: 9.9432959 | E82: 8.706 | H82: 201912 | I82: ALTO | J82: 28.259 | K82: 204.62241 | L82: 22.218999 | O82: 201912 | P82: MUY BAJO | Q82: 66.202352 | R82: 8.8666455 | S82: 13.527 | V82: 201912 | W82: ALTO | X82: 28.259 | Y82: 204.62241 | Z82: 22.218999
A83: 201912 | B83: MUY ALTO | C83: 36.692866 | D83: 4.3155195 | E83: 3.368 | H83: 201912 | I83: BAJO | J83: 38.788 | K83: 195.08985 | L83: 26.793716 | O83: 201912 | P83: BAJO | Q83: 91.685281 | R83: 11.86954 | S83: 14.517 | V83: 201912 | W83: BAJO | X83: 38.788 | Y83: 195.08985 | Z83: 26.793716
A84: 201912 | C84: 6.2954247 | D84: 0.70908685 | E84: 0.848 | H84: 201912 | J84: 4.424 | K84: 54.183151 | L84: 4.5639898 | O84: 201912 | P84: MUY ALTO | Q84: 30.443855 | R84: 3.6948533 | S84: 3.368 | V84: 201912 | X84: 4.424 | Y84: 54.183151 | Z84: 4.5639898
A85: 201912 | B85: BAJO | C85: 107.63231 | D85: 13.992573 | E85: 14.517 | H85: 201912 | I85: MUY ALTO | J85: 16.304 | K85: 119.05857 | L85: 12.959734 | O85: 201912 | P85: MEDIO | Q85: 74.801008 | R85: 8.4609953 | S85: 8.706 | V85: 201912 | W85: MUY ALTO | X85: 16.304 | Y85: 119.05857 | Z85: 12.959734
A86: 201912 | B86: ALTO | C86: 80.862731 | D86: 9.7046375 | E86: 8.124 | H86: 201912 | I86: MUY BAJO | J86: 35.112 | K86: 127.57257 | L86: 20.137982 | O86: 201912 | P86: RECHAZO | Q86: 21.271554 | R86: 3.2498565 | S86: 7.291 | V86: 201912 | W86: MUY BAJO | X86: 35.112 | Y86: 127.57257 | Z86: 20.137982
A87: 201912 | B87: RECHAZO | C87: 24.504496 | D87: 3.7353841 | E87: 7.291 | H87: 201912 | I87: RECHAZO | J87: 18.562 | K87: 43.073115 | L87: 8.0718779 | O87: 201912 | P87: ALTO | Q87: 67.052307 | R87: 8.2625956 | S87: 8.124 | V87: 201912 | W87: RECHAZO | X87: 18.562 | Y87: 43.073115 | Z87: 8.0718779
A88: 202001 | B88: RECHAZO | C88: 18.322729 | D88: 2.8071896 | E88: 6.369 | H88: 202001 | J88: 3.359 | K88: 40.274879 | L88: 3.4822375 | O88: 202001 | P88: MUY BAJO | Q88: 59.860462 | R88: 8.172046 | S88: 13.479 | V88: 202001 | X88: 3.359 | Y88: 40.274879 | Z88: 3.4822375
A89: 202001 | C89: 7.0562253 | D89: 0.60731246 | E89: 0.735 | H89: 202001 | I89: MUY ALTO | J89: 13.645 | K89: 88.600941 | L89: 9.9605823 | O89: 202001 | P89: ALTO | Q89: 72.58609 | R89: 8.6780322 | S89: 8.666 | V89: 202001 | W89: MUY ALTO | X89: 13.645 | Y89: 88.600941 | Z89: 9.9605823
A90: 202001 | B90: BAJO | C90: 93.990133 | D90: 11.796997 | E90: 15.06 | H90: 202001 | I90: MUY BAJO | J90: 30.1 | K90: 116.10615 | L90: 16.90726 | O90: 202001 | P90: RECHAZO | Q90: 18.073918 | R90: 2.7727001 | S90: 6.369 | V90: 202001 | W90: MUY BAJO | X90: 30.1 | Y90: 116.10615 | Z90: 16.90726
A91: 202001 | B91: ALTO | C91: 73.992911 | D91: 8.8351903 | E91: 8.666 | H91: 202001 | I91: ALTO | J91: 24.44 | K91: 166.40247 | L91: 17.904246 | O91: 202001 | P91: BAJO | Q91: 92.488778 | R91: 11.646319 | S91: 15.06 | V91: 202001 | W91: ALTO | X91: 24.44 | Y91: 166.40247 | Z91: 17.904246
A92: 202001 | B92: MUY BAJO | C92: 61.451921 | D92: 8.3144386 | E92: 13.479 | H92: 202001 | I92: RECHAZO | J92: 14.45 | K92: 35.136738 | L92: 6.1646119 | O92: 202001 | Q92: 6.9995557 | R92: 0.60121962 | S92: 0.735 | V92: 202001 | W92: RECHAZO | X92: 14.45 | Y92: 35.136738 | Z92: 6.1646119
A93: 202001 | B93: MUY ALTO | C93: 28.156899 | D93: 3.738261 | E93: 3.427 | H93: 202001 | I93: BAJO | J93: 34.138 | K93: 172.15877 | L93: 22.383314 | O93: 202001 | P93: MEDIO | Q93: 73.076402 | R93: 8.1725697 | S93: 8.955 | V93: 202001 | W93: BAJO | X93: 34.138 | Y93: 172.15877 | Z93: 22.383314
A94: 202001 | B94: MEDIO | C94: 73.92929 | D94: 8.2843745 | E94: 8.955 | H94: 202001 | I94: MEDIO | J94: 22.57 | K94: 132.45927 | L94: 15.653239 | O94: 202001 | P94: MUY ALTO | Q94: 27.398611 | R94: 3.6606676 | S94: 3.427 | V94: 202001 | W94: MEDIO | X94: 22.57 | Y94: 132.45927 | Z94: 15.653239
A95: 202002 | B95: MEDIO | C95: 65.543984 | D95: 7.6581936 | E95: 8.613 | H95: 202002 | J95: 3.016 | K95: 38.413373 | L95: 3.2386928 | O95: 202002 | P95: MUY ALTO | Q95: 28.796832 | R95: 3.7308049 | S95: 3.523 | V95: 202002 | X95: 3.016 | Y95: 38.413373 | Z95: 3.2386928
A96: 202002 | B96: MUY ALTO | C96: 29.120162 | D96: 3.7684788 | E96: 3.523 | H96: 202002 | I96: MUY ALTO | J96: 14.39 | K96: 83.933876 | L96: 10.653999 | O96: 202002 | P96: MUY BAJO | Q96: 55.536344 | R96: 7.4730837 | S96: 12.53 | V96: 202002 | W96: MUY ALTO | X96: 14.39 | Y96: 83.933876 | Z96: 10.653999
A97: 202002 | B97: ALTO | C97: 74.353213 | D97: 8.2531146 | E97: 8.233 | H97: 202002 | I97: RECHAZO | J97: 14.371 | K97: 32.079768 | L97: 5.8738912 | O97: 202002 | P97: MEDIO | Q97: 64.33858 | R97: 7.553484 | S97: 8.613 | V97: 202002 | W97: RECHAZO | X97: 14.371 | Y97: 32.079768 | Z97: 5.8738912
A98: 202002 | C98: 5.1404959 | D98: 0.4651617 | E98: 0.56 | H98: 202002 | I98: BAJO | J98: 35.196 | K98: 158.71696 | L98: 22.751954 | O98: 202002 | P98: RECHAZO | Q98: 15.809923 | R98: 2.3826912 | S98: 5.747 | V98: 202002 | W98: BAJO | X98: 35.196 | Y98: 158.71696 | Z98: 22.751954
A99: 202002 | B99: MUY BAJO | C99: 56.735635 | D99: 7.5815904 | E99: 12.53 | H99: 202002 | I99: MEDIO | J99: 23.47 | K99: 127.9112 | L99: 16.561023 | O99: 202002 | P99: BAJO | Q99: 80.596101 | R99: 10.418259 | S99: 14.15 | V99: 202002 | W99: MEDIO | X99: 23.47 | Y99: 127.9112 | Z99: 16.561023
A100: 202002 | B100: BAJO | C100: 82.160817 | D100: 10.569786 | E100: 14.15 | H100: 202002 | I100: ALTO | J100: 25.175 | K100: 158.21625 | L100: 18.632465 | O100: 202002 | P100: ALTO | Q100: 72.466487 | R100: 8.1051505 | S100: 8.233 | V100: 202002 | W100: ALTO | X100: 25.175 | Y100: 158.21625 | Z100: 18.632465
A101: 202002 | B101: RECHAZO | C101: 16.082375 | D101: 2.406872 | E101: 5.747 | H101: 202002 | I101: MUY BAJO | J101: 30.909 | K101: 113.75975 | L101: 17.302856 | O101: 202002 | Q101: 4.4290006 | R101: 0.4429098 | S101: 0.56 | V101: 202002 | W101: MUY BAJO | X101: 30.909 | Y101: 113.75975 | Z101: 17.302856
...

Sheet CuotasaAnterior
A1: PASE A CUOTAS | J1: COMPRA EN CUOTAS
A3: MES ACTUAL | B3: 202107
A5: CODMES | B5: CA_NIVEL | C5: NumCuotas | D5: FactuPonderada | E5: FactuCuotas | F5: ClientesCuotas | G5: %FactuCuota | H5: %Cuentas | J5: CODMES | K5: CA_NIVEL | L5: NumCuotas | M5: FactuPonderada | N5: FactuCuotas | O5: ClientesCuotas | P5: %FactuCuota | Q5: %Cuentas | S5: % CuotasT
A6: 201901 | C6: 8.066582 | D6: 224.46937 | E6: 27.827073 | F6: 38.417 | G6: =IF(A6="","",E6/IF(A6=$B$3,Resumen!#REF!,VLOOKUP(A6,Graf_PowerBI!$A$4:$D$39,3,0))) -> 0.044983893 | H6: =IF(A6="","",F6/IF(A6=$B$3,Resumen!#REF!,VLOOKUP(A6,Graf_PowerBI!$A$4:$D$39,4,0))) -> 0.063723205 | J6: 201901 | L6: 8.0124278 | M6: 764.81064 | N6: 95.453046 | O6: 141.213 | P6: =IF(J6="","",N6/IF(J6=$B$3,Resumen!#REF!,VLOOKUP(J6,Graf_PowerBI!$A$4:$D$39,3,0))) -> 0.15430475 | Q6: =IF(J6="","",O6/IF(J6=$B$3,Resumen!#REF!,VLOOKUP(J6,Graf_PowerBI!$A$4:$D$39,4,0))) -> 0.23423341 | S6: =IF(A6="","",P6+G6) -> 0.19928864
A7: 201902 | C7: 8.4662205 | D7: 200.98858 | E7: 23.74006 | F7: 34.644 | G7: =IF(A7="","",E7/IF(A7=$B$3,Resumen!#REF!,VLOOKUP(A7,Graf_PowerBI!$A$4:$D$39,3,0))) -> 0.038373598 | H7: =IF(A7="","",F7/IF(A7=$B$3,Resumen!#REF!,VLOOKUP(A7,Graf_PowerBI!$A$4:$D$39,4,0))) -> 0.057023969 | J7: 201902 | L7: 7.9893946 | M7: 784.43349 | N7: 98.184347 | O7: 144.096 | P7: =IF(J7="","",N7/IF(J7=$B$3,Resumen!#REF!,VLOOKUP(J7,Graf_PowerBI!$A$4:$D$39,3,0))) -> 0.15870586 | Q7: =IF(J7="","",O7/IF(J7=$B$3,Resumen!#REF!,VLOOKUP(J7,Graf_PowerBI!$A$4:$D$39,4,0))) -> 0.23718179 | S7: =IF(A7="","",P7+G7) -> 0.19707946
A8: 201903 | C8: 8.2482377 | D8: 201.05888 | E8: 24.37598 | F8: 34.955 | G8: =IF(A8="","",E8/IF(A8=$B$3,Resumen!#REF!,VLOOKUP(A8,Graf_PowerBI!$A$4:$D$39,3,0))) -> 0.034886389 | H8: =IF(A8="","",F8/IF(A8=$B$3,Resumen!#REF!,VLOOKUP(A8,Graf_PowerBI!$A$4:$D$39,4,0))) -> 0.055917085 | J8: 201903 | L8: 8.0995955 | M8: 985.10087 | N8: 121.62347 | O8: 163.298 | P8: =IF(J8="","",N8/IF(J8=$B$3,Resumen!#REF!,VLOOKUP(J8,Graf_PowerBI!$A$4:$D$39,3,0))) -> 0.17406494 | Q8: =IF(J8="","",O8/IF(J8=$B$3,Resumen!#REF!,VLOOKUP(J8,Graf_PowerBI!$A$4:$D$39,4,0))) -> 0.26122581 | S8: =IF(A8="","",P8+G8) -> 0.20895133
A9: 201904 | C9: 7.984031 | D9: 223.89428 | E9: 28.042761 | F9: 41.129 | G9: =IF(A9="","",E9/IF(A9=$B$3,Resumen!#REF!,VLOOKUP(A9,Graf_PowerBI!$A$4:$D$39,3,0))) -> 0.042123079 | H9: =IF(A9="","",F9/IF(A9=$B$3,Resumen!#REF!,VLOOKUP(A9,Graf_PowerBI!$A$4:$D$39,4,0))) -> 0.065169718 | J9: 201904 | L9: 7.9402953 | M9: 846.95053 | N9: 106.66487 | O9: 152.714 | P9: =IF(J9="","",N9/IF(J9=$B$3,Resumen!#REF!,VLOOKUP(J9,Graf_PowerBI!$A$4:$D$39,3,0))) -> 0.16022147 | Q9: =IF(J9="","",O9/IF(J9=$B$3,Resumen!#REF!,VLOOKUP(J9,Graf_PowerBI!$A$4:$D$39,4,0))) -> 0.24197837 | S9: =IF(A9="","",P9+G9) -> 0.20234455
A10: 201905 | C10: 7.6532386 | D10: 258.41039 | E10: 33.764842 | F10: 49.01 | G10: =IF(A10="","",E10/IF(A10=$B$3,Resumen!#REF!,VLOOKUP(A10,Graf_PowerBI!$A$4:$D$39,3,0))) -> 0.046630654 | H10: =IF(A10="","",F10/IF(A10=$B$3,Resumen!#REF!,VLOOKUP(A10,Graf_PowerBI!$A$4:$D$39,4,0))) -> 0.076164102 | J10: 201905 | L10: 7.6657276 | M10: 909.01235 | N10: 118.58135 | O10: 166.454 | P10: =IF(J10="","",N10/IF(J10=$B$3,Resumen!#REF!,VLOOKUP(J10,Graf_PowerBI!$A$4:$D$39,3,0))) -> 0.16376579 | Q10: =IF(J10="","",O10/IF(J10=$B$3,Resumen!#REF!,VLOOKUP(J10,Graf_PowerBI!$A$4:$D$39,4,0))) -> 0.25867822 | S10: =IF(A10="","",P10+G10) -> 0.21039645
A11: 201906 | C11: 7.8688203 | D11: 283.50043 | E11: 36.028327 | F11: 48.143 | G11: =IF(A11="","",E11/IF(A11=$B$3,Resumen!#REF!,VLOOKUP(A11,Graf_PowerBI!$A$4:$D$39,3,0))) -> 0.051922878 | H11: =IF(A11="","",F11/IF(A11=$B$3,Resumen!#REF!,VLOOKUP(A11,Graf_PowerBI!$A$4:$D$39,4,0))) -> 0.074503316 | J11: 201906 | L11: 7.3464946 | M11: 788.10696 | N11: 107.2766 | O11: 158.692 | P11: =IF(J11="","",N11/IF(J11=$B$3,Resumen!#REF!,VLOOKUP(J11,Graf_PowerBI!$A$4:$D$39,3,0))) -> 0.15460362 | Q11: =IF(J11="","",O11/IF(J11=$B$3,Resumen!#REF!,VLOOKUP(J11,Graf_PowerBI!$A$4:$D$39,4,0))) -> 0.24558254 | S11: =IF(A11="","",P11+G11) -> 0.2065265
A12: 201907 | C12: 7.9088808 | D12: 313.09577 | E12: 39.587873 | F12: 48.534 | G12: =IF(A12="","",E12/IF(A12=$B$3,Resumen!#REF!,VLOOKUP(A12,Graf_PowerBI!$A$4:$D$39,3,0))) -> 0.051611048 | H12: =IF(A12="","",F12/IF(A12=$B$3,Resumen!#REF!,VLOOKUP(A12,Graf_PowerBI!$A$4:$D$39,4,0))) -> 0.073776809 | J12: 201907 | L12: 7.5266607 | M12: 729.38732 | N12: 96.907161 | O12: 153.899 | P12: =IF(J12="","",N12/IF(J12=$B$3,Resumen!#REF!,VLOOKUP(J12,Graf_PowerBI!$A$4:$D$39,3,0))) -> 0.12633869 | Q12: =IF(J12="","",O12/IF(J12=$B$3,Resumen!#REF!,VLOOKUP(J12,Graf_PowerBI!$A$4:$D$39,4,0))) -> 0.23394274 | S12: =IF(A12="","",P12+G12) -> 0.17794974
A13: 201908 | C13: 8.2582491 | D13: 381.93012 | E13: 46.248317 | F13: 54.977 | G13: =IF(A13="","",E13/IF(A13=$B$3,Resumen!#REF!,VLOOKUP(A13,Graf_PowerBI!$A$4:$D$39,3,0))) -> 0.062575192 | H13: =IF(A13="","",F13/IF(A13=$B$3,Resumen!#REF!,VLOOKUP(A13,Graf_PowerBI!$A$4:$D$39,4,0))) -> 0.082931826 | J13: 201908 | L13: 7.615164 | M13: 735.87248 | N13: 96.63252 | O13: 155.76 | P13: =IF(J13="","",N13/IF(J13=$B$3,Resumen!#REF!,VLOOKUP(J13,Graf_PowerBI!$A$4:$D$39,3,0))) -> 0.13074635 | Q13: =IF(J13="","",O13/IF(J13=$B$3,Resumen!#REF!,VLOOKUP(J13,Graf_PowerBI!$A$4:$D$39,4,0))) -> 0.23496119 | S13: =IF(A13="","",P13+G13) -> 0.19332154
A14: 201909 | C14: 8.157486 | D14: 327.6703 | E14: 40.168049 | F14: 54.455 | G14: =IF(A14="","",E14/IF(A14=$B$3,Resumen!#REF!,VLOOKUP(A14,Graf_PowerBI!$A$4:$D$39,3,0))) -> 0.056628844 | H14: =IF(A14="","",F14/IF(A14=$B$3,Resumen!#REF!,VLOOKUP(A14,Graf_PowerBI!$A$4:$D$39,4,0))) -> 0.081795951 | J14: 201909 | L14: 7.857218 | M14: 701.577 | N14: 89.290764 | O14: 150.564 | P14: =IF(J14="","",N14/IF(J14=$B$3,Resumen!#REF!,VLOOKUP(J14,Graf_PowerBI!$A$4:$D$39,3,0))) -> 0.12588196 | Q14: =IF(J14="","",O14/IF(J14=$B$3,Resumen!#REF!,VLOOKUP(J14,Graf_PowerBI!$A$4:$D$39,4,0))) -> 0.22615968 | S14: =IF(A14="","",P14+G14) -> 0.1825108
A15: 201910 | C15: 8.1662172 | D15: 336.4751 | E15: 41.2033 | F15: 55.312 | G15: =IF(A15="","",E15/IF(A15=$B$3,Resumen!#REF!,VLOOKUP(A15,Graf_PowerBI!$A$4:$D$39,3,0))) -> 0.054810342 | H15: =IF(A15="","",F15/IF(A15=$B$3,Resumen!#REF!,VLOOKUP(A15,Graf_PowerBI!$A$4:$D$39,4,0))) -> 0.082250406 | J15: 201910 | L15: 7.7393628 | M15: 692.18519 | N15: 89.436973 | O15: 151.034 | P15: =IF(J15="","",N15/IF(J15=$B$3,Resumen!#REF!,VLOOKUP(J15,Graf_PowerBI!$A$4:$D$39,3,0))) -> 0.11897278 | Q15: =IF(J15="","",O15/IF(J15=$B$3,Resumen!#REF!,VLOOKUP(J15,Graf_PowerBI!$A$4:$D$39,4,0))) -> 0.22459155 | S15: =IF(A15="","",P15+G15) -> 0.17378312
A16: 201911 | C16: 7.9207204 | D16: 363.2419 | E16: 45.859705 | F16: 54.519 | G16: =IF(A16="","",E16/IF(A16=$B$3,Resumen!#REF!,VLOOKUP(A16,Graf_PowerBI!$A$4:$D$39,3,0))) -> 0.058861608 | H16: =IF(A16="","",F16/IF(A16=$B$3,Resumen!#REF!,VLOOKUP(A16,Graf_PowerBI!$A$4:$D$39,4,0))) -> 0.080870846 | J16: 201911 | L16: 8.5526016 | M16: 796.26571 | N16: 93.102163 | O16: 145.763 | P16: =IF(J16="","",N16/IF(J16=$B$3,Resumen!#REF!,VLOOKUP(J16,Graf_PowerBI!$A$4:$D$39,3,0))) -> 0.119498 | Q16: =IF(J16="","",O16/IF(J16=$B$3,Resumen!#REF!,VLOOKUP(J16,Graf_PowerBI!$A$4:$D$39,4,0))) -> 0.21621778 | S16: =IF(A16="","",P16+G16) -> 0.17835961
A17: 201912 | C17: 7.9631879 | D17: 420.58069 | E17: 52.815618 | F17: 56.381 | G17: =IF(A17="","",E17/IF(A17=$B$3,Resumen!#REF!,VLOOKUP(A17,Graf_PowerBI!$A$4:$D$39,3,0))) -> 0.062014764 | H17: =IF(A17="","",F17/IF(A17=$B$3,Resumen!#REF!,VLOOKUP(A17,Graf_PowerBI!$A$4:$D$39,4,0))) -> 0.083014806 | J17: 201912 | L17: 7.8981925 | M17: 899.7026 | N17: 113.91247 | O17: 167.331 | P17: =IF(J17="","",N17/IF(J17=$B$3,Resumen!#REF!,VLOOKUP(J17,Graf_PowerBI!$A$4:$D$39,3,0))) -> 0.13375314 | Q17: =IF(J17="","",O17/IF(J17=$B$3,Resumen!#REF!,VLOOKUP(J17,Graf_PowerBI!$A$4:$D$39,4,0))) -> 0.24637645 | S17: =IF(A17="","",P17+G17) -> 0.1957679
... A35: 202106 | C35: 7.6451069 | D35: 204.33849 | E35: 26.728009 | F35: 30.607 | G35: =IF(A35="","",E35/IF(A35=$B$3,Resumen!#REF!,VLOOKUP(A35,Graf_PowerBI!$A$4:$D$39,3,0))) -> 0.033248688 | H35: =IF(A35="","",F35/IF(A35=$B$3,Resumen!#REF!,VLOOKUP(A35,Graf_PowerBI!$A$4:$D$39,4,0))) -> 0.052211576 | J35: 202106 | L35: 6.5568659 | M35: 403.33392 | N35: 61.513217 | O35: 89.452 | P35: =IF(J35="","",N35/IF(J35=$B$3,Resumen!#REF!,VLOOKUP(J35,Graf_PowerBI!$A$4:$D$39,3,0))) -> 0.076520244 | Q35: =IF(J35="","",O35/IF(J35=$B$3,Resumen!#REF!,VLOOKUP(J35,Graf_PowerBI!$A$4:$D$39,4,0))) -> 0.15259352 | S35: =IF(A35="","",P35+G35) -> 0.10976893
A36: 202106 | B36: MUY ALTO | C36: 7.2179694 | D36: 28.644233 | E36: 3.9684614 | F36: 3.163 | G36: =IF(A36="","",E36/IF(A36=$B$3,Resumen!#REF!,VLOOKUP(A36,Graf_PowerBI!$A$4:$D$39,3,0))) -> 0.0049366242 | H36: =IF(A36="","",F36/IF(A36=$B$3,Resumen!#REF!,VLOOKUP(A36,Graf_PowerBI!$A$4:$D$39,4,0))) -> 0.0053956681 | J36: 202106 | K36: MUY ALTO | L36: 7.8623722 | M36: 84.946681 | N36: 10.804205 | O36: 11.779 | P36: =IF(J36="","",N36/IF(J36=$B$3,Resumen!#REF!,VLOOKUP(J36,Graf_PowerBI!$A$4:$D$39,3,0))) -> 0.013440045 | Q36: =IF(J36="","",O36/IF(J36=$B$3,Resumen!#REF!,VLOOKUP(J36,Graf_PowerBI!$A$4:$D$39,4,0))) -> 0.020093448 | S36: =IF(A36="","",P36+G36) -> 0.018376669
A37: 202106 | B37: ALTO | C37: 8.91437 | D37: 46.431104 | E37: 5.2085682 | F37: 4.507 | G37: =IF(A37="","",E37/IF(A37=$B$3,Resumen!#REF!,VLOOKUP(A37,Graf_PowerBI!$A$4:$D$39,3,0))) -> 0.0064792727 | H37: =IF(A37="","",F37/IF(A37=$B$3,Resumen!#REF!,VLOOKUP(A37,Graf_PowerBI!$A$4:$D$39,4,0))) -> 0.0076883579 | J37: 202106 | K37: ALTO | L37: 6.9508079 | M37: 83.185752 | N37: 11.967782 | O37: 14.98 | P37: =IF(J37="","",N37/IF(J37=$B$3,Resumen!#REF!,VLOOKUP(J37,Graf_PowerBI!$A$4:$D$39,3,0))) -> 0.014887493 | Q37: =IF(J37="","",O37/IF(J37=$B$3,Resumen!#REF!,VLOOKUP(J37,Graf_PowerBI!$A$4:$D$39,4,0))) -> 0.025553939 | S37: =IF(A37="","",P37+G37) -> 0.021366766
A38: 202106 | B38: MEDIO | C38: 7.7846328 | D38: 28.152205 | E38: 3.6163819 | F38: 3.822 | G38: =IF(A38="","",E38/IF(A38=$B$3,Resumen!#REF!,VLOOKUP(A38,Graf_PowerBI!$A$4:$D$39,3,0))) -> 0.0044986498 | H38: =IF(A38="","",F38/IF(A38=$B$3,Resumen!#REF!,VLOOKUP(A38,Graf_PowerBI!$A$4:$D$39,4,0))) -> 0.0065198367 | J38: 202106 | K38: MEDIO | L38: 6.2112253 | M38: 50.299783 | N38: 8.0982061 | O38: 11.372 | P38: =IF(J38="","",N38/IF(J38=$B$3,Resumen!#REF!,VLOOKUP(J38,Graf_PowerBI!$A$4:$D$39,3,0))) -> 0.010073879 | Q38: =IF(J38="","",O38/IF(J38=$B$3,Resumen!#REF!,VLOOKUP(J38,Graf_PowerBI!$A$4:$D$39,4,0))) -> 0.019399158 | S38: =IF(A38="","",P38+G38) -> 0.014572529
A39: 202106 | B39: BAJO | C39: 7.4626 | D39: 60.252567 | E39: 8.0739377 | F39: 9.942 | G39: =IF(A39="","",E39/IF(A39=$B$3,Resumen!#REF!,VLOOKUP(A39,Graf_PowerBI!$A$4:$D$39,3,0))) -> 0.01004369 | H39: =IF(A39="","",F39/IF(A39=$B$3,Resumen!#REF!,VLOOKUP(A39,Graf_PowerBI!$A$4:$D$39,4,0))) -> 0.016959764 | J39: 202106 | K39: BAJO | L39: 6.2128413 | M39: 108.94701 | N39: 17.535779 | O39: 27.249 | P39: =IF(J39="","",N39/IF(J39=$B$3,Resumen!#REF!,VLOOKUP(J39,Graf_PowerBI!$A$4:$D$39,3,0))) -> 0.021813882 | Q39: =IF(J39="","",O39/IF(J39=$B$3,Resumen!#REF!,VLOOKUP(J39,Graf_PowerBI!$A$4:$D$39,4,0))) -> 0.046483263 | S39: =IF(A39="","",P39+G39) -> 0.031857572
A40: 202106 | B40: MUY BAJO | C40: 6.8215337 | D40: 29.446743 | E40: 4.3167336 | F40: 6.547 | G40: =IF(A40="","",E40/IF(A40=$B$3,Resumen!#REF!,VLOOKUP(A40,Graf_PowerBI!$A$4:$D$39,3,0))) -> 0.0053698623 | H40: =IF(A40="","",F40/IF(A40=$B$3,Resumen!#REF!,VLOOKUP(A40,Graf_PowerBI!$A$4:$D$39,4,0))) -> 0.011168334 | J40: 202106 | K40: MUY BAJO | L40: 5.6232497 | M40: 49.394813 | N40: 8.7840334 | O40: 16.213 | P40: =IF(J40="","",N40/IF(J40=$B$3,Resumen!#REF!,VLOOKUP(J40,Graf_PowerBI!$A$4:$D$39,3,0))) -> 0.010927024 | Q40: =IF(J40="","",O40/IF(J40=$B$3,Resumen!#REF!,VLOOKUP(J40,Graf_PowerBI!$A$4:$D$39,4,0))) -> 0.027657277 | S40: =IF(A40="","",P40+G40) -> 0.016296886
A41: 202106 | B41: RECHAZO | C41: 6.9123925 | D41: 7.854974 | E41: 1.1363611 | F41: 2.048 | G41: =IF(A41="","",E41/IF(A41=$B$3,Resumen!#REF!,VLOOKUP(A41,Graf_PowerBI!$A$4:$D$39,3,0))) -> 0.0014135926 | H41: =IF(A41="","",F41/IF(A41=$B$3,Resumen!#REF!,VLOOKUP(A41,Graf_PowerBI!$A$4:$D$39,4,0))) -> 0.0034936226 | J41: 202106 | K41: RECHAZO | L41: 4.9729318 | M41: 10.124437 | N41: 2.035909 | O41: 4.785 | P41: =IF(J41="","",N41/IF(J41=$B$3,Resumen!#REF!,VLOOKUP(J41,Graf_PowerBI!$A$4:$D$39,3,0))) -> 0.002532598 | Q41: =IF(J41="","",O41/IF(J41=$B$3,Resumen!#REF!,VLOOKUP(J41,Graf_PowerBI!$A$4:$D$39,4,0))) -> 0.0081625899 | S41: =IF(A41="","",P41+G41) -> 0.0039461907
A42: 202106 | B42: (en blanco) | C42: 8.726601 | D42: 3.5566618 | E42: 0.40756553 | F42: 0.578 | G42: =IF(A42="","",E42/IF(A42=$B$3,Resumen!#REF!,VLOOKUP(A42,Graf_PowerBI!$A$4:$D$39,3,0))) -> 0.00050699696 | H42: =IF(A42="","",F42/IF(A42=$B$3,Resumen!#REF!,VLOOKUP(A42,Graf_PowerBI!$A$4:$D$39,4,0))) -> 0.0009859931 | J42: 202106 | K42: (en blanco) | L42: 7.1855104 | M42: 16.435439 | N42: 2.287303 | O42: 3.074 | P42: =IF(J42="","",N42/IF(J42=$B$3,Resumen!#REF!,VLOOKUP(J42,Graf_PowerBI!$A$4:$D$39,3,0))) -> 0.0028453231 | Q42: =IF(J42="","",O42/IF(J42=$B$3,Resumen!#REF!,VLOOKUP(J42,Graf_PowerBI!$A$4:$D$39,4,0))) -> 0.0052438456 | S42: =IF(A42="","",P42+G42) -> 0.0033523201
A43: 202107 | C43: 6.9613322 | D43: 59.157783 | E43: 8.4980548 | F43: 11.288 | G43: =IF(A43="","",E43/IF(A43=$B$3,Resumen!#REF!,VLOOKUP(A43,Graf_PowerBI!$A$4:$D$39,3,0))) -> #REF! | H43: =IF(A43="","",F43/IF(A43=$B$3,Resumen!#REF!,VLOOKUP(A43,Graf_PowerBI!$A$4:$D$39,4,0))) -> #REF! | J43: 202107 | L43: 6.4275388 | M43: 67.142563 | N43: 10.446077 | O43: 21.051 | P43: =IF(J43="","",N43/IF(J43=$B$3,Resumen!#REF!,VLOOKUP(J43,Graf_PowerBI!$A$4:$D$39,3,0))) -> #REF! | Q43: =IF(J43="","",O43/IF(J43=$B$3,Resumen!#REF!,VLOOKUP(J43,Graf_PowerBI!$A$4:$D$39,4,0))) -> #REF! | S43: =IF(A43="","",P43+G43) -> #REF!
G44: =IF(A44="","",E44/IF(A44=$B$3,Resumen!#REF!,VLOOKUP(A44,Graf_PowerBI!$A$4:$D$39,3,0))) | H44: =IF(A44="","",F44/IF(A44=$B$3,Resumen!#REF!,VLOOKUP(A44,Graf_PowerBI!$A$4:$D$39,4,0))) | P44: =IF(J44="","",N44/IF(J44=$B$3,Resumen!#REF!,VLOOKUP(J44,Graf_PowerBI!$A$4:$D$39,3,0))) | Q44: =IF(J44="","",O44/IF(J44=$B$3,Resumen!#REF!,VLOOKUP(J44,Graf_PowerBI!$A$4:$D$39,4,0))) | S44: =IF(A44="","",P44+G44)
G45: =IF(A45="","",E45/IF(A45=$B$3,Resumen!#REF!,VLOOKUP(A45,Graf_PowerBI!$A$4:$D$39,3,0))) | H45: =IF(A45="","",F45/IF(A45=$B$3,Resumen!#REF!,VLOOKUP(A45,Graf_PowerBI!$A$4:$D$39,4,0))) | P45: =IF(J45="","",N45/IF(J45=$B$3,Resumen!#REF!,VLOOKUP(J45,Graf_PowerBI!$A$4:$D$39,3,0))) | Q45: =IF(J45="","",O45/IF(J45=$B$3,Resumen!#REF!,VLOOKUP(J45,Graf_PowerBI!$A$4:$D$39,4,0))) | S45: =IF(A45="","",P45+G45)
G46: =IF(A46="","",E46/IF(A46=$B$3,Resumen!#REF!,VLOOKUP(A46,Graf_PowerBI!$A$4:$D$39,3,0))) | H46: =IF(A46="","",F46/IF(A46=$B$3,Resumen!#REF!,VLOOKUP(A46,Graf_PowerBI!$A$4:$D$39,4,0))) | P46: =IF(J46="","",N46/IF(J46=$B$3,Resumen!#REF!,VLOOKUP(J46,Graf_PowerBI!$A$4:$D$39,3,0))) | Q46: =IF(J46="","",O46/IF(J46=$B$3,Resumen!#REF!,VLOOKUP(J46,Graf_PowerBI!$A$4:$D$39,4,0))) | S46: =IF(A46="","",P46+G46)
G47: =IF(A47="","",E47/IF(A47=$B$3,Resumen!#REF!,VLOOKUP(A47,Graf_PowerBI!$A$4:$D$39,3,0))) | H47: =IF(A47="","",F47/IF(A47=$B$3,Resumen!#REF!,VLOOKUP(A47,Graf_PowerBI!$A$4:$D$39,4,0))) | P47: =IF(J47="","",N47/IF(J47=$B$3,Resumen!#REF!,VLOOKUP(J47,Graf_PowerBI!$A$4:$D$39,3,0))) | Q47: =IF(J47="","",O47/IF(J47=$B$3,Resumen!#REF!,VLOOKUP(J47,Graf_PowerBI!$A$4:$D$39,4,0))) | S47: =IF(A47="","",P47+G47)
G48: =IF(A48="","",E48/IF(A48=$B$3,Resumen!#REF!,VLOOKUP(A48,Graf_PowerBI!$A$4:$D$39,3,0))) | H48: =IF(A48="","",F48/IF(A48=$B$3,Resumen!#REF!,VLOOKUP(A48,Graf_PowerBI!$A$4:$D$39,4,0))) | P48: =IF(J48="","",N48/IF(J48=$B$3,Resumen!#REF!,VLOOKUP(J48,Graf_PowerBI!$A$4:$D$39,3,0))) | Q48: =IF(J48="","",O48/IF(J48=$B$3,Resumen!#REF!,VLOOKUP(J48,Graf_PowerBI!$A$4:$D$39,4,0))) | S48: =IF(A48="","",P48+G48)
G49: =IF(A49="","",E49/IF(A49=$B$3,Resumen!#REF!,VLOOKUP(A49,Graf_PowerBI!$A$4:$D$39,3,0))) | H49: =IF(A49="","",F49/IF(A49=$B$3,Resumen!#REF!,VLOOKUP(A49,Graf_PowerBI!$A$4:$D$39,4,0))) | P49: =IF(J49="","",N49/IF(J49=$B$3,Resumen!#REF!,VLOOKUP(J49,Graf_PowerBI!$A$4:$D$39,3,0))) | Q49: =IF(J49="","",O49/IF(J49=$B$3,Resumen!#REF!,VLOOKUP(J49,Graf_PowerBI!$A$4:$D$39,4,0))) | S49: =IF(A49="","",P49+G49)
G50: =IF(A50="","",E50/IF(A50=$B$3,Resumen!#REF!,VLOOKUP(A50,Graf_PowerBI!$A$4:$D$39,3,0))) | H50: =IF(A50="","",F50/IF(A50=$B$3,Resumen!#REF!,VLOOKUP(A50,Graf_PowerBI!$A$4:$D$39,4,0))) | P50: =IF(J50="","",N50/IF(J50=$B$3,Resumen!#REF!,VLOOKUP(J50,Graf_PowerBI!$A$4:$D$39,3,0))) | Q50: =IF(J50="","",O50/IF(J50=$B$3,Resumen!#REF!,VLOOKUP(J50,Graf_PowerBI!$A$4:$D$39,4,0))) | S50: =IF(A50="","",P50+G50)
G51: =IF(A51="","",E51/IF(A51=$B$3,Resumen!#REF!,VLOOKUP(A51,Graf_PowerBI!$A$4:$D$39,3,0))) | H51: =IF(A51="","",F51/IF(A51=$B$3,Resumen!#REF!,VLOOKUP(A51,Graf_PowerBI!$A$4:$D$39,4,0))) | P51: =IF(J51="","",N51/IF(J51=$B$3,Resumen!#REF!,VLOOKUP(J51,Graf_PowerBI!$A$4:$D$39,3,0))) | Q51: =IF(J51="","",O51/IF(J51=$B$3,Resumen!#REF!,VLOOKUP(J51,Graf_PowerBI!$A$4:$D$39,4,0))) | S51: =IF(A51="","",P51+G51)
G52: =IF(A52="","",E52/IF(A52=$B$3,Resumen!#REF!,VLOOKUP(A52,Graf_PowerBI!$A$4:$D$39,3,0))) | H52: =IF(A52="","",F52/IF(A52=$B$3,Resumen!#REF!,VLOOKUP(A52,Graf_PowerBI!$A$4:$D$39,4,0))) | P52: =IF(J52="","",N52/IF(J52=$B$3,Resumen!#REF!,VLOOKUP(J52,Graf_PowerBI!$A$4:$D$39,3,0))) | Q52: =IF(J52="","",O52/IF(J52=$B$3,Resumen!#REF!,VLOOKUP(J52,Graf_PowerBI!$A$4:$D$39,4,0))) | S52: =IF(A52="","",P52+G52)
G53: =IF(A53="","",E53/IF(A53=$B$3,Resumen!#REF!,VLOOKUP(A53,Graf_PowerBI!$A$4:$D$39,3,0))) | H53: =IF(A53="","",F53/IF(A53=$B$3,Resumen!#REF!,VLOOKUP(A53,Graf_PowerBI!$A$4:$D$39,4,0))) | P53: =IF(J53="","",N53/IF(J53=$B$3,Resumen!#REF!,VLOOKUP(J53,Graf_PowerBI!$A$4:$D$39,3,0))) | Q53: =IF(J53="","",O53/IF(J53=$B$3,Resumen!#REF!,VLOOKUP(J53,Graf_PowerBI!$A$4:$D$39,4,0))) | S53: =IF(A53="","",P53+G53)
G54: =IF(A54="","",E54/IF(A54=$B$3,Resumen!#REF!,VLOOKUP(A54,Graf_PowerBI!$A$4:$D$39,3,0))) | H54: =IF(A54="","",F54/IF(A54=$B$3,Resumen!#REF!,VLOOKUP(A54,Graf_PowerBI!$A$4:$D$39,4,0))) | P54: =IF(J54="","",N54/IF(J54=$B$3,Resumen!#REF!,VLOOKUP(J54,Graf_PowerBI!$A$4:$D$39,3,0))) | Q54: =IF(J54="","",O54/IF(J54=$B$3,Resumen!#REF!,VLOOKUP(J54,Graf_PowerBI!$A$4:$D$39,4,0))) | S54: =IF(A54="","",P54+G54)
G55: =IF(A55="","",E55/IF(A55=$B$3,Resumen!#REF!,VLOOKUP(A55,Graf_PowerBI!$A$4:$D$39,3,0))) | H55: =IF(A55="","",F55/IF(A55=$B$3,Resumen!#REF!,VLOOKUP(A55,Graf_PowerBI!$A$4:$D$39,4,0))) | P55: =IF(J55="","",N55/IF(J55=$B$3,Resumen!#REF!,VLOOKUP(J55,Graf_PowerBI!$A$4:$D$39,3,0))) | Q55: =IF(J55="","",O55/IF(J55=$B$3,Resumen!#REF!,VLOOKUP(J55,Graf_PowerBI!$A$4:$D$39,4,0))) | S55: =IF(A55="","",P55+G55)
... G253: =IF(A253="","",E253/IF(A253=$B$3,Resumen!#REF!,VLOOKUP(A253,Graf_PowerBI!$A$4:$D$39,3,0))) | H253: =IF(A253="","",F253/IF(A253=$B$3,Resumen!#REF!,VLOOKUP(A253,Graf_PowerBI!$A$4:$D$39,4,0))) | P253: =IF(J253="","",N253/IF(J253=$B$3,Resumen!#REF!,VLOOKUP(J253,Graf_PowerBI!$A$4:$D$39,3,0))) | Q253: =IF(J253="","",O253/IF(J253=$B$3,Resumen!#REF!,VLOOKUP(J253,Graf_PowerBI!$A$4:$D$39,4,0))) | S253: =IF(A253="","",P253+G253)

Sheet cuotas diario
B1: pase | I1: consumo a cuotas
B2: CODMES | C2: FECHA | D2: PONDERADO | E2: FACTU | F2: CLIENTES | I2: CODMES | J2: FECTRANSACCION | K2: CLIENTES | L2: PONDCUOTAS | M2: FACTUTOTAL
B3: 202301 | C3: 44927 | D3: 6.1854641 | E3: 0.76703633 | F3: 1.416 | I3: 202301 | J3: 44927 | K3: 1.55 | L3: 3.1055162 | M3: 0.54206019
B4: 202301 | C4: 44928 | D4: 14.58998 | E4: 1.8920803 | F4: 3.052 | I4: 202301 | J4: 44928 | K4: 6.308 | L4: 24.598104 | M4: 3.4881359
B5: 202301 | C5: 44929 | D5: 11.589479 | E5: 1.5372219 | F5: 2.446 | I5: 202301 | J5: 44929 | K5: 6.737 | L5: 26.932852 | M5: 3.602261
B6: 202301 | C6: 44930 | D6: 27.038417 | E6: 3.3006168 | F6: 5.407 | I6: 202301 | J6: 44930 | K6: 6.25 | L6: 28.227533 | M6: 3.5853843
B7: 202301 | C7: 44931 | D7: 27.767183 | E7: 3.1470803 | F7: 4.714 | I7: 202301 | J7: 44931 | K7: 6.643 | L7: 28.60398 | M7: 3.8312494
B8: 202301 | C8: 44932 | D8: 21.417934 | E8: 2.603463 | F8: 3.802 | I8: 202301 | J8: 44932 | K8: 6.395 | L8: 29.630912 | M8: 3.5662649
B9: 202301 | C9: 44933 | D9: 13.752548 | E9: 1.6265303 | F9: 2.49 | I9: 202301 | J9: 44933 | K9: 7.169 | L9: 26.939494 | M9: 3.6891741
B10: 202301 | C10: 44934 | D10: 8.4692876 | E10: 1.1466035 | F10: 1.687 | I10: 202301 | J10: 44934 | K10: 5.814 | L10: 20.800428 | M10: 2.6852187
B11: 202301 | C11: 44935 | D11: 15.836533 | E11: 1.8535061 | F11: 2.602 | I11: 202301 | J11: 44935 | K11: 6.802 | L11: 33.434137 | M11: 4.0693647
B12: 202301 | C12: 44936 | D12: 27.648181 | E12: 3.1127899 | F12: 4.551 | I12: 202301 | J12: 44936 | K12: 6.635 | L12: 27.043692 | M12: 3.71601
B13: 202301 | C13: 44937 | D13: 21.73302 | E13: 2.5520683 | F13: 3.753 | I13: 202301 | J13: 44937 | K13: 6.729 | L13: 36.066127 | M13: 3.9656071
B14: 202301 | C14: 44938 | D14: 16.719166 | E14: 1.837196 | F14: 2.733 | I14: 202301 | J14: 44938 | K14: 6.54 | L14: 32.453569 | M14: 3.8631775
B15: 202301 | C15: 44939 | D15: 12.327119 | E15: 1.552252 | F15: 2.583 | I15: 202301 | J15: 44939 | K15: 6.314 | L15: 26.376414 | M15: 3.4872926
B18: 202301 | C18: 44940 | D18: 10.61894 | E18: 1.2712743 | F18: 2.067
B19: 202301 | C19: 44941 | D19: 8.2438488 | E19: 0.93700833 | F19: 1.726
B20: 202301 | C20: 44942 | D20: 10.953374 | E20: 1.5161362 | F20: 2.423
B21: 202301 | C21: 44943 | D21: 25.493636 | E21: 2.6062979 | F21: 4.178
B22: 202301 | C22: 44944 | D22: 0.05356689 | E22: 0.00704906 | F22: 0.015
B25: CODMES | C25: FECHA | D25: PONDERADO | E25: FACTU | F25: CLIENTES | I25: CODMES | J25: FECTRANSACCION | K25: CLIENTES | L25: PONDCUOTAS | M25: FACTUTOTAL
B26: 202301 | C26: 44927 | D26: 6.1854641 | E26: 0.76703633 | F26: 1.416 | I26: 202301 | J26: 44927 | K26: 1.55 | L26: 3.1055162 | M26: 0.54206019
B27: 202301 | C27: 44928 | D27: 14.58998 | E27: 1.8920803 | F27: 3.052 | I27: 202301 | J27: 44928 | K27: 6.308 | L27: 24.598104 | M27: 3.4881359
B28: 202301 | C28: 44929 | D28: 11.589479 | E28: 1.5372219 | F28: 2.446 | I28: 202301 | J28: 44929 | K28: 6.738 | L28: 26.932894 | M28: 3.602282
B29: 202301 | C29: 44930 | D29: 27.038417 | E29: 3.3006168 | F29: 5.407 | I29: 202301 | J29: 44930 | K29: 6.25 | L29: 28.227533 | M29: 3.5853843
B30: 202301 | C30: 44931 | D30: 27.767183 | E30: 3.1470803 | F30: 4.714 | I30: 202301 | J30: 44931 | K30: 6.643 | L30: 28.60398 | M30: 3.8312494
B31: 202301 | C31: 44932 | D31: 21.417934 | E31: 2.603463 | F31: 3.802 | I31: 202301 | J31: 44932 | K31: 6.396 | L31: 29.631152 | M31: 3.5663849
B32: 202301 | C32: 44933 | D32: 13.752548 | E32: 1.6265303 | F32: 2.49 | I32: 202301 | J32: 44933 | K32: 7.169 | L32: 26.939494 | M32: 3.6891741
B33: 202301 | C33: 44934 | D33: 8.4692876 | E33: 1.1466035 | F33: 1.687 | I33: 202301 | J33: 44934 | K33: 5.814 | L33: 20.801028 | M33: 2.6853687
B34: 202301 | C34: 44935 | D34: 15.836533 | E34: 1.8535061 | F34: 2.602 | I34: 202301 | J34: 44935 | K34: 6.806 | L34: 33.479357 | M34: 4.0749329
B35: 202301 | C35: 44936 | D35: 27.648181 | E35: 3.1127899 | F35: 4.551 | I35: 202301 | J35: 44936 | K35: 6.639 | L35: 27.052035 | M35: 3.7186669
B36: 202301 | C36: 44937 | D36: 21.73302 | E36: 2.5520683 | F36: 3.753 | I36: 202301 | J36: 44937 | K36: 6.73 | L36: 36.079815 | M36: 3.9690293
B37: 202301 | C37: 44938 | D37: 16.719166 | E37: 1.837196 | F37: 2.733 | I37: 202301 | J37: 44938 | K37: 6.55 | L37: 32.922493 | M37: 3.9052403
... B45: 202301 | C45: 44946 | D45: 15.968885 | E45: 2.0052134 | F45: 3.105 | I45: 202301 | J45: 44946 | K45: 6.411 | L45: 24.309333 | M45: 3.3131981
B46: 202301 | C46: 44947 | D46: 8.8128016 | E46: 1.0475035 | F46: 2.088
B47: 202301 | C47: 44948 | D47: 6.7917639 | E47: 0.81391181 | F47: 1.398
B48: 202301 | C48: 44949 | D48: 8.4667582 | E48: 1.1554155 | F48: 2.066
B49: 202301 | C49: 44950 | D49: 19.566885 | E49: 2.225844 | F49: 3.892
B50: 202301 | C50: 44951 | D50: 14.322174 | E50: 1.6034034 | F50: 2.741
B51: 202301 | C51: 44952 | D51: 0.0156124 | E51: 0.0025673 | F51: 0.004
B53: CODMES | C53: FECHA | D53: PONDERADO | E53: FACTU | F53: CLIENTES | I53: CODMES | J53: FECTRANSACCION | K53: CLIENTES | L53: PONDCUOTAS | M53: FACTUTOTAL
B54: 202301 | C54: 44927 | D54: 6.1854641 | E54: 0.76703633 | F54: 1.416 | I54: 202301 | J54: 44927 | K54: 1.55 | L54: 3.1055162 | M54: 0.54206019
B55: 202301 | C55: 44928 | D55: 14.58998 | E55: 1.8920803 | F55: 3.052 | I55: 202301 | J55: 44928 | K55: 6.308 | L55: 24.598104 | M55: 3.4881359
B56: 202301 | C56: 44929 | D56: 11.589479 | E56: 1.5372219 | F56: 2.446 | I56: 202301 | J56: 44929 | K56: 6.738 | L56: 26.932894 | M56: 3.602282
B57: 202301 | C57: 44930 | D57: 27.038417 | E57: 3.3006168 | F57: 5.407 | I57: 202301 | J57: 44930 | K57: 6.25 | L57: 28.227533 | M57: 3.5853843
B58: 202301 | C58: 44931 | D58: 27.767183 | E58: 3.1470803 | F58: 4.714 | I58: 202301 | J58: 44931 | K58: 6.643 | L58: 28.60398 | M58: 3.8312494
B59: 202301 | C59: 44932 | D59: 21.417934 | E59: 2.603463 | F59: 3.802 | I59: 202301 | J59: 44932 | K59: 6.396 | L59: 29.631152 | M59: 3.5663849
B60: 202301 | C60: 44933 | D60: 13.752548 | E60: 1.6265303 | F60: 2.49 | I60: 202301 | J60: 44933 | K60: 7.169 | L60: 26.939494 | M60: 3.6891741
B61: 202301 | C61: 44934 | D61: 8.4692876 | E61: 1.1466035 | F61: 1.687 | I61: 202301 | J61: 44934 | K61: 5.814 | L61: 20.801028 | M61: 2.6853687
B62: 202301 | C62: 44935 | D62: 15.836533 | E62: 1.8535061 | F62: 2.602 | I62: 202301 | J62: 44935 | K62: 6.806 | L62: 33.479357 | M62: 4.0749329
B63: 202301 | C63: 44936 | D63: 27.648181 | E63: 3.1127899 | F63: 4.551 | I63: 202301 | J63: 44936 | K63: 6.639 | L63: 27.052035 | M63: 3.7186669
B64: 202301 | C64: 44937 | D64: 21.73302 | E64: 2.5520683 | F64: 3.753 | I64: 202301 | J64: 44937 | K64: 6.73 | L64: 36.079815 | M64: 3.9690293
B65: 202301 | C65: 44938 | D65: 16.719166 | E65: 1.837196 | F65: 2.733 | I65: 202301 | J65: 44938 | K65: 6.55 | L65: 32.922493 | M65: 3.9052403
... B73: 202301 | C73: 44946 | D73: 15.968885 | E73: 2.0052134 | F73: 3.105 | I73: 202301 | J73: 44946 | K73: 6.411 | L73: 24.309333 | M73: 3.3131981
B74: 202301 | C74: 44947 | D74: 8.8128016 | E74: 1.0475035 | F74: 2.088
B75: 202301 | C75: 44948 | D75: 6.7917639 | E75: 0.81391181 | F75: 1.398
B76: 202301 | C76: 44949 | D76: 8.4667582 | E76: 1.1554155 | F76: 2.066
B77: 202301 | C77: 44950 | D77: 19.566885 | E77: 2.225844 | F77: 3.892
B78: 202301 | C78: 44951 | D78: 14.322174 | E78: 1.6034034 | F78: 2.741
B79: 202301 | C79: 44952 | D79: 0.0156124 | E79: 0.0025673 | F79: 0.004
B82: CODMES | C82: FECHA | D82: PONDERADO | E82: FACTU | F82: CLIENTES
B83: 202302 | C83: 44954 | D83: 10.007195 | E83: 1.0933856 | F83: 1.81
B84: 202302 | C84: 44955 | D84: 6.0731831 | E84: 0.801987 | F84: 1.34
B85: 202302 | C85: 44956 | D85: 11.237583 | E85: 1.3048945 | F85: 2.137
B86: 202302 | C86: 44957 | D86: 0.0113766 | E86: 0.0037729 | F86: 0.004
A87: miércoles | B87: 202302 | C87: 44958 | D87: 18.821864 | E87: 2.1693264 | F87: 3.769
A88: jueves | B88: 202302 | C88: 44959 | D88: 17.038861 | E88: 1.9129038 | F88: 3.109
A89: viernes | B89: 202302 | C89: 44960 | D89: 14.975089 | E89: 1.7886022 | F89: 2.957
A90: sábado | B90: 202302 | C90: 44961 | D90: 18.401746 | E90: 1.6981139 | F90: 2.66
A91: domingo | B91: 202302 | C91: 44962 | D91: 10.021237 | E91: 1.2997347 | F91: 2.137
A92: lunes | B92: 202302 | C92: 44963 | D92: 16.383215 | E92: 2.084843 | F92: 3.082
A93: martes | B93: 202302 | C93: 44964 | D93: 24.486784 | E93: 2.9401114 | F93: 4.993
A94: miércoles | B94: 202302 | C94: 44965 | D94: 16.760279 | E94: 2.0780315 | F94: 3.283
A95: jueves | B95: 202302 | C95: 44966 | D95: 0.04079692 | E95: 0.00678678 | F95: 0.011
A96: viernes | B96: 202302 | C96: 44967 | D96: 19.70259 | E96: 2.3002219 | F96: 3.342
A97: sábado | B97: 202302 | C97: 44968 | D97: 12.941316 | E97: 1.2639198 | F97: 1.993
A98: domingo | B98: 202302 | C98: 44969 | D98: 7.1942564 | E98: 0.90067811 | F98: 1.546
... A100: martes | B100: 202302 | C100: 44971 | D100: 0.01136542 | E100: 0.00248426 | F100: 0.006

Sheet AMEX
A1: TOTAL | Q1: Proyección Crecimiento Amex
A3: AMEX | B3: 202009 | C3: 202010 | D3: 202011 | E3: 202012 | F3: 202101 | G3: 202102 | H3: 202103 | I3: 202104 | J3: 202105 | K3: 202106 | L3: 202107 | M3: 202108 | N3: 202109 | O3: Proyec Set | Q3: 202103 | R3: 202104 | S3: 202105 | T3: 202106 | U3: 202107 | V3: 202108 | W3: 202109 | X3: 202110 | Y3: 202111 | Z3: 202112
A4: Facturación
A5: Real | B5: 1.4109552e+08 | C5: 1.5463585e+08 | D5: 1.6011516e+08 | E5: 1.89275e+08 | F5: 1.6749357e+08 | G5: 1.4008782e+08 | H5: 1.9790088e+08 | I5: 1.8689541e+08 | J5: 2.1633951e+08 | K5: 2.1387149e+08 | L5: 2.4496765e+08 | M5: 2.4800996e+08 | N5: =Resumen!#REF!*1000000 -> #REF! | O5: =Resumen!B5*Resumen!#REF!*1000000 -> #REF! | P5: =O5/R5 -> #REF! | Q5: 162569329 | R5: 157859429 | S5: 1.7234807e+08 | T5: 1.6544786e+08 | U5: 1.8250957e+08 | V5: 1.7440558e+08 | W5: 1.7158987e+08 | X5: 1.8768119e+08 | Y5: 1.9587551e+08 | Z5: 2.1556457e+08
A6: PPTO | B6: 141219000 | C6: 153477858 | D6: 157524919 | E6: 169377536 | F6: 1.486702e+08 | G6: 1.4630181e+08 | H6: 1.6146462e+08 | I6: 1.5531378e+08 | J6: 1.6717039e+08 | K6: 1.5880528e+08 | L6: 1.749082e+08 | M6: 1.6691863e+08 | N6: 1.6349374e+08
A7: Cumpl | B7: =B5/B6 -> 0.99912562 | C7: =C5/C6 -> 1.007545 | D7: =D5/D6 -> 1.0164434 | E7: =E5/E6 -> 1.117474 | F7: =F5/F6 -> 1.1266116 | G7: =G5/G6 -> 0.95752618 | H7: =H5/H6 -> 1.225661 | I7: =I5/I6 -> 1.2033409 | ... N7: =N5/N6 -> #REF! | O7: =O5/N6 -> #REF!
A8: %Share marca | B8: =+B5/(B5+B29) -> 0.269854 | C8: =+C5/(C5+C29) -> 0.26838626 | D8: =+D5/(D5+D29) -> 0.26677905 | E8: =+E5/(E5+E29) -> 0.26684064 | F8: =+F5/(F5+F29) -> 0.26608771 | G8: =+G5/(G5+G29) -> 0.26092506 | H8: =+H5/(H5+H29) -> 0.26439563 | I8: =+I5/(I5+I29) -> 0.26442489 | ... O8: =+O5/(O5+O29) -> #REF! | Q8: =+Q5/(Q5+Q29) -> 0.26630915 | R8: =+R5/(R5+R29) -> 0.27019945 | S8: =+S5/(S5+S29) -> 0.276947
A10: Entregas | B10: 1871 | C10: 2024 | D10: 1940 | E10: 3484 | F10: 3919 | G10: 3601 | H10: 3922 | I10: 3425 | J10: 4652 | K10: 3815 | L10: 4037 | M10: 5429 | N10: 1112 | O10: =+(Resumen!#REF!*1000)*(N10/(N10+N34)) -> #REF! | P10: =O10/Q10 -> #REF! | Q10: 3657.348 | R10: 3547.9293 | S10: 3778.0617 | T10: 3789.6221 | U10: 3948.7367 | V10: 4113.4502 | W10: 4199.8867 | X10: 4195.6764 | Y10: 4215.3576 | Z10: 4133.9613
F11: =+F10/(F10+F34) -> 0.23004226 | G11: =+G10/(G10+G34) -> 0.23811413 | H11: =+H10/(H10+H34) -> 0.20971019 | I11: =+I10/(I10+I34) -> 0.18939394 | J11: =+J10/(J10+J34) -> 0.18827148 | K11: =+K10/(K10+K34) -> 0.18016529 | L11: =+L10/(L10+L34) -> 0.19211002 | M11: =+M10/(M10+M34) -> 0.20622982 | N11: =+N10/(N10+N34) -> 0.20619321 | Q11: =+Q10/(Q10+Q34) -> 0.20643921 | R11: =+R10/(R10+R34) -> 0.20746739 | S11: =+S10/(S10+S34) -> 0.20830894 | T11: =+T10/(T10+T34) -> 0.20925511 | U11: =+U10/(U10+U34) -> 0.20737247 | V11: =+V10/(V10+V34) -> 0.20867459 | W11: =+W10/(W10+W34) -> 0.20806175 | X11: =+X10/(X10+X34) -> 0.2093291 | ... Z11: =+Z10/(Z10+Z34) -> 0.21123713
A12: Parque | B12: 210260 | C12: 208479 | D12: 206415 | E12: 204649 | F12: 202429 | G12: 201888 | H12: 201788 | I12: 197271 | J12: 198006 | K12: 197653 | L12: 197274 | M12: 200190 | O12: =+(Resumen!B33*1000)*(M12/(M12+M36)) -> 204534.68 | P12: =O12/Q12 -> 1.0162859 | Q12: 201257.02 | R12: 203873.64 | S12: 206744.49 | T12: 208595.87 | U12: 209032.99 | V12: 209858.45 | W12: 210994.17 | X12: 212335.47 | Y12: 213754.99 | Z12: 215368.54
F13: =+F12/(F12+F36) -> 0.23392515 | G13: =+G12/(G12+G36) -> 0.23397566 | H13: =+H12/(H12+H36) -> 0.2331335 | I13: =+I12/(I12+I36) -> 0.23638603 | J13: =+J12/(J12+J36) -> 0.2351713 | K13: =+K12/(K12+K36) -> 0.23479945 | L13: =+L12/(L12+L36) -> 0.2337558 | M13: =+M12/(M12+M36) -> 0.23270899 | ... O13: =+O12/(O12+O36) -> 0.23270899 | Q13: =+Q12/(Q12+Q36) -> 0.23466144 | R13: =+R12/(R12+R36) -> 0.23910383 | S13: =+S12/(S12+S36) -> 0.24347768 | T13: =+T12/(T12+T36) -> 0.24817219 | U13: =+U12/(U12+U36) -> 0.24841723 | V13: =+V12/(V12+V36) -> 0.24861161 | W13: =+W12/(W12+W36) -> 0.24873293 | X13: =+X12/(X12+X36) -> 0.24887036 | ... Z13: =+Z12/(Z12+Z36) -> 0.24918497
A15: Bloq+Canc-Desb | C15: 3652 | D15: 4088 | E15: 3706 | F15: 5704 | G15: 4142 | H15: =+G12+H10-H12 -> 4022 | I15: =+H12+I10-I12 -> 7942 | J15: =+I12+J10-J12 -> 3917 | K15: =+J12+K10-K12 -> 4168 | L15: =+K12+L10-L12 -> 4416 | M15: =+L12+M10-M12 -> 2513 | N15: =+M12+N10-N12 -> 201302 | O15: =+G12+O10-O12 -> #REF! | P15: =O15/Q15 -> #REF! | Q15: 4288.3263 | R15: 4292.2944 | S15: 4268.1872 | T15: 5299.2322 | U15: 3511.6101 | V15: 3287.9956 | W15: 3064.1659 | X15: 2854.3744 | Y15: 2795.8328 | Z15: 2520.4156
A16: Bloqueos | B16: 3511 | C16: 4076 | D16: 3249 | E16: 2966 | F16: 2634 | G16: 2454 | H16: 2333 | I16: 1851 | J16: 2515 | K16: 1825 | L16: 2852 | M16: 1965
C17: =+C16/B12 -> 0.019385523 | D17: =+D16/C12 -> 0.015584303 | E17: =+E16/D12 -> 0.014369111 | F17: =+F16/E12 -> 0.012870818 | G17: =+G16/F12 -> 0.012122769 | H17: =+H16/G12 -> 0.011555912 | I17: =+I16/H12 -> 0.0091729934 | J17: =+J16/I12 -> 0.01274896 | ... N17: =+N16/M12 -> 0
A18: Canc Vol | B18: 1533 | C18: 1478 | D18: 1404 | E18: 1332 | F18: 1332 | G18: 1228 | H18: 1264 | I18: 1112 | J18: 1332 | K18: 1202 | L18: 1317 | M18: 1311
C19: =+C18/B12 -> 0.0070293922 | D19: =+D18/C12 -> 0.0067344912 | E19: =+E18/D12 -> 0.0064530194 | F19: =+F18/E12 -> 0.0065087051 | G19: =+G18/F12 -> 0.0060663245 | H19: =+H18/G12 -> 0.0062608971 | I19: =+I18/H12 -> 0.005510734 | J19: =+J18/I12 -> 0.0067521329 | ... N19: =+N18/M12 -> 0
A20: Canc Inv | B20: 474 | C20: 566 | D20: 1053 | E20: 2373 | F20: 2939 | G20: 1340 | H20: 1531 | I20: 1466 | J20: 1133 | K20: 1806 | L20: 1001 | M20: 505
C21: =+C20/B12 -> 0.0026919053 | D21: =+D20/C12 -> 0.0050508684 | E21: =+E20/D12 -> 0.011496258 | F21: =+F20/E12 -> 0.014361174 | G21: =+G20/F12 -> 0.0066196049 | H21: =+H20/G12 -> 0.0075834126 | I21: =+I20/H12 -> 0.0072650504 | J21: =+J20/I12 -> 0.0057433683 | ... N21: =+N20/M12 -> 0
A23: Ctas CC | B23: 131197 | C23: 132707 | D23: 132335 | E23: 134889 | F23: 134168 | G23: 132132 | H23: 132591 | I23: 137395 | J23: 140928 | K23: 142595 | L23: 144924 | M23: 140928 | O23: =+(Resumen!B17*1000)*(M23/(M23+M46)) -> 184724.41 | P23: =O23/Q23 -> 1.3744046 | Q23: 134403.22 | R23: 136945.66 | S23: 140368.05 | T23: 141781.47 | U23: 144154.88 | V23: 145114.73 | W23: 146587 | X23: 148442.13 | Y23: 150155.03 | Z23: 153835.02
A24: Actividad | B24: 0.624 | C24: 0.637 | D24: 0.641 | E24: 0.659 | F24: =+F23/F12 -> 0.66279041 | G24: =+G23/G12 -> 0.65448169 | H24: =+H23/H12 -> 0.6570807 | I24: =+I23/I12 -> 0.69647845 | J24: =+J23/J12 -> 0.71173601 | K24: =+K23/K12 -> 0.72144111 | L24: =+L23/L12 -> 0.73463305 | M24: =+M23/M12 -> 0.70397123 | ... O24: =+O23/O12 -> 0.9031447 | P24: =O24/Q24 -> 1.3523799 | Q24: 0.66781878 | R24: 0.67171833 | S24: 0.67894457 | T24: 0.67969455 | U24: 0.68962741 | V24: 0.69148861 | W24: 0.69474432 | X24: 0.69909248 | Y24: 0.70246327 | Z24: 0.71428733
A25: CM | B25: 1075 | C25: 1165 | D25: 1210 | E25: 1403 | F25: =+F5/F23 -> 1248.3869 | G25: =+G5/G23 -> 1060.2111 | H25: =+H5/H23 -> 1492.5664 | I25: =+I5/I23 -> 1360.2781 | J25: =+J5/J23 -> 1535.1067 | K25: =+K5/K23 -> 1499.8526 | L25: =+L5/L23 -> 1690.318 | M25: =+M5/M23 -> 1759.8345 | ... O25: =+O5/O23 -> #REF! | P25: =O25/Q25 -> #REF! | Q25: 1209.3529 | R25: 1152.7158 | S25: 1235.1549 | T25: 1173.8694 | U25: 1272.647 | V25: 1207.1562 | W25: 1173.9363 | X25: 1241.7111 | Y25: 1273.6861 | Z25: 1367.1598
A27: MC + VISA | B27: 202009 | C27: 202010 | D27: 202011 | E27: 202012 | F27: 202101 | G27: 202102 | H27: =H3 -> 202103 | I27: 202104 | J27: 202105 | K27: 202106 | L27: 202107 | M27: 202108 | N27: 202109 | O27: =O3 -> Proyec Set
A28: Facturación
A29: Real | B29: 3.8176322e+08 | C29: 4.2153319e+08 | D29: 4.4006376e+08 | E29: 5.2004348e+08 | F29: 4.6197394e+08 | G29: 3.9680127e+08 | H29: 5.5060196e+08 | I29: 5.199042e+08 | J29: 5.9349795e+08 | K29: 5.9004943e+08 | L29: 6.7533296e+08 | M29: 6.8647685e+08 | N29: =(Resumen!#REF!+Resumen!#REF!)*1000000 -> #REF! | O29: =Resumen!B5*(Resumen!#REF!+Resumen!#REF!)*1000000 -> #REF! | P29: =O29/R29 -> #REF! | Q29: 447884093 | R29: 426373545 | S29: 4.499662e+08 | T29: 4.2337608e+08 | U29: 4.6566878e+08 | V29: 4.4345069e+08 | W29: 4.3285917e+08 | X29: 4.6338276e+08 | Y29: 4.825282e+08 | Z29: 5.2979001e+08
A30: PPTO | B30: 3.8163974e+08 | C30: 4.1551909e+08 | D30: 4.2373888e+08 | E30: 4.5261296e+08 | F30: 3.9500551e+08 | G30: 3.8698913e+08 | H30: 4.2473379e+08 | I30: 4.0598819e+08 | J30: 4.3529761e+08 | K30: 4.1112813e+08 | L30: 4.5188012e+08 | M30: 4.3003793e+08 | N30: 4.1950916e+08
A31: Cumpl | B31: =B29/B30 -> 1.0003235 | C31: =C29/C30 -> 1.0144737 | D31: =D29/D30 -> 1.0385258 | E31: =E29/E30 -> 1.1489805 | F31: =F29/F30 -> 1.169538 | G31: =G29/G30 -> 1.0253551 | H31: =H29/H30 -> 1.296346 | I31: =I29/I30 -> 1.2805895 | ... N31: =N29/N30 -> #REF! | O31: =O29/N30 -> #REF!
A32: %Share marca | B32: =+B29/(B29+B5) -> 0.730146 | C32: =+C29/(C29+C5) -> 0.73161374 | D32: =+D29/(D29+D5) -> 0.73322095 | E32: =+E29/(E29+E5) -> 0.73315936 | F32: =+F29/(F29+F5) -> 0.73391229 | G32: =+G29/(G29+G5) -> 0.73907494 | H32: =+H29/(H29+H5) -> 0.73560437 | I32: =+I29/(I29+I5) -> 0.73557511 | ... O32: =+O29/(O29+O5) -> #REF! | Q32: =+Q29/(Q29+Q5) -> 0.73369085 | R32: =+R29/(R29+R5) -> 0.72980055 | S32: =+S29/(S29+S5) -> 0.723053
A34: Entregas | B34: 8096 | C34: 10022 | D34: 9427 | E34: 12024 | F34: 13117 | G34: 11522 | H34: =14761+19 -> 14780 | I34: 14659 | J34: 20057 | K34: 17360 | L34: 16977 | M34: 20896 | N34: 4281 | O34: =+(Resumen!#REF!*1000)*(N34/(N10+N34)) -> #REF! | P34: =O34/Q34 -> #REF! | Q34: 14058.996 | R34: 13553.213 | S34: 14358.758 | T34: 14320.436 | U34: 15093.023 | V34: 15598.822 | W34: 15985.884 | X34: 15847.769 | Y34: 15994.479 | Z34: 15436.279
A36: Parque | B36: 683425 | C36: 680848 | D36: 677354 | E36: 671961 | F36: 662929 | G36: =644191+16780 -> 660971 | H36: =647456+16303 -> 663759 | I36: =623075+14183 -> 637258 | J36: 643959 | K36: 644142 | L36: 646658 | M36: 660069 | O36: =+(Resumen!B33*1000)*(M36/(M12+M36)) -> 674394.32 | P36: =O36/Q36 -> 1.0274271 | Q36: 656391.44 | R36: 648783.7 | S36: 642386.72 | T36: 631932.91 | U36: 632426.33 | V36: 634263.21 | W36: 637281.79 | X36: 640861.63 | Y36: 644748.72 | Z36: 648923.32
A38: Bloq+Canc-Desb | C38: 10673 | D38: 13516 | E38: 14820 | F38: 21056 | G38: 13478 | H38: =+G36+H34-H36 -> 11992 | I38: =+H36+I34-I36 -> 41160 | J38: =+I36+J34-J36 -> 13356 | K38: =+J36+K34-K36 -> 17177 | L38: =+K36+L34-L36 -> 14461 | M38: =+L36+M34-M36 -> 7485 | N38: =+M36+N34-N36 -> 664350 | O38: =+G36+O34-O36 -> #REF! | P38: =O38/Q38 -> #REF! | Q38: 18640.554 | R38: 17799.975 | S38: 17394.754 | T38: 21413.268 | U38: 14599.602 | V38: 13761.939 | W38: 12967.306 | X38: 12267.932 | Y38: 12107.389 | Z38: 11261.676
A39: Bloqueos | B39: 11887 | C39: 14830 | D39: 11935 | E39: 10043 | F39: 9055 | G39: 8887 | H39: 8502 | I39: 8108 | J39: 8848 | K39: 7087 | L39: 10627 | M39: 6856
C40: =+C39/B36 -> 0.021699528 | D40: =+D39/C36 -> 0.01752961 | E40: =+E39/D36 -> 0.014826811 | F40: =+F39/E36 -> 0.013475484 | G40: =+G39/F36 -> 0.013405659 | H40: =+H39/G36 -> 0.012862894 | I40: =+I39/H36 -> 0.012215277 | J40: =+J39/I36 -> 0.013884486 | ... N40: =+N39/M36 -> 0
A41: Canc Vol | B41: 4437 | C41: 4277 | D41: 3862 | E41: 3859 | F41: 3902 | G41: 3521 | H41: 3744 | I41: 3464 | J41: 4346 | K41: 4183 | L41: 4344 | M41: 5110
C42: =+C41/B36 -> 0.0062581849 | D42: =+D41/C36 -> 0.005672338 | E42: =+E41/D36 -> 0.0056971687 | F42: =+F41/E36 -> 0.0058068846 | G42: =+G41/F36 -> 0.0053112777 | H42: =+H41/G36 -> 0.0056643937 | I42: =+I41/H36 -> 0.0052187616 | J42: =+J41/I36 -> 0.0068198438 | ... N42: =+N41/M36 -> 0
A43: Canc Inv | B43: 1893 | C43: 2000 | D43: 3778 | E43: 8875 | F43: 12286 | G43: 5111 | H43: 5388 | I43: 5377 | J43: 4709 | K43: 8144 | L43: 3827 | M43: 2205
C44: =+C43/B36 -> 0.0029264367 | D44: =+D43/C36 -> 0.0055489625 | E44: =+E43/D36 -> 0.013102455 | F44: =+F43/E36 -> 0.018283799 | G44: =+G43/F36 -> 0.0077097246 | H44: =+H43/G36 -> 0.0081516436 | I44: =+I43/H36 -> 0.0081008318 | J44: =+J43/I36 -> 0.0073894718 | ... N44: =+N43/M36 -> 0
A46: Ctas CC | B46: 392801 | C46: 399152 | D46: 400174 | E46: 410224 | F46: 406744 | G46: 398727 | H46: =395565+7839 -> 403404 | I46: 419816 | J46: 434794 | K46: 443791 | L46: 452522 | M46: 434794 | O46: =+(Resumen!B17*1000)*(M46/(M46+M23)) -> 569915.59 | P46: =O46/Q46 -> 1.4167865 | Q46: 402259.33 | R46: 401421.16 | S46: 403458.38 | T46: 398180.3 | U46: 404509.63 | V46: 406121.48 | W46: 408325.74 | X46: 412957.01 | Y46: 417146.28 | Z46: 427747.27
A47: Actividad | B47: 0.575 | C47: 0.586 | D47: 0.591 | E47: 0.61 | F47: =+F46/F36 -> 0.6135559 | G47: =+G46/G36 -> 0.60324432 | H47: =+H46/H36 -> 0.60775673 | I47: =+I46/I36 -> 0.65878498 | J47: =+J46/J36 -> 0.67518895 | K47: =+K46/K36 -> 0.68896455 | L47: =+L46/L36 -> 0.69978567 | M47: =+M46/M36 -> 0.65870992 | ... O47: =+O46/O36 -> 0.84507768 | P47: =O47/Q47 -> 1.3789655 | Q47: 0.61283452 | R47: 0.61872879 | S47: 0.62806152 | T47: 0.63009902 | U47: 0.63961542 | V47: 0.64030433 | W47: 0.64073028 | X47: 0.64437781 | Y47: 0.64699048 | Z47: 0.65916458
A48: CM | B48: 972 | C48: 1056 | D48: 1100 | E48: 1268 | F48: =+F29/F46 -> 1135.7855 | G48: =+G29/G46 -> 995.17031 | H48: =+H29/H46 -> 1364.8897 | I48: =+I29/I46 -> 1238.4097 | J48: =+J29/J46 -> 1365.0095 | K48: =+K29/K46 -> 1329.566 | L48: =+L29/L46 -> 1492.376 | M48: =+M29/M46 -> 1578.8554 | ... O48: =+O29/O46 -> #REF! | P48: =O48/Q48 -> #REF! | Q48: 1113.4213 | R48: 1062.1601 | S48: 1129.2081 | T48: 1065.8626 | U48: 1153.9901 | V48: 1094.5615 | W48: 1062.6388 | X48: 1124.7991 | Y48: 1159.4925 | Z48: 1241.4907
A51: NACIONAL
A53: AMEX | B53: 202009 | C53: 202010 | D53: 202011 | E53: 202012 | F53: 202101 | G53: 202102 | H53: 202103 | I53: 202104 | J53: 202105 | K53: 202106 | L53: 202107 | M53: 202108 | N53: 202109 | O53: =O3 -> Proyec Set
A54: Facturación
A55: Real | B55: 1.2619396e+08 | C55: 1.3791307e+08 | D55: 1.3740784e+08 | E55: 1.6595184e+08 | F55: 1.4454697e+08 | G55: 1.200549e+08 | H55: 1.7052119e+08 | I55: 1.5259391e+08 | J55: 1.6796727e+08 | K55: 1.7055347e+08 | L55: 1.9763851e+08 | M55: 2.0516241e+08 | N55: =N81 -> 1.7996425e+08 | O55: =N55/N5*O5 -> #REF! | P55: =O55/H55-1 -> #REF!
A56: %Share marca | B56: =+B55/(B55+B60) -> 0.26805213 | C56: =+C55/(C55+C60) -> 0.26466827 | D56: =+D55/(D55+D60) -> 0.25985125 | E56: =+E55/(E55+E60) -> 0.26166809 | F56: =+F55/(F55+F60) -> 0.26116617 | G56: =+G55/(G55+G60) -> 0.25708853 | H56: =+H55/(H55+H60) -> 0.25897211 | I56: =+I55/(I55+I60) -> 0.25638259 | ... O56: =+O55/(O55+O60) -> #REF!
A58: MC + VISA | B58: 202009 | C58: 202010 | D58: 202011 | E58: 202012 | F58: 202101 | G58: 202102 | H58: 202103 | I58: 202104 | J58: 202105 | K58: 202106 | L58: 202107 | M58: 202108 | N58: 202109 | O58: =O3 -> Proyec Set
A59: Facturación
A60: Real | B60: 3.4458745e+08 | C60: 3.8316589e+08 | D60: 3.9138638e+08 | E60: 4.6825557e+08 | F60: 4.0892047e+08 | G60: 3.4692392e+08 | H60: 4.879327e+08 | I60: 4.4258657e+08 | J60: 4.8525855e+08 | K60: 4.955812e+08 | L60: 5.7017241e+08 | M60: 5.8436591e+08 | N60: =N80+N82 -> 5.1929902e+08 | O60: =N60/N29*O29 -> #REF! | P60: =O60/H60-1 -> #REF!
A61: %Share marca | B61: =+B60/(B60+B55) -> 0.73194787 | C61: =+C60/(C60+C55) -> 0.73533173 | D61: =+D60/(D60+D55) -> 0.74014875 | E61: =+E60/(E60+E55) -> 0.73833191 | F61: =+F60/(F60+F55) -> 0.73883383 | G61: =+G60/(G60+G55) -> 0.74291147 | H61: =+H60/(H60+H55) -> 0.74102789 | I61: =+I60/(I60+I55) -> 0.74361741 | ... O61: =+O60/(O60+O55) -> #REF!
A64: NACIONAL SIN PAGO SERVICIOS | Q64: Proyección Crecimiento Amex
A66: AMEX | B66: 202009 | C66: 202010 | D66: 202011 | E66: 202012 | F66: 202101 | G66: 202102 | H66: 202103 | I66: 202104 | J66: 202105 | K66: 202106 | L66: 202107 | M66: 202108 | N66: 202109 | O66: =O3 -> Proyec Set | Q66: 202103 | R66: 202104 | S66: 202105 | T66: 202106 | U66: 202107 | V66: 202108 | W66: 202109 | X66: 202110 | Y66: 202111 | Z66: 202112
A67: Facturación
A68: Real | B68: 86044046 | C68: 96806695 | D68: 97264038 | E68: 1.2133699e+08 | F68: 1.0260285e+08 | G68: 76809459 | H68: 1.1894516e+08 | I68: 1.0719414e+08 | J68: 1.1907187e+08 | K68: 1.2268076e+08 | L68: 1.4265819e+08 | M68: 1.4643147e+08 | N68: =N90 -> 1.3144325e+08 | O68: =N68/N5*O5 -> #REF! | P68: =+O68/R68 -> #REF! | Q68: =+Q69*Q5 -> 99167291 | R68: 94340143 | S68: 1.0675684e+08 | T68: 1.0206821e+08 | U68: 1.1021408e+08 | V68: 1.0418875e+08 | W68: 1.031116e+08 | X68: 1.1015251e+08 | Y68: 1.1809222e+08 | Z68: 1.3624978e+08
A69: % sobre total | B69: =+B68/B5 -> 0.60982833 | C69: =+C68/C5 -> 0.62603008 | D69: =+D68/D5 -> 0.607463 | E69: =+E68/E5 -> 0.64106192 | F69: =+F68/F5 -> 0.61257787 | G69: =+G68/G5 -> 0.54829507 | H69: =+H68/H5 -> 0.601034 | I69: =+I68/I5 -> 0.57355147 | ... O69: =+O68/O5 -> #REF! | P69: =+O69-R69 -> #REF! | Q69: 0.61 | R69: =R68/R5 -> 0.59762121 | S69: =S68/S5 -> 0.61942577
A70: %Share marca | B70: =+B68/(B68+B74) -> 0.25272958 | C70: =+C68/(C68+C74) -> 0.25027282 | D70: =+D68/(D68+D74) -> 0.24620803 | E70: =+E68/(E68+E74) -> 0.24929692 | F70: =+F68/(F68+F74) -> 0.24755103 | G70: =+G68/(G68+G74) -> 0.23647106 | H70: =+H68/(H68+H74) -> 0.24397821 | I70: =+I68/(I68+I74) -> 0.24140033 | ... O70: =+O68/(O68+O74) -> #REF! | Q70: =+Q68/(Q68+Q74) -> 0.24362865 | R70: =+R68/(R68+R74) -> 0.24329221 | S70: =+S68/(S68+S74) -> 0.25706648
A72: MC + VISA | B72: 202009 | C72: 202010 | D72: 202011 | E72: 202012 | F72: 202101 | G72: 202102 | H72: 202103 | I72: 202104 | J72: 202105 | K72: 202106 | L72: 202107 | M72: 202108 | N72: 202109 | O72: =O3 -> Proyec Set
A73: Facturación
A74: Real | B74: 2.544149e+08 | C74: 2.8999797e+08 | D74: 2.9778416e+08 | E74: 3.6537978e+08 | F74: 3.1186867e+08 | G74: 2.4800602e+08 | H74: 3.6857853e+08 | I74: 3.368572e+08 | J74: 3.7244189e+08 | K74: 3.8175498e+08 | L74: 4.3970836e+08 | M74: 4.4579107e+08 | N74: =N89+N91 -> 4.0202519e+08 | O74: =N74/N29*O29 -> #REF! | P74: =+O74/R74 -> #REF! | Q74: =+Q75*Q29 -> 3.0787553e+08 | R74: 293424608 | S74: 3.0853198e+08 | T74: 2.8968205e+08 | U74: 3.1613794e+08 | V74: 3.011932e+08 | W74: 2.9300532e+08 | X74: 3.100323e+08 | Y74: 3.2633539e+08 | Z74: 3.6978519e+08
A75: % sobre total | B75: =+B74/B29 -> 0.66642066 | C75: =+C74/C29 -> 0.68795999 | D75: =+D74/D29 -> 0.67668413 | E75: =+E74/E29 -> 0.70259467 | F75: =+F74/F29 -> 0.6750785 | G75: =+G74/G29 -> 0.62501316 | H75: =+H74/H29 -> 0.66941014 | I75: =+I74/I29 -> 0.64792168 | ... O75: =+O74/O29 -> #REF! | P75: =+O75-R75 -> #REF! | Q75: 0.6874 | R75: =R74/R29 -> 0.68818671 | S75: =S74/S29 -> 0.68567813
A76: %Share marca | B76: =+B74/(B74+B68) -> 0.74727042 | C76: =+C74/(C74+C68) -> 0.74972718 | D76: =+D74/(D74+D68) -> 0.75379197 | E76: =+E74/(E74+E68) -> 0.75070308 | F76: =+F74/(F74+F68) -> 0.75244897 | G76: =+G74/(G74+G68) -> 0.76352894 | H76: =+H74/(H74+H68) -> 0.75602179 | I76: =+I74/(I74+I68) -> 0.75859967 | ... O76: =+O74/(O74+O68) -> #REF! | Q76: =+Q74/(Q74+Q68) -> 0.75637135 | R76: =+R74/(R74+R68) -> 0.75670779 | S76: =+S74/(S74+S68) -> 0.74293352
N79: NACIONAL
N80: 5.1419106e+08 | O80: VISA
N81: 1.7996425e+08 | O81: AMEX
N82: 5107960 | O82: MC
N88: NAC. SIN PDS
N89: 3.9828346e+08 | O89: VISA
N90: 1.3144325e+08 | O90: AMEX
N91: 3741727.9 | O91: MC

Sheet Ejer
A1: CRÉDITO TOTAL
A2: Día | B2: 2023 | C2: acum | D2: porc acum | F2: Día | G2: 2022 | H2: acum | I2: porc acum
A3: 1 | B3: 58.795134 | C3: =+B3 -> 58.795134 | D3: =C3/$C$30 -> 0.042690215 | F3: 1 | G3: 44.8562 | H3: =+G3 -> 44.8562 | I3: =H3/$H$30 -> 0.040484978 | K3: =B3/G3-1 -> 0.3107471
A4: =+A3+1 -> 2 | B4: 52.801427 | C4: =+C3+B4 -> 111.59656 | D4: =C4/$C$30 -> 0.081028494 | F4: =+F3+1 -> 2 | G4: 39.832003 | H4: =+H3+G4 -> 84.688203 | I4: =H4/$H$30 -> 0.076435365 | K4: =B4/G4-1 -> 0.3256031
A5: =+A4+1 -> 3 | B5: 49.644029 | C5: =+C4+B5 -> 161.24059 | D5: =C5/$C$30 -> 0.11707424 | F5: =+F4+1 -> 3 | G5: 38.556207 | H5: =+H4+G5 -> 123.24441 | I5: =H5/$H$30 -> 0.11123428 | K5: =B5/G5-1 -> 0.28757551
A6: =+A5+1 -> 4 | B6: 45.074899 | C6: =+C5+B6 -> 206.31549 | D6: =C6/$C$30 -> 0.14980241 | F6: =+F5+1 -> 4 | G6: 39.451713 | H6: =+H5+G6 -> 162.69612 | I6: =H6/$H$30 -> 0.14684144 | K6: =B6/G6-1 -> 0.14253339
A7: =+A6+1 -> 5 | B7: 34.41971 | C7: =+C6+B7 -> 240.7352 | D7: =C7/$C$30 -> 0.17479401 | F7: =+F6+1 -> 5 | G7: 35.794442 | H7: =+H6+G7 -> 198.49057 | I7: =H7/$H$30 -> 0.17914772 | K7: =B7/G7-1 -> -0.038406311
A8: =+A7+1 -> 6 | B8: 52.984139 | C8: =+C7+B8 -> 293.71934 | D8: =C8/$C$30 -> 0.21326496 | F8: =+F7+1 -> 6 | G8: 25.382438 | H8: =+H7+G8 -> 223.873 | I8: =H8/$H$30 -> 0.20205665 | K8: =B8/G8-1 -> 1.087433
A9: =+A8+1 -> 7 | B9: 48.442437 | C9: =+C8+B9 -> 342.16177 | D9: =C9/$C$30 -> 0.24843824 | F9: =+F8+1 -> 7 | G9: 45.967201 | H9: =+H8+G9 -> 269.8402 | I9: =H9/$H$30 -> 0.24354436 | K9: =B9/G9-1 -> 0.053847886
A10: =+A9+1 -> 8 | B10: 48.908099 | C10: =+C9+B10 -> 391.06987 | D10: =C10/$C$30 -> 0.28394964 | F10: =+F9+1 -> 8 | G10: 37.995751 | H10: =+H9+G10 -> 307.83595 | I10: =H10/$H$30 -> 0.27783744 | K10: =B10/G10-1 -> 0.28719919
A11: =+A10+1 -> 9 | B11: 48.710571 | C11: =+C10+B11 -> 439.78044 | D11: =C11/$C$30 -> 0.31931761 | F11: =+F10+1 -> 9 | G11: 38.596293 | H11: =+H10+G11 -> 346.43225 | I11: =H11/$H$30 -> 0.31267254 | K11: =B11/G11-1 -> 0.2620531
A12: =+A11+1 -> 10 | B12: 48.098174 | C12: =+C11+B12 -> 487.87862 | D12: =C12/$C$30 -> 0.35424093 | F12: =+F11+1 -> 10 | G12: 38.480418 | H12: =+H11+G12 -> 384.91267 | I12: =H12/$H$30 -> 0.34740305 | K12: =B12/G12-1 -> 0.24993899
A13: =+A12+1 -> 11 | B13: 45.725752 | C13: =+C12+B13 -> 533.60437 | D13: =C13/$C$30 -> 0.38744168 | F13: =+F12+1 -> 11 | G13: 36.8558 | H13: =+H12+G13 -> 421.76847 | I13: =H13/$H$30 -> 0.38066727 | K13: =B13/G13-1 -> 0.24066639
A14: =+A13+1 -> 12 | B14: 34.331436 | C14: =+C13+B14 -> 567.93581 | D14: =C14/$C$30 -> 0.41236919 | F14: =+F13+1 -> 12 | G14: 39.054951 | H14: =+H13+G14 -> 460.82342 | I14: =H14/$H$30 -> 0.41591633 | K14: =B14/G14-1 -> -0.12094535
A15: =+A14+1 -> 13 | B15: 54.432421 | C15: =+C14+B15 -> 622.36823 | D15: =C15/$C$30 -> 0.45189171 | F15: =+F14+1 -> 13 | G15: 28.152601 | H15: =+H14+G15 -> 488.97602 | I15: =H15/$H$30 -> 0.44132546 | K15: =B15/G15-1 -> 0.93347749
... A29: =+A28+1 -> 27 | B29: 56.715589 | C29: =+C28+B29 -> 1313.9573 | D29: =C29/$C$30 -> 0.95404354 | F29: =+F28+1 -> 27 | G29: 28.915498 | H29: =+H28+G29 -> 1051.107 | I29: =H29/$H$30 -> 0.94867693 | K29: =B29/G29-1 -> 0.96142528
A30: =+A29+1 -> 28 | B30: =59.293569892968+2+1+1 -> 63.29357 | C30: =+C29+B30 -> 1377.2508 | D30: =C30/$C$30 -> 1 | F30: =+F29+1 -> 28 | G30: 56.864496 | H30: =+H29+G30 -> 1107.9715 | I30: =H30/$H$30 -> 1 | K30: =B30/G30-1 -> 0.11305955
B31: =SUM(B3:B30) -> 1377.2508 | G31: =SUM(G3:G30) -> 1107.9715

Sheet CuotasActual
A1: PASE A CUOTAS | J1: COMPRA EN CUOTAS
A3: MES ACTUAL | B3: 202312
A5: CODMES | B5: CA_NIVEL | C5: NumCuotas | D5: FactuPonderada | E5: FactuCuotas | F5: ClientesCuotas | G5: %FactuCuota | H5: %Cuentas | J5: CODMES | K5: CA_NIVEL | L5: NumCuotas | M5: FactuPonderada | N5: FactuCuotas | O5: ClientesCuotas | P5: %FactuCuota | Q5: %Cuentas | S5: % CuotasT
A6: 201901 | C6: 8.0340876 | D6: 210.84555 | E6: 26.24387 | F6: 38.417 | G6: =IF(A6="","",E6/IF(A6=$B$3,Resumen!#REF!,VLOOKUP(A6,Graf_PowerBI!$A$4:$D$39,3,0))) -> 0.042424563 | H6: =IF(A6="","",F6/IF(A6=$B$3,Resumen!#REF!,VLOOKUP(A6,Graf_PowerBI!$A$4:$D$39,4,0))) -> 0.063723205 | J6: 201901 | L6: 8.0124278 | M6: 764.81064 | N6: 95.453046 | O6: 141.213 | P6: =IF(J6="","",N6/IF(J6=$B$3,Resumen!#REF!,VLOOKUP(J6,Graf_PowerBI!$A$4:$D$39,3,0))) -> 0.15430475 | Q6: =IF(J6="","",O6/IF(J6=$B$3,Resumen!#REF!,VLOOKUP(J6,Graf_PowerBI!$A$4:$D$39,4,0))) -> 0.23423341 | S6: =IF(A6="","",P6+G6) -> 0.19672931
A7: 201902 | C7: 8.4577165 | D7: 198.3948 | E7: 23.457253 | F7: 34.644 | G7: =IF(A7="","",E7/IF(A7=$B$3,Resumen!#REF!,VLOOKUP(A7,Graf_PowerBI!$A$4:$D$39,3,0))) -> 0.037916468 | H7: =IF(A7="","",F7/IF(A7=$B$3,Resumen!#REF!,VLOOKUP(A7,Graf_PowerBI!$A$4:$D$39,4,0))) -> 0.057023969 | J7: 201902 | L7: 7.9893946 | M7: 784.43349 | N7: 98.184347 | O7: 144.096 | P7: =IF(J7="","",N7/IF(J7=$B$3,Resumen!#REF!,VLOOKUP(J7,Graf_PowerBI!$A$4:$D$39,3,0))) -> 0.15870586 | Q7: =IF(J7="","",O7/IF(J7=$B$3,Resumen!#REF!,VLOOKUP(J7,Graf_PowerBI!$A$4:$D$39,4,0))) -> 0.23718179 | S7: =IF(A7="","",P7+G7) -> 0.19662233
A8: 201903 | C8: 8.2244518 | D8: 198.26134 | E8: 24.106329 | F8: 34.955 | G8: =IF(A8="","",E8/IF(A8=$B$3,Resumen!#REF!,VLOOKUP(A8,Graf_PowerBI!$A$4:$D$39,3,0))) -> 0.03450047 | H8: =IF(A8="","",F8/IF(A8=$B$3,Resumen!#REF!,VLOOKUP(A8,Graf_PowerBI!$A$4:$D$39,4,0))) -> 0.055917085 | J8: 201903 | L8: 8.0995955 | M8: 985.10087 | N8: 121.62347 | O8: 163.298 | P8: =IF(J8="","",N8/IF(J8=$B$3,Resumen!#REF!,VLOOKUP(J8,Graf_PowerBI!$A$4:$D$39,3,0))) -> 0.17406494 | Q8: =IF(J8="","",O8/IF(J8=$B$3,Resumen!#REF!,VLOOKUP(J8,Graf_PowerBI!$A$4:$D$39,4,0))) -> 0.26122581 | S8: =IF(A8="","",P8+G8) -> 0.20856541
A9: 201904 | C9: 7.9459677 | D9: 219.79775 | E9: 27.661545 | F9: 41.129 | G9: =IF(A9="","",E9/IF(A9=$B$3,Resumen!#REF!,VLOOKUP(A9,Graf_PowerBI!$A$4:$D$39,3,0))) -> 0.041550454 | H9: =IF(A9="","",F9/IF(A9=$B$3,Resumen!#REF!,VLOOKUP(A9,Graf_PowerBI!$A$4:$D$39,4,0))) -> 0.065169718 | J9: 201904 | L9: 7.9402953 | M9: 846.95053 | N9: 106.66487 | O9: 152.714 | P9: =IF(J9="","",N9/IF(J9=$B$3,Resumen!#REF!,VLOOKUP(J9,Graf_PowerBI!$A$4:$D$39,3,0))) -> 0.16022147 | Q9: =IF(J9="","",O9/IF(J9=$B$3,Resumen!#REF!,VLOOKUP(J9,Graf_PowerBI!$A$4:$D$39,4,0))) -> 0.24197837 | S9: =IF(A9="","",P9+G9) -> 0.20177193
A10: 201905 | C10: 7.6265675 | D10: 254.89851 | E10: 33.422442 | F10: 49.01 | G10: =IF(A10="","",E10/IF(A10=$B$3,Resumen!#REF!,VLOOKUP(A10,Graf_PowerBI!$A$4:$D$39,3,0))) -> 0.046157786 | H10: =IF(A10="","",F10/IF(A10=$B$3,Resumen!#REF!,VLOOKUP(A10,Graf_PowerBI!$A$4:$D$39,4,0))) -> 0.076164102 | J10: 201905 | L10: 7.6657276 | M10: 909.01235 | N10: 118.58135 | O10: 166.454 | P10: =IF(J10="","",N10/IF(J10=$B$3,Resumen!#REF!,VLOOKUP(J10,Graf_PowerBI!$A$4:$D$39,3,0))) -> 0.16376579 | Q10: =IF(J10="","",O10/IF(J10=$B$3,Resumen!#REF!,VLOOKUP(J10,Graf_PowerBI!$A$4:$D$39,4,0))) -> 0.25867822 | S10: =IF(A10="","",P10+G10) -> 0.20992358
A11: 201906 | C11: 7.8949816 | D11: 258.53725 | E11: 32.747036 | F11: 48.143 | G11: =IF(A11="","",E11/IF(A11=$B$3,Resumen!#REF!,VLOOKUP(A11,Graf_PowerBI!$A$4:$D$39,3,0))) -> 0.047193985 | H11: =IF(A11="","",F11/IF(A11=$B$3,Resumen!#REF!,VLOOKUP(A11,Graf_PowerBI!$A$4:$D$39,4,0))) -> 0.074503316 | J11: 201906 | L11: 7.3464946 | M11: 788.10696 | N11: 107.2766 | O11: 158.692 | P11: =IF(J11="","",N11/IF(J11=$B$3,Resumen!#REF!,VLOOKUP(J11,Graf_PowerBI!$A$4:$D$39,3,0))) -> 0.15460362 | Q11: =IF(J11="","",O11/IF(J11=$B$3,Resumen!#REF!,VLOOKUP(J11,Graf_PowerBI!$A$4:$D$39,4,0))) -> 0.24558254 | S11: =IF(A11="","",P11+G11) -> 0.2017976
A12: 201907 | C12: 7.8846542 | D12: 288.52096 | E12: 36.592722 | F12: 48.534 | G12: =IF(A12="","",E12/IF(A12=$B$3,Resumen!#REF!,VLOOKUP(A12,Graf_PowerBI!$A$4:$D$39,3,0))) -> 0.047706243 | H12: =IF(A12="","",F12/IF(A12=$B$3,Resumen!#REF!,VLOOKUP(A12,Graf_PowerBI!$A$4:$D$39,4,0))) -> 0.073776809 | J12: 201907 | L12: 7.5266607 | M12: 729.38732 | N12: 96.907161 | O12: 153.899 | P12: =IF(J12="","",N12/IF(J12=$B$3,Resumen!#REF!,VLOOKUP(J12,Graf_PowerBI!$A$4:$D$39,3,0))) -> 0.12633869 | Q12: =IF(J12="","",O12/IF(J12=$B$3,Resumen!#REF!,VLOOKUP(J12,Graf_PowerBI!$A$4:$D$39,4,0))) -> 0.23394274 | S12: =IF(A12="","",P12+G12) -> 0.17404494
A13: 201908 | C13: 8.2417557 | D13: 362.88222 | E13: 44.029723 | F13: 54.977 | G13: =IF(A13="","",E13/IF(A13=$B$3,Resumen!#REF!,VLOOKUP(A13,Graf_PowerBI!$A$4:$D$39,3,0))) -> 0.059573377 | H13: =IF(A13="","",F13/IF(A13=$B$3,Resumen!#REF!,VLOOKUP(A13,Graf_PowerBI!$A$4:$D$39,4,0))) -> 0.082931826 | J13: 201908 | L13: 7.615164 | M13: 735.87248 | N13: 96.63252 | O13: 155.76 | P13: =IF(J13="","",N13/IF(J13=$B$3,Resumen!#REF!,VLOOKUP(J13,Graf_PowerBI!$A$4:$D$39,3,0))) -> 0.13074635 | Q13: =IF(J13="","",O13/IF(J13=$B$3,Resumen!#REF!,VLOOKUP(J13,Graf_PowerBI!$A$4:$D$39,4,0))) -> 0.23496119 | S13: =IF(A13="","",P13+G13) -> 0.19031973
A14: 201909 | C14: 8.1190323 | D14: 321.9831 | E14: 39.657818 | F14: 54.455 | G14: =IF(A14="","",E14/IF(A14=$B$3,Resumen!#REF!,VLOOKUP(A14,Graf_PowerBI!$A$4:$D$39,3,0))) -> 0.05590952 | H14: =IF(A14="","",F14/IF(A14=$B$3,Resumen!#REF!,VLOOKUP(A14,Graf_PowerBI!$A$4:$D$39,4,0))) -> 0.081795951 | J14: 201909 | L14: 7.857218 | M14: 701.577 | N14: 89.290764 | O14: 150.564 | P14: =IF(J14="","",N14/IF(J14=$B$3,Resumen!#REF!,VLOOKUP(J14,Graf_PowerBI!$A$4:$D$39,3,0))) -> 0.12588196 | Q14: =IF(J14="","",O14/IF(J14=$B$3,Resumen!#REF!,VLOOKUP(J14,Graf_PowerBI!$A$4:$D$39,4,0))) -> 0.22615968 | S14: =IF(A14="","",P14+G14) -> 0.18179148
A15: 201910 | C15: 8.0794453 | D15: 328.3598 | E15: 40.641379 | F15: 55.312 | G15: =IF(A15="","",E15/IF(A15=$B$3,Resumen!#REF!,VLOOKUP(A15,Graf_PowerBI!$A$4:$D$39,3,0))) -> 0.054062851 | H15: =IF(A15="","",F15/IF(A15=$B$3,Resumen!#REF!,VLOOKUP(A15,Graf_PowerBI!$A$4:$D$39,4,0))) -> 0.082250406 | J15: 201910 | L15: 7.7393628 | M15: 692.18519 | N15: 89.436973 | O15: 151.034 | P15: =IF(J15="","",N15/IF(J15=$B$3,Resumen!#REF!,VLOOKUP(J15,Graf_PowerBI!$A$4:$D$39,3,0))) -> 0.11897278 | Q15: =IF(J15="","",O15/IF(J15=$B$3,Resumen!#REF!,VLOOKUP(J15,Graf_PowerBI!$A$4:$D$39,4,0))) -> 0.22459155 | S15: =IF(A15="","",P15+G15) -> 0.17303563
A16: 201911 | C16: 7.8043405 | D16: 318.42462 | E16: 40.800964 | F16: 54.519 | G16: =IF(A16="","",E16/IF(A16=$B$3,Resumen!#REF!,VLOOKUP(A16,Graf_PowerBI!$A$4:$D$39,3,0))) -> 0.05236864 | H16: =IF(A16="","",F16/IF(A16=$B$3,Resumen!#REF!,VLOOKUP(A16,Graf_PowerBI!$A$4:$D$39,4,0))) -> 0.080870846 | J16: 201911 | L16: 8.5526016 | M16: 796.26571 | N16: 93.102163 | O16: 145.763 | P16: =IF(J16="","",N16/IF(J16=$B$3,Resumen!#REF!,VLOOKUP(J16,Graf_PowerBI!$A$4:$D$39,3,0))) -> 0.119498 | Q16: =IF(J16="","",O16/IF(J16=$B$3,Resumen!#REF!,VLOOKUP(J16,Graf_PowerBI!$A$4:$D$39,4,0))) -> 0.21621778 | S16: =IF(A16="","",P16+G16) -> 0.17186664
A17: 201912 | C17: 7.9180256 | D17: 356.189 | E17: 44.984572 | F17: 56.381 | G17: =IF(A17="","",E17/IF(A17=$B$3,Resumen!#REF!,VLOOKUP(A17,Graf_PowerBI!$A$4:$D$39,3,0))) -> 0.052819748 | H17: =IF(A17="","",F17/IF(A17=$B$3,Resumen!#REF!,VLOOKUP(A17,Graf_PowerBI!$A$4:$D$39,4,0))) -> 0.083014806 | J17: 201912 | L17: 7.8981925 | M17: 899.7026 | N17: 113.91247 | O17: 167.331 | P17: =IF(J17="","",N17/IF(J17=$B$3,Resumen!#REF!,VLOOKUP(J17,Graf_PowerBI!$A$4:$D$39,3,0))) -> 0.13375314 | Q17: =IF(J17="","",O17/IF(J17=$B$3,Resumen!#REF!,VLOOKUP(J17,Graf_PowerBI!$A$4:$D$39,4,0))) -> 0.24637645 | S17: =IF(A17="","",P17+G17) -> 0.18657289
... A41: 202112 | C41: 8.12415 | D41: 307.1537 | E41: 37.807488 | F41: 40.107 | G41: =IF(A41="","",E41/IF(A41=$B$3,Resumen!#REF!,VLOOKUP(A41,Graf_PowerBI!$A$4:$D$39,3,0))) -> 0.031359392 | H41: =IF(A41="","",F41/IF(A41=$B$3,Resumen!#REF!,VLOOKUP(A41,Graf_PowerBI!$A$4:$D$39,4,0))) -> 0.058336012 | J41: 202112 | L41: 6.7390228 | M41: 709.98188 | N41: 105.35383 | O41: 130.128 | P41: =IF(J41="","",N41/IF(J41=$B$3,Resumen!#REF!,VLOOKUP(J41,Graf_PowerBI!$A$4:$D$39,3,0))) -> 0.087385656 | Q41: =IF(J41="","",O41/IF(J41=$B$3,Resumen!#REF!,VLOOKUP(J41,Graf_PowerBI!$A$4:$D$39,4,0))) -> 0.18927241 | S41: =IF(A41="","",P41+G41) -> 0.11874505
A42: 202201 | C42: 8.4431776 | D42: 333.58613 | E42: 39.509548 | F42: 43.41 | G42: =IF(A42="","",E42/IF(A42=$B$3,Resumen!#REF!,VLOOKUP(A42,Graf_PowerBI!$A$4:$D$40,3,0))) -> 0.037123913 | H42: =IF(A42="","",F42/IF(A42=$B$3,Resumen!#REF!,VLOOKUP(A42,Graf_PowerBI!$A$4:$D$45,4,0))) -> 0.063084194 | J42: 202201 | L42: 7.1694974 | M42: 553.71401 | N42: 77.231915 | O42: 101.7 | P42: =IF(J42="","",N42/IF(J42=$B$3,Resumen!#REF!,VLOOKUP(J42,Graf_PowerBI!$A$4:$D$40,3,0))) -> 0.072568558 | Q42: =IF(J42="","",O42/IF(J42=$B$3,Resumen!#REF!,VLOOKUP(J42,Graf_PowerBI!$A$4:$D$40,4,0))) -> 0.14779227 | S42: =IF(A42="","",P42+G42) -> 0.10969247
A43: 202202 | C43: 8.3032871 | D43: 350.97508 | E43: 42.269413 | F43: 44.721 | G43: =IF(A43="","",E43/IF(A43=$B$3,Resumen!#REF!,VLOOKUP(A43,Graf_PowerBI!$A$4:$D$42,3,0))) -> 0.038150273 | H43: =IF(A43="","",F43/IF(A43=$B$3,Resumen!#REF!,VLOOKUP(A43,Graf_PowerBI!$A$4:$D$45,4,0))) -> 0.063678822 | J43: 202202 | L43: 7.0235539 | M43: 644.89232 | N43: 91.81852 | O43: 117.664 | P43: =IF(J43="","",N43/IF(J43=$B$3,Resumen!#REF!,VLOOKUP(J43,Graf_PowerBI!$A$4:$D$45,3,0))) -> 0.082870835 | Q43: =IF(J43="","",O43/IF(J43=$B$3,Resumen!#REF!,VLOOKUP(J43,Graf_PowerBI!$A$4:$D$45,4,0))) -> 0.16754332 | S43: =IF(A43="","",P43+G43) -> 0.12102111
A44: 202203 | C44: 8.6801252 | D44: 457.85747 | E44: 52.747795 | F44: 51.606 | G44: =IF(A44="","",E44/IF(A44=$B$3,Resumen!#REF!,VLOOKUP(A44,Graf_PowerBI!$A$4:$D$42,3,0))) -> 0.040945984 | H44: =IF(A44="","",F44/IF(A44=$B$3,Resumen!#REF!,VLOOKUP(A44,Graf_PowerBI!$A$4:$D$45,4,0))) -> 0.07058727 | J44: 202203 | L44: 6.9051624 | M44: 771.45359 | N44: 111.72128 | O44: 134.122 | P44: =IF(J44="","",N44/IF(J44=$B$3,Resumen!#REF!,VLOOKUP(J44,Graf_PowerBI!$A$4:$D$45,3,0))) -> 0.086724721 | Q44: =IF(J44="","",O44/IF(J44=$B$3,Resumen!#REF!,VLOOKUP(J44,Graf_PowerBI!$A$4:$D$45,4,0))) -> 0.18345359 | S44: =IF(A44="","",P44+G44) -> 0.12767071
A45: 202204 | C45: 8.4735984 | D45: 421.07959 | E45: 49.693126 | F45: 51.064 | G45: =IF(A45="","",E45/IF(A45=$B$3,Resumen!#REF!,VLOOKUP(A45,Graf_PowerBI!$A$4:$D$48,3,0))) -> 0.041004784 | H45: =IF(A45="","",F45/IF(A45=$B$3,Resumen!#REF!,VLOOKUP(A45,Graf_PowerBI!$A$4:$D$48,4,0))) -> 0.069490997 | J45: 202204 | L45: 6.8335609 | M45: 699.87006 | N45: 102.4166 | O45: 130.679 | P45: =IF(J45="","",N45/IF(J45=$B$3,Resumen!#REF!,VLOOKUP(J45,Graf_PowerBI!$A$4:$D$48,3,0))) -> 0.084510089 | Q45: =IF(J45="","",O45/IF(J45=$B$3,Resumen!#REF!,VLOOKUP(J45,Graf_PowerBI!$A$4:$D$48,4,0))) -> 0.17783593 | S45: =IF(A45="","",P45+G45) -> 0.12551487
A46: 202205 | C46: 8.4300888 | D46: 406.25766 | E46: 48.191385 | F46: 51.617 | G46: =IF(A46="","",E46/IF(A46=$B$3,Resumen!#REF!,VLOOKUP(A46,Graf_PowerBI!$A$4:$D$48,3,0))) -> 0.03686577 | H46: =IF(A46="","",F46/IF(A46=$B$3,Resumen!#REF!,VLOOKUP(A46,Graf_PowerBI!$A$4:$D$48,4,0))) -> 0.06856969 | J46: 202205 | L46: 7.3739646 | M46: 868.29224 | N46: 117.75107 | O46: 142.275 | P46: =IF(J46="","",N46/IF(J46=$B$3,Resumen!#REF!,VLOOKUP(J46,Graf_PowerBI!$A$4:$D$48,3,0))) -> 0.090078009 | Q46: =IF(J46="","",O46/IF(J46=$B$3,Resumen!#REF!,VLOOKUP(J46,Graf_PowerBI!$A$4:$D$48,4,0))) -> 0.18900271 | S46: =IF(A46="","",P46+G46) -> 0.12694378
A47: 202206 | C47: 8.2725407 | D47: 401.01528 | E47: 48.475468 | F47: 51.048 | G47: =IF(A47="","",E47/IF(A47=$B$3,Resumen!#REF!,VLOOKUP(A47,Graf_PowerBI!$A$4:$D$48,3,0))) -> 0.038161526 | H47: =IF(A47="","",F47/IF(A47=$B$3,Resumen!#REF!,VLOOKUP(A47,Graf_PowerBI!$A$4:$D$48,4,0))) -> 0.0668318 | J47: 202206 | L47: 7.3920669 | M47: 821.41597 | N47: 111.12128 | O47: 136.116 | P47: =IF(J47="","",N47/IF(J47=$B$3,Resumen!#REF!,VLOOKUP(J47,Graf_PowerBI!$A$4:$D$48,3,0))) -> 0.087478429 | Q47: =IF(J47="","",O47/IF(J47=$B$3,Resumen!#REF!,VLOOKUP(J47,Graf_PowerBI!$A$4:$D$48,4,0))) -> 0.17820242 | S47: =IF(A47="","",P47+G47) -> 0.12563996
A48: 202207 | C48: 8.219083 | D48: 407.89302 | E48: 49.627558 | F48: 49.496 | G48: =IF(A48="","",E48/IF(A48=$B$3,Resumen!#REF!,VLOOKUP(A48,Graf_PowerBI!$A$4:$D$48,3,0))) -> 0.0362074 | H48: =IF(A48="","",F48/IF(A48=$B$3,Resumen!#REF!,VLOOKUP(A48,Graf_PowerBI!$A$4:$D$48,4,0))) -> 0.064202726 | J48: 202207 | L48: 7.3172294 | M48: 836.72614 | N48: 114.35013 | O48: 135.891 | P48: =IF(J48="","",N48/IF(J48=$B$3,Resumen!#REF!,VLOOKUP(J48,Graf_PowerBI!$A$4:$D$48,3,0))) -> 0.083427859 | Q48: =IF(J48="","",O48/IF(J48=$B$3,Resumen!#REF!,VLOOKUP(J48,Graf_PowerBI!$A$4:$D$48,4,0))) -> 0.17626824 | S48: =IF(A48="","",P48+G48) -> 0.11963526
A49: 202208 | C49: 8.297067 | D49: 448.28831 | E49: 54.029733 | F49: 52.651 | G49: =IF(A49="","",E49/IF(A49=$B$3,Resumen!#REF!,VLOOKUP(A49,Graf_PowerBI!$A$4:$D$48,3,0))) -> 0.03900943 | H49: =IF(A49="","",F49/IF(A49=$B$3,Resumen!#REF!,VLOOKUP(A49,Graf_PowerBI!$A$4:$D$48,4,0))) -> 0.067875642 | J49: 202208 | L49: 7.6134465 | M49: 879.79899 | N49: 115.55857 | O49: 132.598 | P49: =IF(J49="","",N49/IF(J49=$B$3,Resumen!#REF!,VLOOKUP(J49,Graf_PowerBI!$A$4:$D$48,3,0))) -> 0.083433208 | Q49: =IF(J49="","",O49/IF(J49=$B$3,Resumen!#REF!,VLOOKUP(J49,Graf_PowerBI!$A$4:$D$48,4,0))) -> 0.17094024 | S49: =IF(A49="","",P49+G49) -> 0.12244264
A50: 202209 | C50: 8.210851 | D50: 380.39297 | E50: 46.328081 | F50: 49.449 | G50: =IF(A50="","",E50/IF(A50=$B$3,Resumen!#REF!,VLOOKUP(A50,Graf_PowerBI!$A$4:$D$51,3,0))) -> 0.034971962 | H50: =IF(A50="","",F50/IF(A50=$B$3,Resumen!#REF!,VLOOKUP(A50,Graf_PowerBI!$A$4:$D$51,4,0))) -> 0.064034778 | J50: 202209 | L50: 7.5833848 | M50: 805.96511 | N50: 106.28039 | O50: 125.461 | P50: =IF(J50="","",N50/IF(J50=$B$3,Resumen!#REF!,VLOOKUP(J50,Graf_PowerBI!$A$4:$D$48,3,0))) -> 0.080228531 | Q50: =IF(J50="","",O50/IF(J50=$B$3,Resumen!#REF!,VLOOKUP(J50,Graf_PowerBI!$A$4:$D$48,4,0))) -> 0.16246774 | S50: =IF(A50="","",P50+G50) -> 0.11520049
A51: 202210 | C51: 7.6561669 | D51: 383.29308 | E51: 50.063313 | F51: 51.084 | G51: =IF(A51="","",E51/IF(A51=$B$3,Resumen!#REF!,VLOOKUP(A51,Graf_PowerBI!$A$4:$D$51,3,0))) -> 0.034920949 | H51: =IF(A51="","",F51/IF(A51=$B$3,Resumen!#REF!,VLOOKUP(A51,Graf_PowerBI!$A$4:$D$51,4,0))) -> 0.065161238 | J51: 202210 | L51: 7.9603128 | M51: 925.68694 | N51: 116.28776 | O51: 133.218 | P51: =IF(J51="","",N51/IF(J51=$B$3,Resumen!#REF!,VLOOKUP(J51,Graf_PowerBI!$A$4:$D$51,3,0))) -> 0.081114866 | Q51: =IF(J51="","",O51/IF(J51=$B$3,Resumen!#REF!,VLOOKUP(J51,Graf_PowerBI!$A$4:$D$51,4,0))) -> 0.16992894 | S51: =IF(A51="","",P51+G51) -> 0.11603582
A52: 202211 | C52: 8.6910322 | D52: 441.75235 | E52: 50.828525 | F52: 50.505 | G52: =IF(A52="","",E52/IF(A52=$B$3,Resumen!#REF!,VLOOKUP(A52,Graf_PowerBI!$A$4:$D$51,3,0))) -> 0.035039898 | H52: =IF(A52="","",F52/IF(A52=$B$3,Resumen!#REF!,VLOOKUP(A52,Graf_PowerBI!$A$4:$D$51,4,0))) -> 0.063803177 | J52: 202211 | L52: 7.6843578 | M52: 854.51361 | N52: 111.20169 | O52: 126.36 | P52: =IF(J52="","",N52/IF(J52=$B$3,Resumen!#REF!,VLOOKUP(J52,Graf_PowerBI!$A$4:$D$65,3,0))) -> 0.07665963 | Q52: =IF(J52="","",O52/IF(J52=$B$3,Resumen!#REF!,VLOOKUP(J52,Graf_PowerBI!$A$4:$D$65,4,0))) -> 0.15963112 | S52: =IF(A52="","",P52+G52) -> 0.11169953
A53: 202212 | C53: 8.5091924 | D53: 448.07757 | E53: 52.658061 | F53: 51.594 | G53: =IF(A53="","",E53/IF(A53=$B$3,Resumen!#REF!,VLOOKUP(A53,Graf_PowerBI!$A$4:$D$65,3,0))) -> 0.034120971 | H53: =IF(A53="","",F53/IF(A53=$B$3,Resumen!#REF!,VLOOKUP(A53,Graf_PowerBI!$A$4:$D$65,4,0))) -> 0.064625629 | J53: 202212 | L53: 7.5035614 | M53: 975.85481 | N53: 130.05222 | O53: 146.406 | P53: =IF(J53="","",N53/IF(J53=$B$3,Resumen!#REF!,VLOOKUP(J53,Graf_PowerBI!$A$4:$D$65,3,0))) -> 0.08427025 | Q53: =IF(J53="","",O53/IF(J53=$B$3,Resumen!#REF!,VLOOKUP(J53,Graf_PowerBI!$A$4:$D$65,4,0))) -> 0.18338527 | S53: =IF(A53="","",P53+G53) -> 0.11839122
A54: 202301 | C54: 8.45924 | D54: 463.39532 | E54: 54.779781 | F54: 53.49 | G54: =IF(A54="","",E54/IF(A54=$B$3,Resumen!#REF!,VLOOKUP(A54,Graf_PowerBI!$A$4:$D$65,3,0))) -> 0.039065755 | H54: =IF(A54="","",F54/IF(A54=$B$3,Resumen!#REF!,VLOOKUP(A54,Graf_PowerBI!$A$4:$D$65,4,0))) -> 0.067076053 | J54: 202301 | L54: 7.9645575 | M54: 863.33331 | N54: 108.3969 | O54: 123.612 | P54: =IF(J54="","",N54/IF(J54=$B$3,Resumen!#REF!,VLOOKUP(J54,Graf_PowerBI!$A$4:$D$65,3,0))) -> 0.077302364 | Q54: =IF(J54="","",O54/IF(J54=$B$3,Resumen!#REF!,VLOOKUP(J54,Graf_PowerBI!$A$4:$D$65,4,0))) -> 0.15500851 | S54: =IF(A54="","",P54+G54) -> 0.11636812
A55: 202302 | C55: 8.7123853 | D55: 446.86435 | E55: 51.290701 | F55: 52.051 | G55: =IF(A55="","",E55/IF(A55=$B$3,Resumen!#REF!,VLOOKUP(A55,Graf_PowerBI!$A$4:$D$65,3,0))) -> 0.036664963 | H55: =IF(A55="","",F55/IF(A55=$B$3,Resumen!#REF!,VLOOKUP(A55,Graf_PowerBI!$A$4:$D$65,4,0))) -> 0.065281054 | J55: 202302 | L55: 9.1134147 | M55: 1058.5588 | N55: 116.15391 | O55: 126.41 | P55: =IF(J55="","",N55/IF(J55=$B$3,Resumen!#REF!,VLOOKUP(J55,Graf_PowerBI!$A$4:$D$65,3,0))) -> 0.083032184 | Q55: =IF(J55="","",O55/IF(J55=$B$3,Resumen!#REF!,VLOOKUP(J55,Graf_PowerBI!$A$4:$D$65,4,0))) -> 0.15854024 | S55: =IF(A55="","",P55+G55) -> 0.11969715
A56: 202303 | C56: 8.5675974 | D56: 470.33152 | E56: 54.896548 | F56: 53.851 | G56: =IF(A56="","",E56/IF(A56=$B$3,Resumen!#REF!,VLOOKUP(A56,Graf_PowerBI!$A$4:$D$65,3,0))) -> 0.034520165 | H56: =IF(A56="","",F56/IF(A56=$B$3,Resumen!#REF!,VLOOKUP(A56,Graf_PowerBI!$A$4:$D$65,4,0))) -> 0.066346583 | J56: 202303 | L56: 9.5155481 | M56: 1323.6473 | N56: 139.10363 | O56: 139.998 | P56: =IF(J56="","",N56/IF(J56=$B$3,Resumen!#REF!,VLOOKUP(J56,Graf_PowerBI!$A$4:$D$65,3,0))) -> 0.087471447 | Q56: =IF(J56="","",O56/IF(J56=$B$3,Resumen!#REF!,VLOOKUP(J56,Graf_PowerBI!$A$4:$D$65,4,0))) -> 0.17248313 | S56: =IF(A56="","",P56+G56) -> 0.12199161
A57: 202304 | C57: 8.1425214 | D57: 390.30331 | E57: 47.933962 | F57: 78.447 | G57: =IF(A57="","",E57/IF(A57=$B$3,Resumen!#REF!,VLOOKUP(A57,Graf_PowerBI!$A$4:$D$65,3,0))) -> 0.033232411 | H57: =IF(A57="","",F57/IF(A57=$B$3,Resumen!#REF!,VLOOKUP(A57,Graf_PowerBI!$A$4:$D$65,4,0))) -> 0.099231919 | J57: 202304 | L57: 9.2759073 | M57: 1143.4382 | N57: 123.26969 | O57: 130.41 | P57: =IF(J57="","",N57/IF(J57=$B$3,Resumen!#REF!,VLOOKUP(J57,Graf_PowerBI!$A$4:$D$65,3,0))) -> 0.085462351 | Q57: =IF(J57="","",O57/IF(J57=$B$3,Resumen!#REF!,VLOOKUP(J57,Graf_PowerBI!$A$4:$D$65,4,0))) -> 0.16496277 | S57: =IF(A57="","",P57+G57) -> 0.11869476
A58: 202305 | C58: 7.9792081 | D58: 399.89711 | E58: 50.117393 | F58: 51.347 | G58: =IF(A58="","",E58/IF(A58=$B$3,Resumen!#REF!,VLOOKUP(A58,Graf_PowerBI!$A$4:$D$65,3,0))) -> 0.032325649 | H58: =IF(A58="","",F58/IF(A58=$B$3,Resumen!#REF!,VLOOKUP(A58,Graf_PowerBI!$A$4:$D$65,4,0))) -> 0.064451708 | J58: 202305 | L58: 8.9865731 | M58: 1163.8247 | N58: 129.50707 | O58: 137.298 | P58: =IF(J58="","",N58/IF(J58=$B$3,Resumen!#REF!,VLOOKUP(J58,Graf_PowerBI!$A$4:$D$65,3,0))) -> 0.083531879 | Q58: =IF(J58="","",O58/IF(J58=$B$3,Resumen!#REF!,VLOOKUP(J58,Graf_PowerBI!$A$4:$D$65,4,0))) -> 0.172339 | S58: =IF(A58="","",P58+G58) -> 0.11585753
A59: 202306 | C59: 8.1750319 | D59: 530.16411 | E59: 64.851625 | F59: 59.037 | G59: =IF(A59="","",E59/IF(A59=$B$3,Resumen!#REF!,VLOOKUP(A59,Graf_PowerBI!$A$4:$D$65,3,0))) -> 0.044359056 | H59: =IF(A59="","",F59/IF(A59=$B$3,Resumen!#REF!,VLOOKUP(A59,Graf_PowerBI!$A$4:$D$65,4,0))) -> 0.075430933 | J59: 202306 | L59: 8.2826467 | M59: 948.32113 | N59: 114.49494 | O59: 126.783 | P59: =IF(J59="","",N59/IF(J59=$B$3,Resumen!#REF!,VLOOKUP(J59,Graf_PowerBI!$A$4:$D$65,3,0))) -> 0.078315499 | Q59: =IF(J59="","",O59/IF(J59=$B$3,Resumen!#REF!,VLOOKUP(J59,Graf_PowerBI!$A$4:$D$65,4,0))) -> 0.16198926 | S59: =IF(A59="","",P59+G59) -> 0.12267455
A60: 202307 | C60: 8.5223837 | D60: 430.37473 | E60: 50.499337 | F60: 46.092 | G60: =IF(A60="","",E60/IF(A60=$B$3,Resumen!#REF!,VLOOKUP(A60,Graf_PowerBI!$A$4:$D$65,3,0))) -> 0.032326128 | H60: =IF(A60="","",F60/IF(A60=$B$3,Resumen!#REF!,VLOOKUP(A60,Graf_PowerBI!$A$4:$D$65,4,0))) -> 0.060309398 | J60: 202307 | L60: 8.2926092 | M60: 1017.9777 | N60: 122.75723 | O60: 126.988 | P60: =IF(J60="","",N60/IF(J60=$B$3,Resumen!#REF!,VLOOKUP(J60,Graf_PowerBI!$A$4:$D$65,3,0))) -> 0.078580553 | Q60: =IF(J60="","",O60/IF(J60=$B$3,Resumen!#REF!,VLOOKUP(J60,Graf_PowerBI!$A$4:$D$65,4,0))) -> 0.16615833 | S60: =IF(A60="","",P60+G60) -> 0.11090668
A61: 202308 | C61: 8.4966354 | D61: 468.98733 | E61: 55.196829 | F61: 47.785 | G61: =IF(A61="","",E61/IF(A61=$B$3,Resumen!#REF!,VLOOKUP(A61,Graf_PowerBI!$A$4:$D$65,3,0))) -> 0.035735287 | H61: =IF(A61="","",F61/IF(A61=$B$3,Resumen!#REF!,VLOOKUP(A61,Graf_PowerBI!$A$4:$D$65,4,0))) -> 0.06287045 | J61: 202308 | L61: 8.3311122 | M61: 998.72113 | N61: 119.87849 | O61: 122.369 | P61: =IF(J61="","",N61/IF(J61=$B$3,Resumen!#REF!,VLOOKUP(J61,Graf_PowerBI!$A$4:$D$65,3,0))) -> 0.077611201 | Q61: =IF(J61="","",O61/IF(J61=$B$3,Resumen!#REF!,VLOOKUP(J61,Graf_PowerBI!$A$4:$D$65,4,0))) -> 0.16100019 | S61: =IF(A61="","",P61+G61) -> 0.11334649
A62: 202309 | C62: 8.3637072 | D62: 355.26212 | E62: 42.476633 | F62: 40.976 | G62: =IF(A62="","",E62/IF(A62=$B$3,Resumen!#REF!,VLOOKUP(A62,Graf_PowerBI!$A$4:$D$65,3,0))) -> 0.030440224 | H62: =IF(A62="","",F62/IF(A62=$B$3,Resumen!#REF!,VLOOKUP(A62,Graf_PowerBI!$A$4:$D$65,4,0))) -> 0.056537649 | J62: 202309 | L62: 8.3466658 | M62: 882.03555 | N62: 105.6752 | O62: 112.615 | P62: =IF(J62="","",N62/IF(J62=$B$3,Resumen!#REF!,VLOOKUP(J62,Graf_PowerBI!$A$4:$D$65,3,0))) -> 0.075730499 | Q62: =IF(J62="","",O62/IF(J62=$B$3,Resumen!#REF!,VLOOKUP(J62,Graf_PowerBI!$A$4:$D$65,4,0))) -> 0.15538333
A63: 202310 | C63: 8.4658783 | D63: 360.77463 | E63: 42.615145 | F63: 40.028 | G63: =IF(A63="","",E63/IF(A63=$B$3,Resumen!#REF!,VLOOKUP(A63,Graf_PowerBI!$A$4:$D$65,3,0))) -> 0.029698305 | H63: =IF(A63="","",F63/IF(A63=$B$3,Resumen!#REF!,VLOOKUP(A63,Graf_PowerBI!$A$4:$D$65,4,0))) -> 0.056045119 | J63: 202310 | L63: 9.0989286 | M63: 990.4989 | N63: 108.85885 | O63: 111.431 | P63: =IF(J63="","",N63/IF(J63=$B$3,Resumen!#REF!,VLOOKUP(J63,Graf_PowerBI!$A$4:$D$65,3,0))) -> 0.075863248 | Q63: =IF(J63="","",O63/IF(J63=$B$3,Resumen!#REF!,VLOOKUP(J63,Graf_PowerBI!$A$4:$D$65,4,0))) -> 0.15601988
A64: 202311 | C64: 8.1422017 | D64: 316.2541 | E64: 38.841349 | F64: 35.578 | G64: =IF(A64="","",E64/IF(A64=$B$3,Resumen!#REF!,VLOOKUP(A64,Graf_PowerBI!$A$4:$D$65,3,0))) -> 0.028332051 | H64: =IF(A64="","",F64/IF(A64=$B$3,Resumen!#REF!,VLOOKUP(A64,Graf_PowerBI!$A$4:$D$65,4,0))) -> 0.05256719 | J64: 202311 | L64: 9.3956646 | M64: 978.46435 | N64: 104.13998 | O64: 100.716 | P64: =IF(J64="","",N64/IF(J64=$B$3,Resumen!#REF!,VLOOKUP(J64,Graf_PowerBI!$A$4:$D$65,3,0))) -> 0.075962844 | Q64: =IF(J64="","",O64/IF(J64=$B$3,Resumen!#REF!,VLOOKUP(J64,Graf_PowerBI!$A$4:$D$65,4,0))) -> 0.14880986 | S64: =IF(A64="","",P64+G64) -> 0.1042949
A65: 202312 | C65: 8.3620292 | D65: 42.596542 | E65: 5.0940437 | F65: 7.553 | G65: =IF(A65="","",E65/IF(A65=$B$3,Resumen!#REF!,VLOOKUP(A65,Graf_PowerBI!$A$4:$D$65,3,0))) -> #REF! | H65: =IF(A65="","",F65/IF(A65=$B$3,Resumen!#REF!,VLOOKUP(A65,Graf_PowerBI!$A$4:$D$65,4,0))) -> #REF! | J65: 202312 | L65: 9.026562 | M65: 457.4068 | N65: 50.673424 | O65: 60.089 | P65: =IF(J65="","",N65/IF(J65=$B$3,Resumen!#REF!,VLOOKUP(J65,Graf_PowerBI!$A$4:$D$65,3,0))) -> #REF! | Q65: =IF(J65="","",O65/IF(J65=$B$3,Resumen!#REF!,VLOOKUP(J65,Graf_PowerBI!$A$4:$D$65,4,0))) -> #REF! | S65: =IF(A65="","",P65+G65) -> #REF!
G66: =IF(A66="","",E66/IF(A66=$B$3,Resumen!#REF!,VLOOKUP(A66,Graf_PowerBI!$A$4:$D$39,3,0))) | H66: =IF(A66="","",F66/IF(A66=$B$3,Resumen!#REF!,VLOOKUP(A66,Graf_PowerBI!$A$4:$D$39,4,0))) | P66: =IF(J66="","",N66/IF(J66=$B$3,Resumen!#REF!,VLOOKUP(J66,Graf_PowerBI!$A$4:$D$39,3,0))) | Q66: =IF(J66="","",O66/IF(J66=$B$3,Resumen!#REF!,VLOOKUP(J66,Graf_PowerBI!$A$4:$D$39,4,0))) | S66: =IF(A66="","",P66+G66)
G67: =IF(A67="","",E67/IF(A67=$B$3,Resumen!#REF!,VLOOKUP(A67,Graf_PowerBI!$A$4:$D$39,3,0))) | H67: =IF(A67="","",F67/IF(A67=$B$3,Resumen!#REF!,VLOOKUP(A67,Graf_PowerBI!$A$4:$D$39,4,0))) | P67: =IF(J67="","",N67/IF(J67=$B$3,Resumen!#REF!,VLOOKUP(J67,Graf_PowerBI!$A$4:$D$39,3,0))) | Q67: =IF(J67="","",O67/IF(J67=$B$3,Resumen!#REF!,VLOOKUP(J67,Graf_PowerBI!$A$4:$D$39,4,0))) | S67: =IF(A67="","",P67+G67)
G68: =IF(A68="","",E68/IF(A68=$B$3,Resumen!#REF!,VLOOKUP(A68,Graf_PowerBI!$A$4:$D$39,3,0))) | H68: =IF(A68="","",F68/IF(A68=$B$3,Resumen!#REF!,VLOOKUP(A68,Graf_PowerBI!$A$4:$D$39,4,0))) | P68: =IF(J68="","",N68/IF(J68=$B$3,Resumen!#REF!,VLOOKUP(J68,Graf_PowerBI!$A$4:$D$39,3,0))) | Q68: =IF(J68="","",O68/IF(J68=$B$3,Resumen!#REF!,VLOOKUP(J68,Graf_PowerBI!$A$4:$D$39,4,0))) | S68: =IF(A68="","",P68+G68)
G69: =IF(A69="","",E69/IF(A69=$B$3,Resumen!#REF!,VLOOKUP(A69,Graf_PowerBI!$A$4:$D$39,3,0))) | H69: =IF(A69="","",F69/IF(A69=$B$3,Resumen!#REF!,VLOOKUP(A69,Graf_PowerBI!$A$4:$D$39,4,0))) | P69: =IF(J69="","",N69/IF(J69=$B$3,Resumen!#REF!,VLOOKUP(J69,Graf_PowerBI!$A$4:$D$39,3,0))) | Q69: =IF(J69="","",O69/IF(J69=$B$3,Resumen!#REF!,VLOOKUP(J69,Graf_PowerBI!$A$4:$D$39,4,0))) | S69: =IF(A69="","",P69+G69)
G70: =IF(A70="","",E70/IF(A70=$B$3,Resumen!#REF!,VLOOKUP(A70,Graf_PowerBI!$A$4:$D$39,3,0))) | H70: =IF(A70="","",F70/IF(A70=$B$3,Resumen!#REF!,VLOOKUP(A70,Graf_PowerBI!$A$4:$D$39,4,0))) | P70: =IF(J70="","",N70/IF(J70=$B$3,Resumen!#REF!,VLOOKUP(J70,Graf_PowerBI!$A$4:$D$39,3,0))) | Q70: =IF(J70="","",O70/IF(J70=$B$3,Resumen!#REF!,VLOOKUP(J70,Graf_PowerBI!$A$4:$D$39,4,0))) | S70: =IF(A70="","",P70+G70)
G71: =IF(A71="","",E71/IF(A71=$B$3,Resumen!#REF!,VLOOKUP(A71,Graf_PowerBI!$A$4:$D$39,3,0))) | H71: =IF(A71="","",F71/IF(A71=$B$3,Resumen!#REF!,VLOOKUP(A71,Graf_PowerBI!$A$4:$D$39,4,0)))
G72: =IF(A72="","",E72/IF(A72=$B$3,Resumen!#REF!,VLOOKUP(A72,Graf_PowerBI!$A$4:$D$39,3,0))) | H72: =IF(A72="","",F72/IF(A72=$B$3,Resumen!#REF!,VLOOKUP(A72,Graf_PowerBI!$A$4:$D$39,4,0))) | P72: =IF(J72="","",N72/IF(J72=$B$3,Resumen!#REF!,VLOOKUP(J72,Graf_PowerBI!$A$4:$D$39,3,0))) | Q72: =IF(J72="","",O72/IF(J72=$B$3,Resumen!#REF!,VLOOKUP(J72,Graf_PowerBI!$A$4:$D$39,4,0))) | S72: =IF(A72="","",P72+G72)
G73: =IF(A73="","",E73/IF(A73=$B$3,Resumen!#REF!,VLOOKUP(A73,Graf_PowerBI!$A$4:$D$39,3,0))) | H73: =IF(A73="","",F73/IF(A73=$B$3,Resumen!#REF!,VLOOKUP(A73,Graf_PowerBI!$A$4:$D$39,4,0))) | P73: =IF(J73="","",N73/IF(J73=$B$3,Resumen!#REF!,VLOOKUP(J73,Graf_PowerBI!$A$4:$D$39,3,0))) | Q73: =IF(J73="","",O73/IF(J73=$B$3,Resumen!#REF!,VLOOKUP(J73,Graf_PowerBI!$A$4:$D$39,4,0))) | S73: =IF(A73="","",P73+G73)
G74: =IF(A74="","",E74/IF(A74=$B$3,Resumen!#REF!,VLOOKUP(A74,Graf_PowerBI!$A$4:$D$39,3,0))) | H74: =IF(A74="","",F74/IF(A74=$B$3,Resumen!#REF!,VLOOKUP(A74,Graf_PowerBI!$A$4:$D$39,4,0))) | P74: =IF(J74="","",N74/IF(J74=$B$3,Resumen!#REF!,VLOOKUP(J74,Graf_PowerBI!$A$4:$D$39,3,0))) | Q74: =IF(J74="","",O74/IF(J74=$B$3,Resumen!#REF!,VLOOKUP(J74,Graf_PowerBI!$A$4:$D$39,4,0))) | S74: =IF(A74="","",P74+G74)
G75: =IF(A75="","",E75/IF(A75=$B$3,Resumen!#REF!,VLOOKUP(A75,Graf_PowerBI!$A$4:$D$39,3,0))) | H75: =IF(A75="","",F75/IF(A75=$B$3,Resumen!#REF!,VLOOKUP(A75,Graf_PowerBI!$A$4:$D$39,4,0))) | P75: =IF(J75="","",N75/IF(J75=$B$3,Resumen!#REF!,VLOOKUP(J75,Graf_PowerBI!$A$4:$D$39,3,0))) | Q75: =IF(J75="","",O75/IF(J75=$B$3,Resumen!#REF!,VLOOKUP(J75,Graf_PowerBI!$A$4:$D$39,4,0))) | S75: =IF(A75="","",P75+G75)
G76: =IF(A76="","",E76/IF(A76=$B$3,Resumen!#REF!,VLOOKUP(A76,Graf_PowerBI!$A$4:$D$39,3,0))) | H76: =IF(A76="","",F76/IF(A76=$B$3,Resumen!#REF!,VLOOKUP(A76,Graf_PowerBI!$A$4:$D$39,4,0))) | P76: =IF(J76="","",N76/IF(J76=$B$3,Resumen!#REF!,VLOOKUP(J76,Graf_PowerBI!$A$4:$D$39,3,0))) | Q76: =IF(J76="","",O76/IF(J76=$B$3,Resumen!#REF!,VLOOKUP(J76,Graf_PowerBI!$A$4:$D$39,4,0))) | S76: =IF(A76="","",P76+G76)
G77: =IF(A77="","",E77/IF(A77=$B$3,Resumen!#REF!,VLOOKUP(A77,Graf_PowerBI!$A$4:$D$39,3,0))) | H77: =IF(A77="","",F77/IF(A77=$B$3,Resumen!#REF!,VLOOKUP(A77,Graf_PowerBI!$A$4:$D$39,4,0))) | P77: =IF(J77="","",N77/IF(J77=$B$3,Resumen!#REF!,VLOOKUP(J77,Graf_PowerBI!$A$4:$D$39,3,0))) | Q77: =IF(J77="","",O77/IF(J77=$B$3,Resumen!#REF!,VLOOKUP(J77,Graf_PowerBI!$A$4:$D$39,4,0))) | S77: =IF(A77="","",P77+G77)
G78: =IF(A78="","",E78/IF(A78=$B$3,Resumen!#REF!,VLOOKUP(A78,Graf_PowerBI!$A$4:$D$39,3,0))) | H78: =IF(A78="","",F78/IF(A78=$B$3,Resumen!#REF!,VLOOKUP(A78,Graf_PowerBI!$A$4:$D$39,4,0))) | P78: =IF(J78="","",N78/IF(J78=$B$3,Resumen!#REF!,VLOOKUP(J78,Graf_PowerBI!$A$4:$D$39,3,0))) | Q78: =IF(J78="","",O78/IF(J78=$B$3,Resumen!#REF!,VLOOKUP(J78,Graf_PowerBI!$A$4:$D$39,4,0))) | S78: =IF(A78="","",P78+G78)
G79: =IF(A79="","",E79/IF(A79=$B$3,Resumen!#REF!,VLOOKUP(A79,Graf_PowerBI!$A$4:$D$39,3,0))) | H79: =IF(A79="","",F79/IF(A79=$B$3,Resumen!#REF!,VLOOKUP(A79,Graf_PowerBI!$A$4:$D$39,4,0))) | P79: =IF(J79="","",N79/IF(J79=$B$3,Resumen!#REF!,VLOOKUP(J79,Graf_PowerBI!$A$4:$D$39,3,0))) | Q79: =IF(J79="","",O79/IF(J79=$B$3,Resumen!#REF!,VLOOKUP(J79,Graf_PowerBI!$A$4:$D$39,4,0))) | S79: =IF(A79="","",P79+G79)
G80: =IF(A80="","",E80/IF(A80=$B$3,Resumen!#REF!,VLOOKUP(A80,Graf_PowerBI!$A$4:$D$39,3,0))) | H80: =IF(A80="","",F80/IF(A80=$B$3,Resumen!#REF!,VLOOKUP(A80,Graf_PowerBI!$A$4:$D$39,4,0))) | P80: =IF(J80="","",N80/IF(J80=$B$3,Resumen!#REF!,VLOOKUP(J80,Graf_PowerBI!$A$4:$D$39,3,0))) | Q80: =IF(J80="","",O80/IF(J80=$B$3,Resumen!#REF!,VLOOKUP(J80,Graf_PowerBI!$A$4:$D$39,4,0))) | S80: =IF(A80="","",P80+G80)
G81: =IF(A81="","",E81/IF(A81=$B$3,Resumen!#REF!,VLOOKUP(A81,Graf_PowerBI!$A$4:$D$39,3,0))) | H81: =IF(A81="","",F81/IF(A81=$B$3,Resumen!#REF!,VLOOKUP(A81,Graf_PowerBI!$A$4:$D$39,4,0))) | P81: =IF(J81="","",N81/IF(J81=$B$3,Resumen!#REF!,VLOOKUP(J81,Graf_PowerBI!$A$4:$D$39,3,0))) | Q81: =IF(J81="","",O81/IF(J81=$B$3,Resumen!#REF!,VLOOKUP(J81,Graf_PowerBI!$A$4:$D$39,4,0))) | S81: =IF(A81="","",P81+G81)
G82: =IF(A82="","",E82/IF(A82=$B$3,Resumen!#REF!,VLOOKUP(A82,Graf_PowerBI!$A$4:$D$39,3,0))) | H82: =IF(A82="","",F82/IF(A82=$B$3,Resumen!#REF!,VLOOKUP(A82,Graf_PowerBI!$A$4:$D$39,4,0))) | P82: =IF(J82="","",N82/IF(J82=$B$3,Resumen!#REF!,VLOOKUP(J82,Graf_PowerBI!$A$4:$D$39,3,0))) | Q82: =IF(J82="","",O82/IF(J82=$B$3,Resumen!#REF!,VLOOKUP(J82,Graf_PowerBI!$A$4:$D$39,4,0))) | S82: =IF(A82="","",P82+G82)
G83: =IF(A83="","",E83/IF(A83=$B$3,Resumen!#REF!,VLOOKUP(A83,Graf_PowerBI!$A$4:$D$39,3,0))) | H83: =IF(A83="","",F83/IF(A83=$B$3,Resumen!#REF!,VLOOKUP(A83,Graf_PowerBI!$A$4:$D$39,4,0))) | P83: =IF(J83="","",N83/IF(J83=$B$3,Resumen!#REF!,VLOOKUP(J83,Graf_PowerBI!$A$4:$D$39,3,0))) | Q83: =IF(J83="","",O83/IF(J83=$B$3,Resumen!#REF!,VLOOKUP(J83,Graf_PowerBI!$A$4:$D$39,4,0))) | S83: =IF(A83="","",P83+G83)
... G251: =IF(A251="","",E251/IF(A251=$B$3,Resumen!#REF!,VLOOKUP(A251,Graf_PowerBI!$A$4:$D$39,3,0))) | H251: =IF(A251="","",F251/IF(A251=$B$3,Resumen!#REF!,VLOOKUP(A251,Graf_PowerBI!$A$4:$D$39,4,0))) | P251: =IF(J251="","",N251/IF(J251=$B$3,Resumen!#REF!,VLOOKUP(J251,Graf_PowerBI!$A$4:$D$39,3,0))) | Q251: =IF(J251="","",O251/IF(J251=$B$3,Resumen!#REF!,VLOOKUP(J251,Graf_PowerBI!$A$4:$D$39,4,0))) | S251: =IF(A251="","",P251+G251)

Sheet Resumen
A1: 1 Proyección Factu TC Abril 2026
B2: =+B25-D25 -> 144.22807 | C2: Plan 200 | D2: 1679.84 | E2: =+B5/D2 -> 1.0211677 | G2: =D2/30 -> 55.994667 | I2: =D5-B5 -> -137.01799
B3: Días del mes | C3: =+DAY(EOMONTH(B4,0)) -> 30 | J3: =+C5/E5-1 -> 0.17241634
A4: Indicador | B4: 46142 | C4: 46138 | D4: Ppto | E4: 45748 | F4: 46109 | G4: Cumplimiento Ppto | H4: Abril vs Mar | I4: 2026 vs 2025 | J4: =+B5-D5 -> 137.01799 | K4: Variación Semana vs Semana | N4: 1636.7987 | O4: =+N4/F5-1 -> -0.056875758
A5: Facturación (S/MM) | B5: =+C102 -> 1715.3983 | C5: 1660.972 | D5: =+Graf_PowerBI!T7 -> 1578.3803 | E5: =+Graf_PowerBI!C79 -> 1416.7083 | F5: 1735.507 | G5: =+B5/D5 -> 1.0868092 | H5: =+B5/F5-1 -> -0.011586621 | I5: =+B5/E5-1 -> 0.21083376 | J5: =+B5*1000000 -> 1.7153983e+09 | K5: =+B5-C5 -> 54.426283 | L5: =+B5/C5-1 -> 0.03276773 | M5: =+B5/J5 -> 1e-06 | N5: =+B5-J5 -> -1.7153966e+09
K6: =+B6-C6 -> 0 | M6: =+B6/J6 -> #DIV/0!
A7: Benefit | B7: =+$B$5*(#REF!/#REF!) -> #REF! | C7: #REF! | D7: 505.23891 | F7: #REF! | G7: =+B7/D7 -> #REF! | H7: =+B7/F7-1 -> #REF! | I7: =+B7/E7-1 -> #REF! | K7: =+B7-C7 -> #REF! | M7: =+B7/J7 -> #REF!
A8: Premia | B8: =+$B$5*(#REF!/#REF!) -> #REF! | C8: #REF! | D8: 72.830924 | F8: #REF! | G8: =+B8/D8 -> #REF! | H8: =+B8/F8-1 -> #REF! | I8: =+B8/E8-1 -> #REF! | K8: =+B8-C8 -> #REF! | M8: =+B8/J8 -> #REF!
A9: Access | B9: =+$B$5*(#REF!/#REF!) -> #REF! | C9: #REF! | D9: =D5-D7-#REF!-D8 -> #REF! | F9: #REF! | K9: =+B9-C9 -> #REF! | M9: =+B9/J9 -> #REF!
K10: =+B10-C10 -> 0 | M10: =+B10/J10 -> #DIV/0!
A11: Visa | B11: =+$B$5*(#REF!/#REF!) -> #REF! | C11: #REF! | D11: 427.20062 | F11: #REF! | K11: =+B11-C11 -> #REF! | M11: =+B11/J11 -> #REF!
A12: Amex | B12: =+$B$5*(#REF!/#REF!) -> #REF! | C12: #REF! | D12: 167.17039 | F12: #REF! | K12: =+B12-C12 -> #REF! | M12: =+B12/J12 -> #REF!
K13: =+B13-C13 -> 0 | M13: =+B13/J13 -> #DIV/0!
A14: Renta Alta | B14: =+$B$5*(#REF!/#REF!) -> #REF! | C14: #REF! | D14: 286.52584 | F14: #REF! | G14: =+B14/D14 -> #REF! | H14: =+B14/F14-1 -> #REF! | I14: =+B14/E14-1 -> #REF! | K14: =+B14-C14 -> #REF! | M14: =+B14/J14 -> #REF!
A15: Masivos | B15: =+$B$5*(#REF!/#REF!) -> #REF! | C15: #REF! | D15: =+D5-D14 -> 1291.8545 | F15: #REF! | G15: =+B15/D15 -> #REF! | H15: =+B15/F15-1 -> #REF! | I15: =+B15/E15-1 -> #REF! | K15: =+B15-C15 -> #REF! | M15: =+B15/J15 -> #REF!
K16: =+B16-C16 -> 0 | M16: =+B16/J16 -> #DIV/0!
A17: Cuentas con Consumo (miles) | B17: =Proyección_indicadores!I3/1000 -> 754.64 | C17: 756.1489 | D17: =+D33*D36 -> 741.40423 | E17: =+Graf_PowerBI!D79 -> 689.248 | F17: 748.408 | G17: =+B17/D17 -> 1.0178523 | H17: =+B17/F17-1 -> 0.0083270088 | I17: =+B17/E17-1 -> 0.094874414 | J17: =+B17*1000 -> 754640 | K17: =+B17-C17 -> -1.5089018 | L17: =+B17/C17-1 -> -0.0019955088 | M17: =+B17/J17 -> 0.001 | N17: =+B17-J17 -> -753885.36 | P17: =+C33-B33 -> 0.297
K18: =+B18-C18 -> 0 | M18: =+B18/J18 -> #DIV/0!
A19: Benefit | K19: =+B19-C19 -> 0 | M19: =+B19/J19 -> #DIV/0!
A20: Cashback | K20: =+B20-C20 -> 0 | M20: =+B20/J20 -> #DIV/0!
A21: Premia | K21: =+B21-C21 -> 0 | M21: =+B21/J21 -> #DIV/0!
K22: =+B22-C22 -> 0 | M22: =+B22/J22 -> #DIV/0!
A23: Goodbank | B23: =+B17*90.8% -> 685.21312 | C23: 686.5832 | D23: 502.02915 | F23: 679.55446 | H23: =+B23/F23-1 -> 0.0083270088 | K23: =+B23-C23 -> -1.3700828 | M23: =+B23/J23 -> #DIV/0!
A24: Badbank | B24: =+B17-B23 -> 69.42688 | C24: 69.565699 | D24: =+D17-D23 -> 239.37508 | F24: 68.853536 | H24: =+B24/F24-1 -> 0.0083270088 | K24: =+B24-C24 -> -0.13881896 | M24: =+B24/J24 -> #DIV/0!
A25: Consumo Medio (S/) | B25: =+B5/B17*1000 -> 2273.1346 | C25: 2196.6203 | D25: =+Graf_PowerBI!V7 -> 2128.9065 | E25: =+Graf_PowerBI!G79 -> 2055.4406 | F25: 2318.9316 | G25: =+B25/D25 -> 1.0677475 | H25: =+B25/F25-1 -> -0.019749178 | I25: =+B25/E25-1 -> 0.1059111 | K25: =+B25-C25 -> 76.51432 | L25: =+B25/C25-1 -> 0.034832748 | N25: =+B25-J25 -> 2273.1346
K26: =+B26-C26 -> 0 | M26: =+B26/J26 -> #DIV/0!
A27: Benefit | K27: =+B27-C27 -> 0 | M27: =+B27/J27 -> #DIV/0!
A28: Cashback | K28: =+B28-C28 -> 0 | M28: =+B28/J28 -> #DIV/0!
A29: Premia | K29: =+B29-C29 -> 0 | M29: =+B29/J29 -> #DIV/0!
K30: =+B30-C30 -> 0 | M30: =+B30/J30 -> #DIV/0!
A31: Goodbank | B31: =F31*1.052 -> 24472.954 | C31: 24472.954 | D31: 1153.0454 | F31: 23263.264 | H31: =+B31/F31-1 -> 0.052 | K31: =+B31-C31 -> 0 | M31: =+B31/J31 -> #DIV/0!
A32: Badbank | B32: =+#REF!*1000/B24 -> #REF! | C32: #REF! | D32: 766.26259 | F32: #REF! | H32: =+B32/F32-1 -> #REF! | K32: =+B32-C32 -> #REF! | M32: =+B32/J32 -> #REF!
A33: Parque (miles) | B33: =+F33+I61+I65-I62-I66 -> 878.929 | C33: 879.226 | D33: =+Graf_PowerBI!X7 -> 873.61228 | E33: =+Graf_PowerBI!E79 -> 816.013 | F33: 867.91 | G33: =+B33/D33 -> 1.0060859 | H33: =+B33/F33-1 -> 0.012696017 | I33: =+B33/E33-1 -> 0.077101713 | J33: =+B33*1000 -> 878929 | K33: =+B33-C33 -> -0.297 | L33: =+B33/C33-1 -> -0.00033779711 | M33: =+B33/J33 -> 0.001 | N33: =+B33-J33 -> -878050.07
A34: Goodbank | B34: =+F34+15 -> 1602.6319 | C34: 1602.6319 | D34: 761.35515 | F34: 1587.6319 | H34: =+B34/F34-1 -> 0.0094480337 | K34: =+B34-C34 -> 0
A35: Badbank | B35: =B33-B34 -> -723.70293 | C35: -723.40593 | D35: =+D33-D34 -> 112.25713 | F35: -719.72193 | H35: =+B35/F35-1 -> 0.0055313029 | K35: =+B35-C35 -> -0.297
A36: Actividad | B36: =+B17/B33 -> 0.8585904 | C36: 0.86001654 | D36: =+Graf_PowerBI!U7 -> 0.84866508 | E36: =+Graf_PowerBI!F79 -> 0.84465321 | F36: 0.86231061 | G36: =+B36/D36 -> 1.0116952 | H36: =+B36/F36-1 -> -0.0043142345 | I36: =+B36/E36-1 -> 0.016500485 | J36: Castigo para Cuentas/Trx | K36: =+B36-C36 -> -0.0014261412 | L36: =+B36/C36-1 -> -0.0016582718 | M36: =+J17/J33 -> 0.8585904 | N36: =+B36/M36 -> 1
A37: Goodbank | B37: =+B23/B34 -> 0.42755489 | C37: 0.42840979 | D37: 0.65938892 | F37: 0.42803023 | H37: =+B37/F37-1 -> -0.0011105325 | K37: =+B37-C37 -> -0.00085489548
A38: Badbank | B38: =+B24/B35 -> -0.095932843 | C38: -0.096164125 | D38: 0.65750728 | F38: -0.095666858 | H38: =+B38/F38-1 -> 0.0027803271 | K38: =+B38-C38 -> 0.00023128234
A39: Tx por cliente | B39: =+Proyección_indicadores!I4/Proyección_indicadores!I3 -> 12.813112 | C39: 12.243389 | D39: =+Graf_PowerBI!W7 -> 12.664218 | E39: =+Graf_PowerBI!H79 -> 12.189878 | F39: 12.978496 | G39: =+B39/D39 -> 1.0117571 | H39: =+B39/F39-1 -> -0.012742885 | I39: =+B39/E39-1 -> 0.051127194 | J39: 1
A40: Goodbank | B40: =B44/B23*1000 -> #REF! | C40: #REF! | D40: 6.5334271 | F40: #REF! | K40: =+B40-C40 -> #REF!
A41: Badbank | B41: =B45/B24*1000 -> #REF! | C41: #REF! | D41: 5.4735905 | F41: #REF! | K41: =+B41-C41 -> #REF!
A42: Gap diario vs. Ppto | B42: =+I102/31 -> 53.662664 | C42: 53.662664 | F42: 55.536311 | K42: =+B42-C42 -> 0
A43: Trx Total (MM) | B43: =+B39*B17/1000 -> 9.669287 | C43: 9.2578254 | D43: =+D39*D17/1000 -> 9.3893049 | E43: =+E39*E17/1000 -> 8.401849 | F43: 9.71321 | G43: =+B43/D43 -> 1.0298193 | H43: =+B43/F43-1 -> -0.004521986 | I43: =+B43/E43-1 -> 0.15085227 | J43: 1 | K43: =+B43-C43 -> 0.41146159
A44: Goodbank | B44: =B43*(#REF!/#REF!) -> #REF! | C44: #REF! | F44: #REF! | K44: =+B44-C44 -> #REF!
A45: Badbank | B45: =B43*(#REF!/#REF!) -> #REF! | C45: #REF! | F45: #REF! | K45: =+B45-C45 -> #REF!
A46: Facturación sin PdS (S/MM) | B46: 1167.2927 | C46: 1167.2927 | D46: =+D5-D48*D5 -> 1166.423 | E46: =+Graf_PowerBI!L79 -> 1167.2927 | F46: 1167.2927 | H46: =+B46/F46-1 -> 0 | I46: =+B46/E46-1 -> 0 | J46: =+IF(AND(DAY(B4)=C3,OR(J39<>100%,J43<>100%)),"ES CIERRE DE MES","") | K46: =+B46-C46 -> 0
A47: Ticket Promedio (S/) | B47: =+B25/B39 -> 177.40691 | C47: 179.41276 | D47: =+D25/D39 -> 168.10406 | E47: =+E25/E39 -> 168.61864 | F47: 178.67491 | G47: =+B47/D47 -> 1.0553398 | H47: =+B47/F47-1 -> -0.007096726 | I47: =+B47/E47-1 -> 0.052119194 | J47: =+IF(AND(DAY(B4)=C3,OR(J39<>100%,J43<>100%)),"RESTAURA EL CASTIGO AL 100%","") | K47: =+B47-C47 -> -2.0058539
A48: % Factu Pds | B48: =1-B46/B5 -> 0.31952089 | C48: 0.29722314 | D48: =+Graf_PowerBI!Z7 -> 0.261 | E48: =+Graf_PowerBI!N79 -> 0.17605292 | F48: 0.32740535 | J48: =+IF(AND(DAY(B4)=C3,AND(J39=100%,J43=100%)),"TODO CHECK","") -> TODO CHECK
A49: % Factu Pds Real | B49: 876.0867 | C49: 876.0867
B50: 34.7 | C50: =+B50/B5 -> 0.020228538
A51: Explicación de Gap: | B51: 758.14773
C52: 1552.4851 | E52: =+C52-A58 -> 1431.7374 | S52: Vs PPTO
B53: Parque | C53: Actividad | D53: CM | E53: Total | T53: Parque | U53: Actividad | V53: CM | W53: Total
A54: Parque | B54: =+(B33-C33)*C25*C36/1000 -> -0.56107154 | E54: =+SUM(B54:D54) -> -0.56107154 | S54: Parque | T54: =+(B33-D33)*D25*D36/1000 -> 9.6058782 | W54: =+SUM(T54:V54) -> 9.6058782
A55: Actividad | B55: =+(B33-C33)*(B36-C36)*C25/1000 -> 0.00093040912 | C55: =+C33*(B36-C36)*C25/1000 -> -2.7543431 | E55: =+SUM(B55:D55) -> -2.7534127 | S55: Actividad | T55: =+(B33-D33)*(B36-D36)*D25/1000 -> 0.11234281 | U55: =+D33*(B36-D36)*D25/1000 -> 18.459496 | W55: =+SUM(T55:V55) -> 18.571839
A56: Consumo Medio | B56: =+(B33-C33)*(B36-C36)*(B25-C25)/1000+(B33-C33)*C36*(B25-C25)/1000 -> -0.019511255 | C56: =+C33*(B36-C36)*(B25-C25)/1000 -> -0.095941338 | D56: =+C33*C36*(B25-C25)/1000 -> 57.856219 | E56: =+SUM(B56:D56) -> 57.740767 | S56: Consumo Medio | T56: =+(B33-D33)*(B36-D36)*(B25-D25)/1000+(B33-D33)*D36*(B25-D25)/1000 -> 0.65838506 | U56: =+D33*(B36-D36)*(B25-D25)/1000 -> 1.2505845 | V56: =+D33*D36*(B25-D25)/1000 -> 106.9313 | W56: =+SUM(T56:V56) -> 108.84027
E57: =+SUM(E54:E56) -> 54.426283 | W57: =+SUM(W54:W56) -> 137.01799
A58: =+'Fecha Proceso'!D39+'Fecha Proceso'!E39 -> 120.74769
B59: Facturación Procesada | D59: =+IF(C3=COUNT('Facturación_Procesada - Prop'!A2:A32),"","AJUSTAR CANTIDAD DE DIAS EN FACTURACION_PROCESADA") | H59: Parque Proyectado | J59: =+B33+J60 -> 872.989 | K59: 1479.8377
C60: =+IF(MONTH(B62)<>MONTH('Facturación_Procesada - Prop'!A2),"CORREGIR MES EN HOJA FACTU_PROCESADA","") | I60: =+B4 -> 46142 | J60: =+J61-I61 -> -5.94 | K60: 1.4798377e+09
B61: Fecha proyección | C61: Facturación Procesada | D61: Ppto | E61: Diff | H61: Entregas | I61: =27.6*0.9 -> 24.84 | J61: =21*0.9 -> 18.9
A62: 1486.795 | B62: 46118 | C62: 1651.0093 | D62: 1687.1085 | E62: -36.099183 | G62: =+C66/B5 -> 0.99925808 | H62: Cancelaciones | I62: 9.797
A63: =+A62-C66 -> -227.33058 | B63: =B62+7 -> 46125 | C63: 1637.5338 | D63: 1687.1085 | E63: -49.574711 | H63: Involuntarias | I63: 3.661 | J63: =1/2*1000000/1000000 -> 0.5
B64: =B63+7 -> 46132 | C64: 1709.583 | D64: 1687.1085 | E64: 22.474481 | H64: Voluntarias | I64: 6.136
A65: 1510.5936 | B65: =B64+7 -> 46139 | C65: 1705.0134 | D65: 1687.1085 | E65: 17.90497 | H65: Desbloqueos | I65: =13513/1000 -> 13.513 | AC65: Voluntarias
B66: Cierre | C66: =+'Facturación_Procesada - Prop'!E32 -> 1714.1256 | D66: 1687.1085 | E66: =+C66-D66 -> 27.017127 | H66: Bloqueos | I66: =17537/1000 -> 17.537
C67: ^ Este resultado es proyección/lo ideal | H67: =+C66-102+4 -> 1616.1256
C68: en caso alguien pida procesada es mejor usar el query | H68: =+H67/B5 -> 0.94212849
A69: 2 Control de meta diaria - Marzo 2026
A71: Fecha | B71: Día Sem | C71: Real | D71: Última proyección | E71: Presupuesto | F71: Gap PPTO | G71: Gap Meta | H71: Real Hasta el 9 | I71: Proyeccion | K71: TDT | L71: ORACLE
A72: 46113 | B72: =+TEXT(A72,"dddddd") -> miércoles | C72: 69.450155 | D72: 69.447655 | E72: 55.902833 | F72: =+C72-E72 -> 13.547321 | G72: =+C72-D72 -> 0.0025 | H72: 52.744676 | I72: 52.7726 | J72: =C72/D72-1 -> 3.5998336e-05 | K72: 65.7033 | L72: =+C72 -> 69.450155 | M72: 69.444111 | Q72: =+C72-O72 -> 69.450155 | R72: =+G72-C72 -> -69.447655 | U72: 71.2668 | V72: =+U72-C72 -> 1.8166454
A73: =+A72+1 -> 46114 | B73: =+TEXT(A73,"dddddd") -> jueves | C73: 54.145315 | D73: 54.145315 | E73: 59.257003 | F73: =+C73-E73 -> -5.1116883 | G73: =+C73-D73 -> 0 | H73: 69.032773 | I73: 69.1537 | J73: =C73/D73-1 -> 0 | K73: 52.2148 | L73: =+C73 -> 54.145315 | M73: 54.131711 | P73: =+SUM($C$72:C73)/SUM($E$72:E73) -> 1.0732515 | Q73: =+C73-O73 -> 54.145315 | R73: =+G73-C73 -> -54.145315 | S73: =+SUM(C$72:C73)/SUM(#REF!) -> #REF! | U73: 59.8883 | V73: =+U73-C73 -> 5.7429852
A74: =+A73+1 -> 46115 | B74: =+TEXT(A74,"dddddd") -> viernes | C74: 36.973361 | D74: 36.973356 | E74: 63.914228 | F74: =+C74-E74 -> -26.940867 | G74: =+C74-D74 -> 4.60313e-06 | H74: 62.446638 | I74: 62.5292 | J74: =C74/D74-1 -> 1.2449857e-07 | K74: 35.9553 | L74: =+C74 -> 36.973361 | M74: 36.95336 | P74: =+SUM($C$72:C74)/SUM($E$72:E74) -> 0.89666156 | Q74: =+C74-O74 -> 36.973361 | R74: =+G74-C74 -> -36.973356 | S74: =+SUM(C$72:C74)/SUM(#REF!) -> #REF! | U74: 58.6045 | V74: =+U74-C74 -> 21.631139
A75: =+A74+1 -> 46116 | B75: =+TEXT(A75,"dddddd") -> sábado | C75: 49.38905 | D75: 49.38905 | E75: 60.562 | F75: =+C75-E75 -> -11.17295 | G75: =+C75-D75 -> 0 | H75: 60.72719 | I75: 60.9382 | J75: =C75/D75-1 -> 0 | K75: 47.8997 | L75: =+C75 -> 49.38905 | M75: 49.378886 | P75: =+SUM($C$72:C75)/SUM($E$72:E75) -> 0.8761531 | Q75: =+C75-O75 -> 49.38905 | R75: =+G75-C75 -> -49.38905 | S75: =+SUM(C$72:C75)/SUM(#REF!) -> #REF! | U75: 56.4798 | V75: =+U75-C75 -> 7.0907503
A76: =+A75+1 -> 46117 | B76: =+TEXT(A76,"dddddd") -> domingo | C76: 39.947746 | D76: 39.947746 | E76: 54.772241 | F76: =+C76-E76 -> -14.824495 | G76: =+C76-D76 -> 0 | H76: 65.146543 | I76: 65.3622 | J76: =C76/D76-1 -> 0 | K76: 38.91 | L76: =+C76 -> 39.947746 | M76: 39.906691 | P76: =+SUM($C$72:C76)/SUM($E$72:E76) -> 0.84884027 | Q76: =+C76-O76 -> 39.947746 | R76: =+G76-C76 -> -39.947746 | S76: =+SUM(C$72:C76)/SUM(#REF!) -> #REF! | U76: 61.1864 | V76: =+U76-C76 -> 21.238654
A77: =+A76+1 -> 46118 | B77: =+TEXT(A77,"dddddd") -> lunes | C77: 61.585565 | D77: 61.585561 | E77: 56.518585 | F77: =+C77-E77 -> 5.0669801 | G77: =+C77-D77 -> 3.67759e-06 | H77: 58.757554 | I77: 58.8189 | J77: =C77/D77-1 -> 5.9715133e-08 | K77: 60.4536 | L77: =+C77 -> 61.585565 | M77: 61.535572 | P77: =+SUM($C$72:C77)/SUM($E$72:E77) -> 0.88762417 | Q77: =+C77-O77 -> 61.585565 | R77: =+G77-C77 -> -61.585561 | S77: =+SUM(C$72:C77)/SUM(#REF!) -> #REF! | U77: 52.7729 | V77: =+U77-C77 -> -8.812665
A78: =+A77+1 -> 46119 | B78: =+TEXT(A78,"dddddd") -> martes | C78: 63.431738 | D78: 63.431738 | E78: 52.28129 | F78: =+C78-E78 -> 11.150448 | G78: =+C78-D78 -> 0 | H78: 52.106237 | I78: 52.1398 | J78: =C78/D78-1 -> 0 | K78: 62.8021 | L78: =+C78 -> 63.431738 | M78: 63.139694 | P78: =+SUM($C$72:C78)/SUM($E$72:E78) -> 0.92984951 | Q78: =+C78-O78 -> 63.431738 | R78: =+G78-C78 -> -63.431738 | S78: =+SUM(C$72:C78)/SUM(#REF!) -> #REF! | U78: 41.6574 | V78: =+U78-C78 -> -21.774338
A79: =+A78+1 -> 46120 | B79: =+TEXT(A79,"dddddd") -> miércoles | C79: 55.969331 | D79: 55.967166 | E79: 33.5417 | F79: =+C79-E79 -> 22.427631 | G79: =+C79-D79 -> 0.0021647711 | H79: 40.353005 | I79: 40.3795 | J79: =C79/D79-1 -> 3.8679305e-05 | K79: 55.4758 | L79: =+C79 -> 55.969331 | M79: 55.305714 | P79: =+SUM($C$72:C79)/SUM($E$72:E79) -> 0.98658816 | Q79: =+C79-O79 -> 55.969331 | R79: =+G79-C79 -> -55.967166 | S79: =+SUM(C$72:C79)/SUM(#REF!) -> #REF! | U79: 44.517 | V79: =+U79-C79 -> -11.452331
A80: =+A79+1 -> 46121 | B80: =+TEXT(A80,"dddddd") -> jueves | C80: 52.036933 | D80: 52.036741 | E80: 57.248167 | F80: =+C80-E80 -> -5.2112338 | G80: =+C80-D80 -> 0.00019187 | H80: 54.839604 | I80: 54.9641 | J80: =C80/D80-1 -> 3.6872025e-06 | K80: 51.3482 | L80: =+C80 -> 52.036933 | P80: =+SUM($C$72:C80)/SUM($E$72:E80) -> 0.97759332 | Q80: =+C80-O80 -> 52.036933 | R80: =+G80-C80 -> -52.036741 | S80: =+SUM(C$72:C80)/SUM(#REF!) -> #REF! | U80: 45.4868 | V80: =+U80-C80 -> -6.5501329
A81: =+A80+1 -> 46122 | B81: =+TEXT(A81,"dddddd") -> viernes | C81: 57.908774 | D81: 57.908731 | E81: 58.904582 | F81: =+C81-E81 -> -0.99580814 | G81: =+C81-D81 -> 4.33e-05 | H81: 55.659553 | I81: 55.7491 | J81: =C81/D81-1 -> 7.4772835e-07 | K81: 57.5354 | L81: =+C81 -> 57.908774 | P81: =+SUM($C$72:C81)/SUM($E$72:E81) -> 0.97817941 | Q81: =+C81-O81 -> 57.908774 | R81: =+G81-C81 -> -57.908731 | S81: =+SUM(C$72:C81)/SUM(#REF!) -> #REF! | U81: 59.252 | V81: =+U81-C81 -> 1.3432258
A82: =+A81+1 -> 46123 | B82: =+TEXT(A82,"dddddd") -> sábado | C82: 52.59586 | D82: 52.595734 | E82: 59.455331 | F82: =+C82-E82 -> -6.859471 | G82: =+C82-D82 -> 0.00012621624 | H82: 55.415182 | I82: 55.5116 | J82: =C82/D82-1 -> 2.3997429e-06 | K82: 52.5701 | L82: =+C82 -> 52.59586 | P82: =+SUM($C$72:C82)/SUM($E$72:E82) -> 0.96909629 | Q82: =+C82-O82 -> 52.59586 | R82: =+G82-C82 -> -52.595734 | S82: =+SUM(C$72:C82)/SUM(#REF!) -> #REF! | U82: 55.6955 | V82: =+U82-C82 -> 3.0996401
A83: =+A82+1 -> 46124 | B83: =+TEXT(A83,"dddddd") -> domingo | C83: 33.390566 | D83: 33.390419 | E83: 56.502218 | F83: =+C83-E83 -> -23.111652 | G83: =+C83-D83 -> 0.00014633914 | H83: 58.12406 | I83: 58.1683 | J83: =C83/D83-1 -> 4.3826685e-06 | K83: 33.3354 | L83: =+C83 -> 33.390566 | P83: =+SUM($C$72:C83)/SUM($E$72:E83) -> 0.93715311 | Q83: =+C83-O83 -> 33.390566 | R83: =+G83-C83 -> -33.390419 | S83: =+SUM(C$72:C83)/SUM(#REF!) -> #REF! | U83: 60.2769 | V83: =+U83-C83 -> 26.886334
A84: =+A83+1 -> 46125 | B84: =+TEXT(A84,"dddddd") -> lunes | C84: 55.947468 | D84: 55.94737 | E84: 60.178497 | F84: =+C84-E84 -> -4.2310284 | G84: =+C84-D84 -> 9.892568e-05 | H84: 56.904081 | I84: 56.9896 | J84: =C84/D84-1 -> 1.7681918e-06 | K84: 55.6629 | L84: =+C84 -> 55.947468 | P84: =+SUM($C$72:C84)/SUM($E$72:E84) -> 0.93653723 | Q84: =+C84-O84 -> 55.947468 | R84: =+G84-C84 -> -55.94737 | S84: =+SUM(C$72:C84)/SUM(#REF!) -> #REF! | U84: 53.6467 | V84: =+U84-C84 -> -2.3007685
A85: =+A84+1 -> 46126 | B85: =+TEXT(A85,"dddddd") -> martes | C85: 57.332144 | D85: 57.329766 | E85: 52.407944 | F85: =+C85-E85 -> 4.9242002 | G85: =+C85-D85 -> 0.002378106 | H85: 52.886747 | I85: 52.9444 | J85: =C85/D85-1 -> 4.1481174e-05 | K85: 57.1158 | L85: =+C85 -> 57.332144 | P85: =+SUM($C$72:C85)/SUM($E$72:E85) -> 0.94709477 | Q85: =+C85-O85 -> 57.332144 | R85: =+G85-C85 -> -57.329766 | S85: =+SUM(C$72:C85)/SUM(#REF!) -> #REF! | U85: 44.8429 | V85: =+U85-C85 -> -12.489244
A86: =+A85+1 -> 46127 | B86: =+TEXT(A86,"dddddd") -> miércoles | C86: 64.122387 | D86: 64.120554 | E86: 32.423643 | F86: =+C86-E86 -> 31.698743 | G86: =+C86-D86 -> 0.0018322226 | H86: 41.166063 | I86: 41.2296 | J86: =C86/D86-1 -> 2.8574653e-05 | K86: 63.249 | L86: =+C86 -> 64.122387 | P86: =+SUM($C$72:C86)/SUM($E$72:E86) -> 0.98815061 | Q86: =+C86-O86 -> 64.122387 | R86: =+G86-C86 -> -64.120554 | S86: =+SUM(C$72:C86)/SUM(#REF!) -> #REF! | U86: 66.2358 | V86: =+U86-C86 -> 2.1134134
A87: =+A86+1 -> 46128 | B87: =+TEXT(A87,"dddddd") -> jueves | C87: 56.954019 | D87: 56.94807 | E87: 60.169534 | F87: =+C87-E87 -> -3.2155152 | G87: =+C87-D87 -> 0.0059489556 | H87: 56.71697 | I87: 56.8171 | J87: =C87/D87-1 -> 0.00010446281 | K87: 51.2774 | L87: =+C87 -> 56.954019 | P87: =+SUM($C$72:C87)/SUM($E$72:E87) -> 0.98528741 | Q87: =+C87-O87 -> 56.954019 | R87: =+G87-C87 -> -56.94807 | S87: =+SUM(C$72:C87)/SUM(#REF!) -> #REF! | U87: 58.1841 | V87: =+U87-C87 -> 1.2300811
A88: =+A87+1 -> 46129 | B88: =+TEXT(A88,"dddddd") -> viernes | C88: 54.782683 | D88: 54.782168 | E88: 56.511796 | F88: =+C88-E88 -> -1.7291136 | G88: =+C88-D88 -> 0.00051442794 | H88: 54.837065 | I88: 54.9226 | J88: =C88/D88-1 -> 9.3904268e-06 | K88: 16.5131 | L88: =+C88 -> 54.782683 | P88: =+SUM($C$72:C88)/SUM($E$72:E88) -> 0.98432274 | Q88: =+C88-O88 -> 54.782683 | R88: =+G88-C88 -> -54.782168 | S88: =+SUM(C$72:C88)/SUM(#REF!) -> #REF! | U88: 57.5552 | V88: =+U88-C88 -> 2.7725173
A89: =+A88+1 -> 46130 | B89: =+TEXT(A89,"dddddd") -> sábado | C89: 54.563294 | D89: 54.557621 | E89: 60.311114 | F89: =+C89-E89 -> -5.7478201 | G89: =+C89-D89 -> 0.0056727 | H89: 54.987827 | I89: 55.1446 | J89: =C89/D89-1 -> 0.00010397631 | L89: =+C89 -> 54.563294 | P89: =+SUM($C$72:C89)/SUM($E$72:E89) -> 0.97947615 | Q89: =+C89-O89 -> 54.563294 | R89: =+G89-C89 -> -54.557621 | S89: =+SUM(C$72:C89)/SUM(#REF!) -> #REF! | U89: 51.4624 | V89: =+U89-C89 -> -3.1008936
A90: =+A89+1 -> 46131 | B90: =+TEXT(A90,"dddddd") -> domingo | C90: 41.411148 | D90: 41.40467 | E90: 60.300052 | F90: =+C90-E90 -> -18.888905 | G90: =+C90-D90 -> 0.0064776733 | H90: 55.652709 | I90: 55.7688 | J90: =C90/D90-1 -> 0.00015644789 | L90: =+C90 -> 41.411148 | P90: =+SUM($C$72:C90)/SUM($E$72:E90) -> 0.96268397 | Q90: =+C90-O90 -> 41.411148 | R90: =+G90-C90 -> -41.40467 | S90: =+SUM(C$72:C90)/SUM(#REF!) -> #REF!
A91: =+A90+1 -> 46132 | B91: =+TEXT(A91,"dddddd") -> lunes | C91: 81.913181 | D91: 81.904764 | E91: 60.864969 | F91: =+C91-E91 -> 21.048212 | G91: =+C91-D91 -> 0.0084169631 | H91: 65.130427 | I91: 65.2193 | J91: =C91/D91-1 -> 0.00010276525 | L91: =+C91 -> 81.913181 | P91: =+SUM($C$72:C91)/SUM($E$72:E91) -> 0.98365417 | Q91: =+C91-O91 -> 81.913181 | R91: =+G91-C91 -> -81.904764 | S91: =+SUM(C$72:C91)/SUM(#REF!) -> #REF!
A92: =+A91+1 -> 46133 | B92: =+TEXT(A92,"dddddd") -> martes | C92: 72.335877 | D92: 72.315318 | E92: 55.816194 | F92: =+C92-E92 -> 16.519683 | G92: =+C92-D92 -> 0.020559224 | H92: 54.529519 | I92: 54.5717 | J92: =C92/D92-1 -> 0.00028429971 | L92: =+C92 -> 72.335877 | N92: 56.8398 | O92: =+N92-C92 -> -15.496077 | P92: =+SUM($C$72:C92)/SUM($E$72:E92) -> 0.99858086 | Q92: =+C92-O92 -> 87.831955 | R92: =+G92-C92 -> -72.315318 | S92: =+SUM(C$72:C92)/SUM(#REF!) -> #REF!
A93: =+A92+1 -> 46134 | B93: =+TEXT(A93,"dddddd") -> miércoles | C93: 69.080742 | D93: 69.068469 | E93: 36.336842 | F93: =+C93-E93 -> 32.7439 | G93: =+C93-D93 -> 0.01227344 | H93: 42.407571 | I93: 42.4164 | J93: =C93/D93-1 -> 0.00017769961 | L93: =+C93 -> 69.080742 | N93: 56.7137 | O93: =+N93-C93 -> -12.367042 | P93: =+SUM($C$72:C93)/SUM($E$72:E93) -> 1.0258155 | Q93: =+C93-O93 -> 81.447784
A94: =+A93+1 -> 46135 | B94: =+TEXT(A94,"dddddd") -> jueves | C94: 69.501411 | D94: 69.464991 | E94: 59.075111 | F94: =+C94-E94 -> 10.426299 | G94: =+C94-D94 -> 0.036419439 | H94: 62.011572 | I94: 62.0862 | J94: =C94/D94-1 -> 0.0005242848 | L94: =+C94 -> 69.501411 | N94: 54.5944 | O94: =+N94-C94 -> -14.907011 | P94: =+SUM($C$72:C94)/SUM($E$72:E94) -> 1.0328618 | Q94: =+C94-O94 -> 84.408421
A95: =+A94+1 -> 46136 | B95: =+TEXT(A95,"dddddd") -> viernes | C95: 60.136749 | D95: 60.080523 | E95: 57.519038 | F95: =+C95-E95 -> 2.617711 | G95: =+C95-D95 -> 0.056225599 | H95: 55.685257 | I95: 55.8661 | J95: =C95/D95-1 -> 0.00093583737 | L95: =+C95 -> 60.136749 | N95: 47.1778 | O95: =+N95-C95 -> -12.958949 | P95: =+SUM($C$72:C95)/SUM($E$72:E95) -> 1.0334126 | Q95: =+C95-O95 -> 73.095697
A96: =+A95+1 -> 46137 | B96: =+TEXT(A96,"dddddd") -> sábado | C96: 54.432364 | D96: 54.395382 | E96: 60.724905 | F96: =+C96-E96 -> -6.2925411 | G96: =+C96-D96 -> 0.036981999 | H96: 54.921143 | I96: 55.0848 | J96: =C96/D96-1 -> 0.00067987387 | L96: =+C96 -> 54.432364 | N96: 37.0171 | O96: =+N96-C96 -> -17.415264 | P96: =+SUM($C$72:C96)/SUM($E$72:E96) -> 1.0273891 | Q96: =+C96-O96 -> 71.847627
A97: =+A96+1 -> 46138 | B97: =+TEXT(A97,"dddddd") -> domingo | C97: 43.044571 | D97: 42.950657 | E97: 54.321944 | F97: =+C97-E97 -> -11.277373 | G97: =+C97-D97 -> 0.093913183 | H97: 52.497701 | I97: 52.6804 | J97: =C97/D97-1 -> 0.0021865366 | L97: =+C97 -> 43.044571 | N97: 50.9952 | O97: =+N97-C97 -> 7.9506294 | P97: =+SUM($C$72:C97)/SUM($E$72:E97) -> 1.0184986
A98: =+A97+1 -> 46139 | B98: =+TEXT(A98,"dddddd") -> lunes | C98: 57.04462 | D98: 57.375928 | E98: 50.799346 | F98: =+C98-E98 -> 6.2452742 | G98: =+C98-D98 -> -0.33130748 | H98: 60.987667 | I98: 61.1259 | J98: =C98/D98-1 -> -0.0057743289 | L98: =+C98 -> 57.04462 | N98: 53.7093 | O98: =+N98-C98 -> -3.3353203 | P98: =+SUM($C$72:C98)/SUM($E$72:E98) -> 1.0220675
A99: =+A98+1 -> 46140 | B99: =+TEXT(A99,"dddddd") -> martes | C99: 60.548066 | D99: 63.907266 | E99: 54.615203 | F99: =+C99-E99 -> 5.9328624 | G99: =+C99-D99 -> -3.3592003 | H99: =C99 -> 60.548066 | I99: 55.5249 | J99: =C99/D99-1 -> -0.052563668 | L99: =+C99 -> 60.548066 | N99: 55.278 | O99: =+N99-C99 -> -5.2700657 | P99: =+SUM($C$72:C99)/SUM($E$72:E99) -> 1.0251349
A100: =+A99+1 -> 46141 | B100: =+TEXT(A100,"dddddd") -> miércoles | C100: 62.084 | D100: 63.288224 | E100: 34.659757 | F100: =+C100-E100 -> 27.424243 | G100: =+C100-D100 -> -1.2042242 | H100: =C100 -> 62.084 | I100: 41.6421 | J100: =C100/D100-1 -> -0.019027619 | L100: =+C100 -> 62.084 | N100: 52.0879 | O100: =+N100-C100 -> -9.9961 | P100: =+SUM($C$72:C100)/SUM($E$72:E100) -> 1.0419844
A101: =+A100+1 -> 46142 | B101: =+TEXT(A101,"dddddd") -> jueves | C101: 73.339175 | D101: 74.09662 | E101: 57.02089 | F101: =+C101-E101 -> 16.318285 | G101: =+C101-D101 -> -0.75744486 | H101: =C101 -> 73.339175 | I101: 57.02089 | J101: =C101/D101-1 -> -0.010222394 | L101: =+C101 -> 73.339175 | P101: =+SUM($C$72:C101)/SUM($E$72:E101) -> 1.0505117
...

Sheet Hoja3
AL1: Psea a cuotas
C2: Factu total | Z2: Cuotas
AL3: codmes | AM3: dia | AN3: volumen | AS3: día | AT3: cuotas | AU3: trx | AV3: volumen | AX3: Suma de volumen | AY3: Etiquetas de columna
C4: dia | D4: Marca | E4: trx | F4: volumen | H4: Suma de volumen | I4: Etiquetas de columna | Z4: Dia | AA4: Cuotas | AB4: Trx | AC4: Volumen | AE4: Suma de Trx | AF4: Etiquetas de columna | AL4: 202603 | AM4: 46082 | AN4: 1209882.7 | AP4: =AN4/1000000 -> 1.2098827 | AQ4: 4336 | AS4: 46113 | AT4: N | AU4: 372731 | AV4: 65.508008 | AX4: Etiquetas de fila | AY4: N | AZ4: S | BA4: Total general
C5: 46113 | D5: Visa | E5: 269617 | F5: 48.856372 | H5: Etiquetas de fila | I5: Amex | J5: Visa | K5: Total general | Z5: 46082 | AA5: N | AB5: 348736 | AC5: 48.660338 | AE5: Etiquetas de fila | AF5: N | AG5: S | AH5: Total general | AJ5: Cuota | AL5: 202603 | AM5: 46083 | AN5: 1534260.7 | AP5: =AN5/1000000 -> 1.5342607 | AQ5: 4015 | AS5: 46113 | AT5: S | AU5: 5618 | AV5: 3.9395986 | AX5: 46113 | AY5: 65.508008 | AZ5: 3.9395986 | BA5: 69.447607
C6: 46113 | D6: Amex | E6: 108732 | F6: 20.591235 | H6: 46113 | I6: 20.591235 | J6: 48.856372 | K6: 69.447607 | L6: =I6/K6 -> 0.29650029 | M6: =J6/K6 -> 0.70349971 | N6: 69.447607 | O6: Día | P6: Amex | Q6: Visa | R6: total | S6: Peso Amex | T6: Peso Visa | U6: 69.447607 | V6: 69.447607 | Z6: 46082 | AA6: S | AB6: 6381 | AC6: 4.0843378 | AE6: 46082 | AF6: 348736 | AG6: 6381 | AH6: 355117 | AJ6: =AG6/AH6 -> 0.017968726 | AL6: 202603 | AM6: 46084 | AN6: 1306040.2 | AP6: =AN6/1000000 -> 1.3060402 | AQ6: 3318 | AS6: 46114 | AT6: S | AU6: 5978 | AV6: 3.6864762 | AX6: 46114 | AY6: 50.458839 | AZ6: 3.6864762 | BA6: 54.145315
C7: 46114 | D7: Amex | E7: 96560 | F7: 15.831768 | H7: 46114 | I7: 15.831768 | J7: 38.313547 | K7: 54.145315 | L7: =I7/K7 -> 0.29239405 | M7: =J7/K7 -> 0.70760595 | N7: 54.145315 | O7: 46135 | P7: 16.841603 | Q7: 49.342773 | R7: 66.184376 | S7: 0.25446493 | T7: 0.74553507 | U7: 54.145315 | V7: 54.145315 | Z7: 46083 | AA7: S | AB7: 6766 | AC7: 4.5848076 | AE7: 46083 | AF7: 356359 | AG7: 6766 | AH7: 363125 | AJ7: =AG7/AH7 -> 0.018632702 | AL7: 202603 | AM7: 46085 | AN7: 1247381.4 | AP7: =AN7/1000000 -> 1.2473814 | AQ7: 3293 | AS7: 46114 | AT7: N | AU7: 333036 | AV7: 50.458839 | AX7: 46115 | AY7: 34.712716 | AZ7: 2.2606396 | BA7: 36.973356
C8: 46114 | D8: Visa | E8: 242454 | F8: 38.313547 | H8: 46115 | I8: 10.908937 | J8: 26.064419 | K8: 36.973356 | L8: =I8/K8 -> 0.2950486 | M8: =J8/K8 -> 0.7049514 | N8: 36.973356 | O8: 46136 | P8: 8.5553347 | Q8: 41.951795 | R8: 50.50713 | S8: 0.16938865 | T8: 0.83061135 | U8: 36.973356 | V8: 36.973356 | Z8: 46083 | AA8: N | AB8: 356359 | AC8: 64.447965 | AE8: 46084 | AF8: 303970 | AG8: 6629 | AH8: 310599 | AJ8: =AG8/AH8 -> 0.021342631 | AL8: 202603 | AM8: 46086 | AN8: 1420996.3 | AP8: =AN8/1000000 -> 1.4209963 | AQ8: 3356 | AS8: 46115 | AT8: S | AU8: 4373 | AV8: 2.2606396 | AX8: 46116 | AY8: 45.59778 | AZ8: 3.7912694 | BA8: 49.38905
C9: 46115 | D9: Amex | E9: 77762 | F9: 10.908937 | H9: 46116 | I9: 14.379304 | J9: 35.009746 | K9: 49.38905 | L9: =I9/K9 -> 0.29114357 | M9: =J9/K9 -> 0.70885643 | N9: 49.38905 | U9: 49.38905 | V9: 49.38905 | Z9: 46084 | AA9: S | AB9: 6629 | AC9: 4.4661156 | AE9: 46085 | AF9: 299882 | AG9: 6305 | AH9: 306187 | AJ9: =AG9/AH9 -> 0.020591991 | AL9: 202603 | AM9: 46087 | AN9: 1231896.9 | AP9: =AN9/1000000 -> 1.2318969 | AQ9: 3330 | AS9: 46115 | AT9: N | AU9: 266868 | AV9: 34.712716 | AX9: 46117 | AY9: 37.067642 | AZ9: 2.8801047 | BA9: 39.947746
C10: 46115 | D10: Visa | E10: 193479 | F10: 26.064419 | H10: 46117 | I10: 12.012143 | J10: 27.935603 | K10: 39.947746 | L10: =I10/K10 -> 0.3006964 | M10: =J10/K10 -> 0.6993036 | N10: 39.947746 | U10: 39.947746 | V10: 39.947746 | Z10: 46084 | AA10: N | AB10: 303970 | AC10: 57.980523 | AE10: 46086 | AF10: 308326 | AG10: 6745 | AH10: 315071 | AJ10: =AG10/AH10 -> 0.021407873 | AL10: 202603 | AM10: 46088 | AN10: 1212079.1 | AP10: =AN10/1000000 -> 1.2120791 | AQ10: 4116 | AS10: 46116 | AT10: S | AU10: 6469 | AV10: 3.7912694 | AX10: 46118 | AY10: 57.900816 | AZ10: 3.6846001 | BA10: 61.585416
C11: 46116 | D11: Visa | E11: 235057 | F11: 35.009746 | H11: 46118 | I11: 18.792717 | J11: 42.7927 | K11: 61.585416 | L11: =I11/K11 -> 0.30514881 | M11: =J11/K11 -> 0.69485119 | N11: 61.585416 | U11: 61.585416 | V11: 61.585416 | Z11: 46085 | AA11: S | AB11: 6305 | AC11: 4.1975377 | AE11: 46087 | AF11: 315902 | AG11: 6249 | AH11: 322151 | AJ11: =AG11/AH11 -> 0.019397736 | AL11: 202603 | AM11: 46089 | AN11: 934277.1 | AP11: =AN11/1000000 -> 0.9342771 | AQ11: 3895 | AS11: 46116 | AT11: N | AU11: 320755 | AV11: 45.59778 | AX11: 46119 | AY11: 58.195981 | AZ11: 5.2357572 | BA11: 63.431738
C12: 46116 | D12: Amex | E12: 92167 | F12: 14.379304 | H12: 46119 | I12: 18.669131 | J12: 44.762608 | K12: 63.431738 | L12: =I12/K12 -> 0.29431844 | M12: =J12/K12 -> 0.70568156 | N12: 63.431738 | U12: 63.431738 | V12: 63.431738 | Z12: 46085 | AA12: N | AB12: 299882 | AC12: 56.529652 | AE12: 46088 | AF12: 330068 | AG12: 6842 | AH12: 336910 | AJ12: =AG12/AH12 -> 0.020308094 | AL12: 202603 | AM12: 46090 | AN12: 1102537.2 | AP12: =AN12/1000000 -> 1.1025372 | AQ12: 2935 | AS12: 46117 | AT12: N | AU12: 291418 | AV12: 37.067642 | AX12: 46120 | AY12: 51.621761 | AZ12: 4.3454051 | BA12: 55.967166
C13: 46117 | D13: Amex | E13: 84931 | F13: 12.012143 | H13: 46120 | I13: 16.480017 | J13: 39.487149 | K13: 55.967166 | L13: =I13/K13 -> 0.29445866 | M13: =J13/K13 -> 0.70554134 | N13: 55.967166 | U13: 55.967166 | V13: 55.967166 | Z13: 46086 | AA13: S | AB13: 6745 | AC13: 4.6121562 | AE13: 46089 | AF13: 301919 | AG13: 6186 | AH13: 308105 | AJ13: =AG13/AH13 -> 0.020077571 | AL13: 202603 | AM13: 46091 | AN13: 1174002 | AP13: =AN13/1000000 -> 1.174002 | AQ13: 2678 | AS13: 46117 | AT13: S | AU13: 5338 | AV13: 2.8801047 | AX13: 46121 | AY13: 48.386413 | AZ13: 3.6503282 | BA13: 52.036741
C14: 46117 | D14: Visa | E14: 211825 | F14: 27.935603 | H14: 46121 | I14: 15.14076 | J14: 36.895981 | K14: 52.036741 | L14: =I14/K14 -> 0.29096287 | M14: =J14/K14 -> 0.70903713 | N14: 52.036741 | U14: 52.036741 | V14: 52.036741 | Z14: 46086 | AA14: N | AB14: 308326 | AC14: 60.541525 | AE14: 46090 | AF14: 280500 | AG14: 5879 | AH14: 286379 | AJ14: =AG14/AH14 -> 0.02052874 | AL14: 202603 | AM14: 46092 | AN14: 1339922.2 | AP14: =AN14/1000000 -> 1.3399222 | AQ14: 3059 | AS14: 46118 | AT14: N | AU14: 332506 | AV14: 57.900816 | AX14: 46122 | AY14: 53.632045 | AZ14: 4.275362 | BA14: 57.907407
C15: 46118 | D15: Amex | E15: 95748 | F15: 18.792717 | H15: 46122 | I15: 17.289274 | J15: 40.618133 | K15: 57.907407 | L15: =I15/K15 -> 0.29856757 | M15: =J15/K15 -> 0.70143243 | N15: 57.907407 | U15: 57.907407 | V15: 57.907407 | Z15: 46087 | AA15: N | AB15: 315902 | AC15: 54.587262 | AE15: 46091 | AF15: 275421 | AG15: 5564 | AH15: 280985 | AJ15: =AG15/AH15 -> 0.019801769 | AL15: 202603 | AM15: 46093 | AN15: 1278386 | AP15: =AN15/1000000 -> 1.278386 | AQ15: 3230 | AS15: 46118 | AT15: S | AU15: 5274 | AV15: 3.6846001 | AX15: 46123 | AY15: 48.251312 | AZ15: 4.3444214 | BA15: 52.595734
C16: 46118 | D16: Visa | E16: 242032 | F16: 42.7927 | H16: 46123 | I16: 15.532558 | J16: 37.063176 | K16: 52.595734 | L16: =I16/K16 -> 0.29531973 | M16: =J16/K16 -> 0.70468027 | N16: 52.595734 | U16: 52.595734 | V16: 52.595734 | Z16: 46087 | AA16: S | AB16: 6249 | AC16: 4.1702916 | AE16: 46092 | AF16: 280717 | AG16: 5842 | AH16: 286559 | AJ16: =AG16/AH16 -> 0.020386727 | AL16: 202603 | AM16: 46094 | AN16: 1238936.8 | AP16: =AN16/1000000 -> 1.2389368 | AQ16: 3153 | AS16: 46119 | AT16: N | AU16: 289149 | AV16: 58.195981 | AX16: 46124 | AY16: 30.818127 | AZ16: 2.5691273 | BA16: 33.387254
C17: 46119 | D17: Amex | E17: 82804 | F17: 18.669131 | H17: 46124 | I17: 9.7399084 | J17: 23.647345 | K17: 33.387254 | L17: =I17/K17 -> 0.29172535 | M17: =J17/K17 -> 0.70827465 | N17: 33.387254 | U17: 33.387186 | V17: 33.387254 | Z17: 46088 | AA17: N | AB17: 330068 | AC17: 47.753465 | AE17: 46093 | AF17: 281832 | AG17: 5890 | AH17: 287722 | AJ17: =AG17/AH17 -> 0.020471149 | AL17: 202603 | AM17: 46095 | AN17: 1298524.2 | AP17: =AN17/1000000 -> 1.2985242 | AQ17: 4108 | AS17: 46119 | AT17: S | AU17: 6048 | AV17: 5.2357572 | AX17: 46125 | AY17: 52.138402 | AZ17: 3.8088286 | BA17: 55.947231
C18: 46119 | D18: Visa | E18: 212393 | F18: 44.762608 | H18: 46125 | I18: 15.667133 | J18: 40.280098 | K18: 55.947231 | L18: =I18/K18 -> 0.28003411 | M18: =J18/K18 -> 0.71996589 | N18: 55.947231 | U18: 55.937996 | V18: 55.947231 | Z18: 46088 | AA18: S | AB18: 6842 | AC18: 4.3528346 | AE18: 46094 | AF18: 312010 | AG18: 5397 | AH18: 317407 | AJ18: =AG18/AH18 -> 0.017003406 | AL18: 202603 | AM18: 46096 | AN18: 913914.97 | AP18: =AN18/1000000 -> 0.91391497 | AQ18: 3629 | AS18: 46120 | AT18: N | AU18: 288991 | AV18: 51.621761 | AX18: 46126 | AY18: 53.833463 | AZ18: 3.4949012 | BA18: 57.328365
C19: 46120 | D19: Visa | E19: 212216 | F19: 39.487149 | H19: 46126 | I19: 16.602013 | J19: 40.726351 | K19: 57.328365 | L19: =I19/K19 -> 0.28959509 | M19: =J19/K19 -> 0.71040491 | N19: 57.328365 | U19: 57.327798 | V19: 57.328365 | Z19: 46089 | AA19: S | AB19: 6186 | AC19: 3.3103857 | AE19: 46095 | AF19: 330336 | AG19: 6750 | AH19: 337086 | AJ19: =AG19/AH19 -> 0.020024563 | AL19: 202603 | AM19: 46097 | AN19: 1080136.3 | AP19: =AN19/1000000 -> 1.0801363 | AQ19: 2779 | AS19: 46120 | AT19: S | AU19: 5764 | AV19: 4.3454051 | AX19: 46127 | AY19: 59.862622 | AZ19: 4.257104 | BA19: 64.119726
C20: 46120 | D20: Amex | E20: 82539 | F20: 16.480017 | H20: 46127 | I20: 19.204316 | J20: 44.91541 | K20: 64.119726 | L20: =I20/K20 -> 0.29950715 | M20: =J20/K20 -> 0.70049285 | N20: 64.119726 | U20: 64.117895 | V20: 64.119726 | Z20: 46089 | AA20: N | AB20: 301919 | AC20: 37.042619 | AE20: 46096 | AF20: 296859 | AG20: 6281 | AH20: 303140 | AJ20: =AG20/AH20 -> 0.020719799 | AL20: 202603 | AM20: 46098 | AN20: 946681.19 | AP20: =AN20/1000000 -> 0.94668119 | AQ20: 2617 | AS20: 46121 | AT20: S | AU20: 5344 | AV20: 3.6503282 | AX20: 46128 | AY20: 52.863929 | AZ20: 4.0837614 | BA20: 56.947691
... C27: 46124 | D27: Visa | E27: 194835 | F27: 23.647345 | H27: 46134 | I27: 19.775121 | J27: 49.023698 | K27: 68.798819 | L27: =I27/K27 -> 0.28743401 | M27: =J27/K27 -> 0.71256599 | N27: 68.798819 | U27: 67.944455 | V27: 68.798819 | Z27: 46093 | AA27: N | AB27: 281832 | AC27: 54.038922 | AE27: 46103 | AF27: 308867 | AG27: 6798 | AH27: 315665 | AJ27: =AG27/AH27 -> 0.021535489 | AL27: 202603 | AM27: 46105 | AN27: 907827.46 | AP27: =AN27/1000000 -> 0.90782746 | AQ27: 2242 | AS27: 46124 | AT27: S | AU27: 4938 | AV27: 2.5691273 | AX27: 46135 | AY27: 57.366505 | AZ27: 8.8178708 | BA27: 66.184376
C28: 46124 | D28: Amex | E28: 77149 | F28: 9.7399084 | H28: 46135 | I28: 16.841603 | J28: 49.342773 | K28: 66.184376 | L28: =I28/K28 -> 0.25446493 | M28: =J28/K28 -> 0.74553507 | N28: =J28/AVERAGE(M6:M27) -> 69.750427 | O28: =N28*AVERAGE(L6:L27) -> 20.407654 | P28: =J28 -> 49.342773 | R28: =O28-I28 -> 3.5660513 | U28: 61.592236 | V28: 69.750427 | Z28: 46093 | AA28: S | AB28: 5890 | AC28: 4.0853156 | AE28: 46104 | AF28: 314193 | AG28: 6882 | AH28: 321075 | AJ28: =AG28/AH28 -> 0.021434244 | AL28: 202603 | AM28: 46106 | AN28: 795479.84 | AP28: =AN28/1000000 -> 0.79547984 | AQ28: 2052 | AS28: 46125 | AT28: N | AU28: 297815 | AV28: 52.138402 | AX28: 46136 | AY28: 46.773009 | AZ28: 3.7341215 | BA28: 50.50713
C29: 46125 | D29: Visa | E29: 218972 | F29: 40.280098 | H29: 46136 | I29: 8.5553347 | J29: 41.951795 | K29: 50.50713 | L29: =I29/K29 -> 0.16938865 | M29: =J29/K29 -> 0.83061135 | N29: =J29/AVERAGE(M7:M28) -> 59.142877 | O29: =N29*AVERAGE(L7:L28) -> 17.191081 | P29: =J29 -> 41.951795 | R29: =O29-I29 -> 8.6357468 | U29: 53.205826 | V29: 59.142877 | Z29: 46094 | AA29: N | AB29: 312010 | AC29: 53.200415 | AE29: 46105 | AF29: 278862 | AG29: 6160 | AH29: 285022 | AJ29: =AG29/AH29 -> 0.021612367 | AL29: 202603 | AM29: 46107 | AN29: 879281.29 | AP29: =AN29/1000000 -> 0.87928129 | AQ29: 2508 | AS29: 46125 | AT29: S | AU29: 5559 | AV29: 3.8088286 | AX29: Total general | AY29: 1242.3801 | AZ29: 109.08346 | BA29: 1351.4635
C30: 46125 | D30: Amex | E30: 84402 | F30: 15.667133 | H30: Total general | I30: 386.8596 | J30: 964.60392 | K30: 1351.4635 | N30: =SUM(N6:N29) -> 1363.6653 | R30: =SUM(R28:R29) -> 12.201798 | U30: 51.245969 | V30: 51.245969 | Z30: 46094 | AA30: S | AB30: 5397 | AC30: 3.7036823 | AE30: 46106 | AF30: 299466 | AG30: 6270 | AH30: 305736 | AJ30: =AG30/AH30 -> 0.020507889 | AL30: 202603 | AM30: 46108 | AN30: 1089117.1 | AP30: =AN30/1000000 -> 1.0891171 | AQ30: 2851 | AS30: 46126 | AT30: S | AU30: 5453 | AV30: 3.4949012
C31: 46126 | D31: Amex | E31: 85231 | F31: 16.602013 | U31: 41.22999 | V31: 41.22999 | Z31: 46095 | AA31: N | AB31: 330336 | AC31: 48.795834 | AE31: 46107 | AF31: 286686 | AG31: 6022 | AH31: 292708 | AJ31: =AG31/AH31 -> 0.020573404 | AL31: 202603 | AM31: 46109 | AN31: 1130981.1 | AP31: =AN31/1000000 -> 1.1309811 | AQ31: 3594 | AS31: 46126 | AT31: N | AU31: 297062 | AV31: 53.833463
C32: 46126 | D32: Visa | E32: 217284 | F32: 40.726351 | H32: Día | I32: Amex | J32: Visa | K32: total | L32: Peso Amex | M32: Peso Vsia | U32: 55.875928 | V32: 55.875928 | Z32: 46095 | AA32: S | AB32: 6750 | AC32: 4.0914825 | AE32: 46108 | AF32: 317642 | AG32: 6453 | AH32: 324095 | AJ32: =AG32/AH32 -> 0.019910829 | AL32: 202603 | AM32: 46110 | AN32: 743750.61 | AP32: =AN32/1000000 -> 0.74375061 | AQ32: 2914 | AS32: 46127 | AT32: N | AU32: 300975 | AV32: 59.862622
C33: 46127 | D33: Amex | E33: 86221 | F33: 19.204316 | H33: 46134 | I33: 19.775121 | J33: 49.023698 | K33: 68.798819 | L33: =I33/$K$6 -> 0.28474877 | M33: =J33/$K$6 -> 0.70590911 | U33: 58.507266 | V33: 58.507266 | Z33: 46096 | AA33: N | AB33: 296859 | AC33: 37.706396 | AE33: 46109 | AF33: 358355 | AG33: 7217 | AH33: 365572 | AJ33: =AG33/AH33 -> 0.019741665 | AL33: 202603 | AM33: 46111 | AN33: 1046804.6 | AP33: =AN33/1000000 -> 1.0468046 | AQ33: 2459 | AS33: 46127 | AT33: S | AU33: 6376 | AV33: 4.257104
C34: 46127 | D34: Visa | E34: 221130 | F34: 44.91541 | H34: 46135 | I34: 16.841603 | J34: 49.342773 | K34: 66.184376 | L34: =I34/$K$6 -> 0.24250804 | M34: =J34/$K$6 -> 0.71050358 | U34: 57.788224 | V34: 57.788224 | Z34: 46096 | AA34: S | AB34: 6281 | AC34: 3.4631623 | AE34: 46110 | AF34: 304676 | AG34: 6379 | AH34: 311055 | AJ34: =AG34/AH34 -> 0.020507627 | AL34: 202603 | AM34: 46112 | AN34: 1124632.6 | AP34: =AN34/1000000 -> 1.1246326 | AQ34: 2393 | AS34: 46128 | AT34: N | AU34: 301786 | AV34: 52.863929
C35: 46128 | D35: Visa | E35: 221502 | F35: 40.849398 | H35: 46136 | I35: 8.5553347 | J35: 41.951795 | K35: 50.50713 | L35: =I35/$K$6 -> 0.12319121 | M35: =J35/$K$6 -> 0.60407835 | U35: 63.29662 | V35: 63.29662 | Z35: 46097 | AA35: N | AB35: 285753 | AC35: 52.80358 | AE35: 46111 | AF35: 305172 | AG35: 6132 | AH35: 311304 | AJ35: =AG35/AH35 -> 0.019697787 | AS35: 46128 | AT35: S | AU35: 5992 | AV35: 4.0837614
C36: 46128 | D36: Amex | E36: 86276 | F36: 16.098293 | U36: =SUM(U6:U35) -> 1676.2151 | V36: =SUM(V6:V35) -> 1691.6093 | Z36: 46097 | AA36: S | AB36: 5821 | AC36: 3.9145047 | AE36: 46112 | AF36: 301614 | AG36: 5751 | AH36: 307365 | AJ36: =AG36/AH36 -> 0.018710653 | AQ36: =SUM(AQ4:AQ34) -> 96781 | AS36: 46129 | AT36: S | AU36: 5573 | AV36: 3.376028
C37: 46129 | D37: Amex | E37: 90016 | F37: 15.583323 | Z37: 46098 | AA37: N | AB37: 288071 | AC37: 50.79636 | AE37: Total general | AF37: 9519812 | AG37: 193701 | AH37: 9713513 | AS37: 46129 | AT37: N | AU37: 312734 | AV37: 51.406021
C38: 46129 | D38: Visa | E38: 228291 | F38: 39.198726 | Z38: 46098 | AA38: S | AB38: 5586 | AC38: 4.0414717 | AS38: 46130 | AT38: N | AU38: 352795 | AV38: 50.295489
C39: 46130 | D39: Visa | E39: 258171 | F39: 38.929422 | Z39: 46099 | AA39: S | AB39: 5754 | AC39: 3.8287983 | AS39: 46130 | AT39: S | AU39: 6997 | AV39: 4.2597164
C40: 46130 | D40: Amex | E40: 101621 | F40: 15.625784 | Z40: 46099 | AA40: N | AB40: 281223 | AC40: 51.159748 | AS40: 46131 | AT40: N | AU40: 312898 | AV40: 38.31767
C41: 46131 | D41: Amex | E41: 91362 | F41: 12.056113 | Z41: 46100 | AA41: S | AB41: 5638 | AC41: 3.9668852 | AS41: 46131 | AT41: S | AU41: 6085 | AV41: 3.0764532
C42: 46131 | D42: Visa | E42: 227621 | F42: 29.338011 | Z42: 46100 | AA42: N | AB42: 286713 | AC42: 51.694043 | AS42: 46132 | AT42: N | AU42: 355084 | AV42: 73.11119
C43: 46132 | D43: Amex | E43: 103324 | F43: 24.933292 | Z43: 46101 | AA43: N | AB43: 333390 | AC43: 61.113513 | AS43: 46132 | AT43: S | AU43: 9622 | AV43: 8.7532902
C44: 46132 | D44: Visa | E44: 261382 | F44: 56.931188 | Z44: 46101 | AA44: S | AB44: 5638 | AC44: 4.030317 | AS44: 46133 | AT44: N | AU44: 328922 | AV44: 64.068913
C45: 46133 | D45: Visa | E45: 243818 | F45: 51.670271 | Z45: 46102 | AA45: N | AB45: 346292 | AC45: 49.297533 | AS45: 46133 | AT45: S | AU45: 8938 | AV45: 8.1508851
C46: 46133 | D46: Amex | E46: 94042 | F46: 20.549527 | Z46: 46102 | AA46: S | AB46: 7494 | AC46: 5.2358751 | AS46: 46134 | AT46: S | AU46: 9333 | AV46: 8.6074123
C47: 46134 | D47: Visa | E47: 235845 | F47: 49.023698 | Z47: 46103 | AA47: S | AB47: 6798 | AC47: 4.1395313 | AS47: 46134 | AT47: N | AU47: 317238 | AV47: 60.191407
C48: 46134 | D48: Amex | E48: 90726 | F48: 19.775121 | Z48: 46103 | AA48: N | AB48: 308867 | AC48: 38.270862 | AS48: 46135 | AT48: S | AU48: 9397 | AV48: 8.8178708
C49: 46135 | D49: Amex | E49: 72988 | F49: 16.841603 | Z49: 46104 | AA49: S | AB49: 6882 | AC49: 5.2456201 | AS49: 46135 | AT49: N | AU49: 298067 | AV49: 57.366505
... C51: 46136 | D51: Amex | E51: 44177 | F51: 8.5553347 | Z51: 46105 | AA51: N | AB51: 278862 | AC51: 50.958627 | AS51: 46136 | AT51: N | AU51: 282983 | AV51: 46.773009
C52: 46136 | D52: Visa | E52: 244256 | F52: 41.951795 | Z52: 46105 | AA52: S | AB52: 6160 | AC52: 4.7340453
Z53: 46106 | AA53: S | AB53: 6270 | AC53: 4.8457542
Z54: 46106 | AA54: N | AB54: 299466 | AC54: 50.114492
Z55: 46107 | AA55: S | AB55: 6022 | AC55: 4.2613315
Z56: 46107 | AA56: N | AB56: 286686 | AC56: 48.273123
Z57: 46108 | AA57: N | AB57: 317642 | AC57: 56.21799
Z58: 46108 | AA58: S | AB58: 6453 | AC58: 5.0858631
Z59: 46109 | AA59: N | AB59: 358355 | AC59: 50.597498
Z60: 46109 | AA60: S | AB60: 7217 | AC60: 5.2356003
Z61: 46110 | AA61: N | AB61: 304676 | AC61: 37.980387
Z62: 46110 | AA62: S | AB62: 6379 | AC62: 4.2670438
Z63: 46111 | AA63: N | AB63: 305172 | AC63: 58.519331
Z64: 46111 | AA64: S | AB64: 6132 | AC64: 4.4975846
... Z66: 46112 | AA66: S | AB66: 5751 | AC66: 4.3631659

Sheet Res
M2: TC
B3: ="Facturación se proyecta en "&ROUND(Resumen!B5,0)& "M / YoY " & CONCATENATE(ROUND(Resumen!I5*100,1),"%") -> Facturación se proyecta en 1715M / YoY 21.1% | M3: -Facturación se proyecta en 1372M, -3M vs ppto(1375MM)/ YoY -5.4%
B4: ="Cuentas con consumo Res! "&ROUND(Resumen!B17,0)& "K / YoY " & CONCATENATE(ROUND(Resumen!I6*100,1),"%") -> Cuentas con consumo Res! 755K / YoY 0% | M4: -Cuentas con consumo 680K, -147K vs ppto(827K)
B5: ="Facturación se proyecta en "&ROUND(Resumen!B7,0)& "/ YoY " & CONCATENATE(ROUND(Resumen!I7*100,1),"%") -> #REF! | M5: -Consumo medio de 2016, +20 vs ppto(1996)
B6: ="Facturación se proyecta en "&ROUND(Resumen!#REF!,0)& "/ YoY " & CONCATENATE(ROUND(Resumen!#REF!*100,1),"%") -> #REF! | M6: -Actividad 86.1%, +10.8% vs ppto(76.4%)
B7: ="Facturación se proyecta en "&ROUND(Resumen!B8,0)& "/ YoY " & CONCATENATE(ROUND(Resumen!I8*100,1),"%") -> #REF! | M7: -Parque 790K, -3K vs ppto(793K)
M8: -Factu Digital 400M, -84M vs ppto(484M) / YoY +0.7%
M9: -Actividad Digital 49.5%, +9.7% vs ppto(39.8%)

Sheet Proyección_indicadores
A1: 30 | B1: fecha de proy | D1: 2024 | E1: 2025 | H1: 2026
B2: Corte Acum | C2: Cierre | D2: Factor | E2: Corte Acum | F2: Cierre | G2: Factor | H2: Corte Acum | I2: Cierre | J2: Factor | K2: Castigo | O2: Indicador
A3: Cuentas con Consumo | B3: =+VLOOKUP($A$1,$C$9:$G$38,2,0) -> 656118 | C3: =+D38 -> 656118 | D3: =+C3/B3 -> 1 | E3: =+VLOOKUP($A$1,$C$9:$G$38,3,0) -> 690265 | F3: =+E38 -> 690265 | G3: =+F3/E3 -> 1 | H3: =+VLOOKUP($A$1,$C$9:$G$38,5,0) -> 754640 | I3: =+H3*J3 -> 754640 | J3: 1 | K3: 1 | L3: =+Resumen!B36 -> 0.8585904 | M3: (Actividad) | O3: =+Resumen!B36 -> 0.8585904
A4: Transacciones | B4: =+VLOOKUP($A$1,$C$48:$G$77,2,0) -> 7899550 | C4: =+D77 -> 7899550 | D4: =+C4/B4 -> 1 | E4: =+VLOOKUP($A$1,$C$48:$G$77,3,0) -> 8401849 | F4: =+E77 -> 8401849 | G4: =+F4/E4 -> 1 | H4: =+VLOOKUP($A$1,$C$48:$G$77,5,0) -> 9669287 | I4: =+H4*J4 -> 9669287 | J4: =+AVERAGE(D4,G4)*K4 -> 1 | K4: =+Resumen!J43 -> 1 | L4: =+I4/I3 -> 12.813112 | M4: Trx promedio | O4: =+Resumen!B39 -> 12.813112
A8: Cuentas con Consumo | D8: 2024 | E8: 2025 | F8: 2026P | G8: 2026R | V8: Crecimiento 2025 | W8: 25-24
B9: =+G9-F9 -> 4117.4 | C9: 1 | D9: 179322 | E9: 170678 | F9: =+E9*1.2 -> 204813.6 | G9: 208931 | H9: =+E9/D9-1 -> -0.04820379 | I9: =+F9/E9-1 -> 0.2 | J9: =+G9/E9-1 -> 0.22412379 | K9: =+D9 -> 179322 | L9: =+K9/SUM($K$9:$K$38) -> 0.27330755 | M9: =+E9 -> 170678 | N9: =+M9/SUM($M$9:$M$38) -> 0.24726446 | O9: =L9 -> 0.27330755 | P9: =+D9 -> 179322 | Q9: =+P9/SUM($P$9:$P$38) -> 0.27330755 | R9: =+E9 -> 170678 | S9: =+R9/SUM($R$9:$R$38) -> 0.24726446 | T9: =+AVERAGE(Q9,S9) -> 0.260286 | V9: =+G9 -> 208931 | W9: =+V9-M9 -> 38253
B10: =+G10-F10 -> 861.05819 | C10: =+C9+1 -> 2 | D10: 267607 | E10: 254342 | F10: =+($F$38-$F$9)*T10+F9 -> 297692.94 | G10: 298554 | H10: =+E10/D10-1 -> -0.049568957 | I10: =+F10/E10-1 -> 0.1704435 | J10: =+G10/E10-1 -> 0.17382894 | K10: =+D10-D9 -> 88285 | L10: =+K10/SUM($K$10:$K$38) -> 0.18516305 | M10: =+E10-E9 -> 83664 | N10: =+M10/SUM($M$10:$M$38) -> 0.16102019 | O10: =L10 -> 0.18516305 | P10: =+D10-D9 -> 88285 | Q10: =+P10/SUM($P$10:$P$38) -> 0.18516305 | R10: =+E10-E9 -> 83664 | S10: =+R10/SUM($R$10:$R$38) -> 0.16102019 | T10: =+AVERAGE(Q10,S10) -> 0.17309162 | V10: =+G10-G9 -> 89623 | W10: =+V10-M10 -> 5959 | AF10: 354419 | AG10: =+AF10 -> 354419
B11: =+G11-F11 -> -43272.572 | C11: =+C10+1 -> 3 | D11: 319636 | E11: 342761 | F11: =+($F$38-$F$9)*T11+F10 -> 388041.57 | G11: 344769 | H11: =+E11/D11-1 -> 0.072347921 | I11: =+F11/E11-1 -> 0.13210538 | J11: =+G11/E11-1 -> 0.0058583094 | K11: =+D11-D10 -> 52029 | L11: =+K11/SUM($K$11:$K$38) -> 0.13391899 | M11: =+E11-E10 -> 88419 | N11: =+M11/SUM($M$11:$M$38) -> 0.20283169 | O11: =L11 -> 0.13391899 | P11: =+D11-D10 -> 52029 | Q11: =+P11/SUM($P$11:$P$38) -> 0.13391899 | R11: =+E11-E10 -> 88419 | S11: =+R11/SUM($R$11:$R$38) -> 0.20283169 | T11: =+AVERAGE(Q11,S11) -> 0.16837534 | V11: =+G11-G10 -> 46215 | W11: =+V11-M11 -> -42204 | AF11: 302529 | AG11: =+AG10+AF11 -> 656948
B12: =+G12-F12 -> -59771.8 | C12: =+C11+1 -> 4 | D12: 356463 | E12: 383022 | F12: =+($F$38-$F$9)*T12+F11 -> 448489.8 | G12: 388718 | H12: =+E12/D12-1 -> 0.074507032 | I12: =+F12/E12-1 -> 0.17092438 | J12: =+G12/E12-1 -> 0.014871208 | K12: =+D12-D11 -> 36827 | L12: =+K12/SUM($K$12:$K$38) -> 0.10944716 | M12: =+E12-E11 -> 40261 | N12: =+M12/SUM($M$12:$M$38) -> 0.11585766 | O12: =L12 -> 0.10944716 | P12: =+D12-D11 -> 36827 | Q12: =+P12/SUM($P$12:$P$38) -> 0.10944716 | R12: =+E12-E11 -> 40261 | S12: =+R12/SUM($R$12:$R$38) -> 0.11585766 | T12: =+AVERAGE(Q12,S12) -> 0.11265241 | V12: =+G12-G11 -> 43949 | W12: =+V12-M12 -> 3688 | AF12: 288178 | AG12: =+AG11+AF12 -> 945126
B13: =+G13-F13 -> -91645.605 | C13: =+C12+1 -> 5 | D13: 396851 | E13: 423462 | F13: =+($F$38-$F$9)*T13+F12 -> 511915.61 | G13: 420270 | H13: =+E13/D13-1 -> 0.067055394 | I13: =+F13/E13-1 -> 0.20888204 | J13: =+G13/E13-1 -> -0.0075378664 | K13: =+D13-D12 -> 40388 | L13: =+K13/SUM($K$12:$K$38) -> 0.12003019 | M13: =+E13-E12 -> 40440 | N13: =+M13/SUM($M$12:$M$38) -> 0.11637276 | O13: =L13 -> 0.12003019 | P13: =+D13-D12 -> 40388 | Q13: =+P13/SUM($P$12:$P$38) -> 0.12003019 | R13: =+E13-E12 -> 40440 | S13: =+R13/SUM($R$12:$R$38) -> 0.11637276 | T13: =+AVERAGE(Q13,S13) -> 0.11820148 | V13: =+G13-G12 -> 31552 | W13: =+V13-M13 -> -8888 | AF13: 305132 | AG13: =+AG12+AF13 -> 1250258
B14: =+G14-F14 -> -84416.942 | C14: =+C13+1 -> 6 | D14: 424283 | E14: 449639 | F14: =+($F$38-$F$9)*T14+F13 -> 553998.94 | G14: 469582 | H14: =+E14/D14-1 -> 0.059761998 | I14: =+F14/E14-1 -> 0.23209718 | J14: =+G14/E14-1 -> 0.044353359 | K14: =+D14-D13 -> 27432 | L14: =+K14/SUM($K$12:$K$38) -> 0.081525906 | M14: =+E14-E13 -> 26177 | N14: =+M14/SUM($M$12:$M$38) -> 0.075328629 | O14: =L14 -> 0.081525906 | P14: =+D14-D13 -> 27432 | Q14: =+P14/SUM($P$12:$P$38) -> 0.081525906 | R14: =+E14-E13 -> 26177 | S14: =+R14/SUM($R$12:$R$38) -> 0.075328629 | T14: =+AVERAGE(Q14,S14) -> 0.078427268 | V14: =+G14-G13 -> 49312 | W14: =+V14-M14 -> 23135 | AF14: 264596 | AG14: =+AG13+AF14 -> 1514854
B15: =+G15-F15 -> -90353.988 | C15: =+C14+1 -> 7 | D15: 442987 | E15: 474491 | F15: =+($F$38-$F$9)*T15+F14 -> 588099.99 | G15: 497746 | H15: =+E15/D15-1 -> 0.071117211 | I15: =+F15/E15-1 -> 0.23943339 | J15: =+G15/E15-1 -> 0.049010413 | K15: =+D15-D14 -> 18704 | L15: =+K15/SUM($K$12:$K$38) -> 0.055586926 | M15: =+E15-E14 -> 24852 | N15: =+M15/SUM($M$12:$M$38) -> 0.071515724 | O15: =L15 -> 0.055586926 | P15: =+D15-D14 -> 18704 | Q15: =+P15/SUM($P$12:$P$38) -> 0.055586926 | R15: =+E15-E14 -> 24852 | S15: =+R15/SUM($R$12:$R$38) -> 0.071515724 | T15: =+AVERAGE(Q15,S15) -> 0.063551325 | V15: =+G15-G14 -> 28164 | W15: =+V15-M15 -> 3312 | AF15: 296573 | AG15: =+AG14+AF15 -> 1811427
B16: =+G16-F16 -> -100006.35 | C16: =+C15+1 -> 8 | D16: 464336 | E16: 495029 | F16: =+($F$38-$F$9)*T16+F15 -> 620979.35 | G16: 520973 | H16: =+E16/D16-1 -> 0.066100841 | I16: =+F16/E16-1 -> 0.25443025 | J16: =+G16/E16-1 -> 0.052409051 | K16: =+D16-D15 -> 21349 | L16: =+K16/SUM($K$12:$K$38) -> 0.063447673 | M16: =+E16-E15 -> 20538 | N16: =+M16/SUM($M$12:$M$38) -> 0.059101478 | O16: =L16 -> 0.063447673 | P16: =+D16-D15 -> 21349 | Q16: =+P16/SUM($P$12:$P$38) -> 0.063447673 | R16: =+E16-E15 -> 20538 | S16: =+R16/SUM($R$12:$R$38) -> 0.059101478 | T16: =+AVERAGE(Q16,S16) -> 0.061274576 | V16: =+G16-G15 -> 23227 | W16: =+V16-M16 -> 2689 | AF16: 258835 | AG16: =+AG15+AF16 -> 2070262
B17: =+G17-F17 -> -106900.97 | C17: =+C16+1 -> 9 | D17: 484906 | E17: 508945 | F17: =+($F$38-$F$9)*T17+F16 -> 648124.97 | G17: 541224 | H17: =+E17/D17-1 -> 0.049574557 | I17: =+F17/E17-1 -> 0.2734676 | J17: =+G17/E17-1 -> 0.063423356 | K17: =+D17-D16 -> 20570 | L17: =+K17/SUM($K$12:$K$38) -> 0.061132542 | M17: =+E17-E16 -> 13916 | N17: =+M17/SUM($M$12:$M$38) -> 0.040045582 | O17: =L17 -> 0.061132542 | P17: =+D17-D16 -> 20570 | Q17: =+P17/SUM($P$12:$P$38) -> 0.061132542 | R17: =+E17-E16 -> 13916 | S17: =+R17/SUM($R$12:$R$38) -> 0.040045582 | T17: =+AVERAGE(Q17,S17) -> 0.050589062 | V17: =+G17-G16 -> 20251 | W17: =+V17-M17 -> 6335 | AF17: 298925 | AG17: =+AG16+AF17 -> 2369187
B18: =+G18-F18 -> -138211.09 | C18: =+C17+1 -> 10 | D18: 499075 | E18: 528368 | F18: =+($F$38-$F$9)*T18+F17 -> 699068.09 | G18: 560857 | H18: =+E18/D18-1 -> 0.058694585 | I18: =+F18/E18-1 -> 0.32307046 | J18: =+G18/E18-1 -> 0.061489341 | K18: =+D18-D17 -> 14169 | L18: =+K18/SUM($K$18:$K$38) -> 0.08275705 | M18: =+E18-E17 -> 19423 | N18: =+M18/SUM($M$18:$M$38) -> 0.10712001 | O18: =L18 -> 0.08275705 | P18: =+D18-D17 -> 14169 | Q18: =+P18/SUM($P$18:$P$38) -> 0.08275705 | R18: =+E18-E17 -> 19423 | S18: =+R18/SUM($R$18:$R$38) -> 0.10712001 | T18: =+AVERAGE(Q18,S18) -> 0.094938529 | V18: =+G18-G17 -> 19633 | W18: =+V18-M18 -> 210 | AF18: 274484 | AG18: =+AG17+AF18 -> 2643671
B19: =+G19-F19 -> -168030.87 | C19: =+C18+1 -> 11 | D19: 512543 | E19: 544241 | F19: =+($F$38-$F$9)*T19+F18 -> 743659.87 | G19: 575629 | H19: =+E19/D19-1 -> 0.061844567 | I19: =+F19/E19-1 -> 0.36641647 | J19: =+G19/E19-1 -> 0.057672979 | K19: =+D19-D18 -> 13468 | L19: =+K19/SUM($K$18:$K$38) -> 0.078662711 | M19: =+E19-E18 -> 15873 | N19: =+M19/SUM($M$18:$M$38) -> 0.087541363 | O19: =L19 -> 0.078662711 | P19: =+D19-D18 -> 13468 | Q19: =+P19/SUM($P$18:$P$38) -> 0.078662711 | R19: =+E19-E18 -> 15873 | S19: =+R19/SUM($R$18:$R$38) -> 0.087541363 | T19: =+AVERAGE(Q19,S19) -> 0.083102037 | V19: =+G19-G18 -> 14772 | W19: =+V19-M19 -> -1101 | AF19: 282947 | AG19: =+AG18+AF19 -> 2926618
B20: =+G20-F20 -> -198438.37 | C20: =+C19+1 -> 12 | D20: 525434 | E20: 558519 | F20: =+($F$38-$F$9)*T20+F19 -> 784987.37 | G20: 586549 | H20: =+E20/D20-1 -> 0.062966995 | I20: =+F20/E20-1 -> 0.40548016 | J20: =+G20/E20-1 -> 0.050186296 | K20: =+D20-D19 -> 12891 | L20: =+K20/SUM($K$18:$K$38) -> 0.07529262 | M20: =+E20-E19 -> 14278 | N20: =+M20/SUM($M$18:$M$38) -> 0.078744761 | O20: =L20 -> 0.07529262 | P20: =+D20-D19 -> 12891 | Q20: =+P20/SUM($P$18:$P$38) -> 0.07529262 | R20: =+E20-E19 -> 14278 | S20: =+R20/SUM($R$18:$R$38) -> 0.078744761 | T20: =+AVERAGE(Q20,S20) -> 0.07701869 | V20: =+G20-G19 -> 10920 | W20: =+V20-M20 -> -3358 | AF20: 309805 | AG20: =+AG19+AF20 -> 3236423
A21: 609128.03 | B21: =+G21-F21 -> -228958.05 | C21: =+C20+1 -> 13 | D21: 536631 | E21: 570893 | F21: =+($F$38-$F$9)*T21+F20 -> 833174.05 | G21: 604216 | H21: =+E21/D21-1 -> 0.063846479 | I21: =+F21/E21-1 -> 0.45942243 | J21: =+G21/E21-1 -> 0.058369957 | K21: =+D21-D20 -> 11197 | L21: =+K21/SUM($K$21:$K$38) -> 0.085679961 | M21: =+E21-E20 -> 12374 | N21: =+M21/SUM($M$21:$M$38) -> 0.093923155 | O21: =L21 -> 0.085679961 | P21: =+D21-D20 -> 11197 | Q21: =+P21/SUM($P$21:$P$38)+Q42 -> 0.085679961 | R21: =+E21-E20 -> 12374 | S21: =+R21/SUM($R$21:$R$38) -> 0.093923155 | T21: =+AVERAGE(Q21,S21) -> 0.089801558 | V21: =+G21-G20 -> 17667 | W21: =+V21-M21 -> 5293 | AF21: 258204 | AG21: =+AG20+AF21 -> 3494627
